Workbook

Sheet Cover
B2: Air Asia
B4: Modelled by Peter Hopkinson
B5: =DATE(2026, 10, 3) -> 46298

Sheet Assumptions
B2: Air Asia Group
B3: Forecast Assumptions | 2026F-2030F
B5: SECTION A - STATIC ASSUMPTIONS
B7: A1. Fleet and Operating Parameters
B9: Fleet Capacity | D9: 247
B10: Operating days | D10: 365
B11: Flights per day | D11: 3
B12: Average Aircraft Size | D12: 320
B13: Average Flight Distance | D13: 1200
B14: Aircraft Capacity | D14: 0.975
B16: A2. Aircraft Leases & ROU Assets
B18: Initial New Aircraft Cost | D18: 20
B19: Term | D19: 10
B20: Discount Rate | D20: 0.06
B22: A3. PP&E, Intangibles, Lease & Maintenance
B24: PP&E useful life | D24: 7
B25: Finite Intangible asset life | D25: 10
B26: Lease liabilities average contract life | D26: 5.6
B27: Intangible Additions - % of Revenue | D27: 0.0075
B28: Maintenance provision per aircraft | D28: 0.75
B29: Maintenance provision utilization | D29: 0.035
B31: A4. Financial Policy & Liquidity
B33: Target dividend payout ratio | D33: 0.3
B34: Share buyback ratio | D34: 0
B35: Minimum cash requirement | D35: 1500
B36: Minimum net income requirememt | D36: 250
B37: Opening share count | D37: 3360826386
B38: Current share price | D38: 0.475
B40: SECTION B - TEMPORAL / FORECAST ASSUMPTIONS
D43: 2024 | E43: 2025 | F43: =E43+1 -> 2026 | G43: =F43+1 -> 2027 | H43: =G43+1 -> 2028 | I43: =H43+1 -> 2029 | J43: =I43+1 -> 2030
D44: PF = Pro forma | J44: F = Forecast
B46: B1. Macro Assumptions
B48: Inflation | F48: 0.045 | G48: 0.04 | H48: 0.035 | I48: 0.03 | J48: 0.03
B49: Southeast Asia real GDP growth | C49: % | D49: 0.048 | E49: 0.045 | F49: 0.047 | G49: 0.049 | H49: 0.045 | I49: 0.045 | J49: 0.045
B50: Fuel Prices | E50: 102 | F50: 150 | G50: 110 | H50: 100 | I50: 100 | J50: 100
B51: Hedged Fuel Spread | F51: 5 | G51: 5 | H51: 5 | I51: 5 | J51: 5
B52: Hedged Fuel Price | F52: =E50+F51 -> 107 | G52: =F50+5 -> 155 | H52: =G50+5 -> 115 | I52: =H50+5 -> 105 | J52: =I50+5 -> 105
B53: Hedge Ratio | F53: 0.5 | G53: 0.5 | H53: 0.5 | I53: 0.5 | J53: 0.5
B55: B2. Passenger demand and Capacity Constraints
B57: Passenger growth | C57: % | F57: 0.06 | G57: 0.06 | H57: 0.06 | I57: 0.06 | J57: 0.06
B58: Aircraft returned/retired | F58: 4 | G58: 4 | H58: 4 | I58: 4 | J58: 4
B59: Aircraft additions | F59: 10 | G59: 18 | H59: 13 | I59: 35 | J59: 46
B60: Capacity per aircraft | E60: 341200 | F60: 341200 | G60: 341200 | H60: 341200 | I60: 341200 | J60: 341200
B61: Fuel efficiency improvements | F61: 0.01 | G61: 0.01 | H61: 0.01 | I61: 0.01 | J61: 0.01
B62: Initial New Aircraft Deposit | C62: RMm | F62: 25 | G62: =F62*(1+G48) -> 26 | H62: =G62*(1+H48) -> 26.91 | I62: =H62*(1+I48) -> 27.7173 | J62: =I62*(1+J48) -> 28.548819
B63: Capital expenditure growth rate | C63: % | F63: 0.05 | G63: 0.05 | H63: 0.05 | I63: 0.05 | J63: 0.05
B65: B3. Capital Management
B67: Borrowing cost | C67: % | F67: 0.05 | G67: 0.05 | H67: 0.05 | I67: 0.05 | J67: 0.05
B68: Debentures cost | C68: % | F68: 0.05 | G68: 0.05 | H68: 0.05 | I68: 0.05 | J68: 0.05
B69: Interest earned on cash | C69: % | F69: 0.03 | G69: 0.03 | H69: 0.03 | I69: 0.03 | J69: 0.03
B70: Borrowing issuance | C70: RMm | F70: 0 | G70: 0 | H70: 0 | I70: 0 | J70: 0
B71: Debenture issuance | C71: RMm | F71: 0 | G71: 0 | H71: 0 | I71: 0 | J71: 0
B72: Borrowing redemption | C72: RMm | F72: 0 | G72: 0 | H72: 0 | I72: 0 | J72: 0
B73: Debenture redemtpion | C73: RMm | F73: 0 | G73: 0 | H73: 0 | I73: 0 | J73: 0
B74: Share issuance | C74: RMm | F74: 0 | G74: 0 | H74: 0 | I74: 0 | J74: 0
B76: B4. Tax Rates
B78: Statuatory Tax Rate | C78: % | F78: 0.24 | G78: 0.24 | H78: 0.24 | I78: 0.24 | J78: 0.24
B79: Cash Tax Paid | C79: % | F79: 0.02 | G79: 0.04 | H79: 0.09 | I79: 0.14 | J79: 0.2

Sheet Model
B2: Air Asia Group
B3: Financial Statements - Income Statement
B5: RM millions, unless otherwise stated
E7: 2024 | F7: 2025 | G7: =F7+1 -> 2026 | H7: =G7+1 -> 2027 | I7: =H7+1 -> 2028 | J7: =I7+1 -> 2029 | K7: =J7+1 -> 2030
E8: PF = Pro forma | K8: F = Forecast
B10: Revenue | E10: 22181 | F10: 22221 | G10: =G231 -> 24370.593 | H10: =H231 -> 26600.522 | I10: =I231 -> 28895.027 | J10: =J231 -> 31235.842 | K10: =K231 -> 33766.403
B11: Staff cost | E11: -2376 | F11: -2455 | G11: =-G290 -> -2632.8187 | H11: =-H290 -> -2867.8324 | I11: =-I290 -> -3060.6776 | J11: =-J290 -> -3468.9197 | K11: =-K290 -> -4013.9345
B12: Aircraft fuel expenses | E12: -8610 | F12: -7691 | G12: =-G281 -> -10854.289 | H12: =-H281 -> -11651.803 | I12: =-I281 -> -9863.5541 | J12: =-J281 -> -10098.143 | K12: =-K281 -> -11360.41
B13: Maintenance and overhaul | E13: -4458 | F13: -3444 | G13: =-G292 -> -3547.9823 | H13: =-H292 -> -3841.4376 | I13: =-I292 -> -4148.4117 | J13: =-J292 -> -4587.8767 | K13: =-K292 -> -5316.2021
B14: User charges | E14: -3666 | F14: -3206 | G14: =-G296 -> -3485.5984 | H14: =-H296 -> -3773.8939 | I14: =-I296 -> -4075.4705 | J14: =-J296 -> -4507.2084 | K14: =-K296 -> -5222.7277
B15: Other operating expenses | E15: -1581 | F15: -1044 | G15: =-G301 -> -1144.9934 | H15: =-H301 -> -1249.7613 | I15: =-I301 -> -1357.563 | J15: =-J301 -> -1467.5405 | K15: =-K301 -> -1586.4329
B16: Operating expenses | E16: =SUM(E11:E15) -> -20691 | F16: =SUM(F11:F15) -> -17840 | G16: =SUM(G11:G15) -> -21665.682 | H16: =SUM(H11:H15) -> -23384.728 | I16: =SUM(I11:I15) -> -22505.677 | J16: =SUM(J11:J15) -> -24129.688 | K16: =SUM(K11:K15) -> -27499.708
B17: Other income | E17: 1236 | F17: 179 | G17: =F17 -> 179 | H17: =G17 -> 179 | I17: =H17 -> 179 | J17: =I17 -> 179 | K17: =J17 -> 179
B18: EBITDA | E18: =E10+E16+E17 -> 2726 | F18: =F10+F16+F17 -> 4560 | G18: =G10+G16+G17 -> 2883.9107 | H18: =H10+H16+H17 -> 3394.7938 | I18: =I10+I16+I17 -> 6568.3499 | J18: =J10+J16+J17 -> 7285.1537 | K18: =K10+K16+K17 -> 6445.6951
B19: EBITDA margin | E19: =E18/E10 -> 0.12289798 | F19: =F18/F10 -> 0.20521129 | G19: =G18/G10 -> 0.11833568 | H19: =H18/H10 -> 0.12762132 | I19: =I18/I10 -> 0.22731766 | J19: =J18/J10 -> 0.23323059 | K19: =K18/K10 -> 0.19089078
B21: Depreciation | G21: =-G378-G327 -> -2325.9157 | H21: =-H378-H327 -> -2737.562 | I21: =-I378-I327 -> -3190.8194 | J21: =-J378-J327 -> -3869.7993 | K21: =-K378-K327 -> -4984.9043
B22: Amortisation | G22: =-G415 -> -395.35487 | H22: =-H415 -> -414.46904 | I22: =-I415 -> -435.27987 | J22: =-J415 -> -457.82895 | K22: =-K415 -> -482.20479
B23: Depreciation and Amortisation | E23: -1839 | F23: -1942 | G23: =SUM(G21:G22) -> -2721.2706 | H23: =SUM(H21:H22) -> -3152.031 | I23: =SUM(I21:I22) -> -3626.0993 | J23: =SUM(J21:J22) -> -4327.6282 | K23: =SUM(K21:K22) -> -5467.1091
B25: EBIT | E25: =E18+E23 -> 887 | F25: =F18+F23 -> 2618 | G25: =G18+G23 -> 162.64012 | H25: =H18+H23 -> 242.76279 | I25: =I18+I23 -> 2942.2506 | J25: =J18+J23 -> 2957.5255 | K25: =K18+K23 -> 978.58604
B26: Operating profit margin | E26: =E25/E10 -> 0.03998918 | F26: =F25/F10 -> 0.11781648 | G26: =G25/G10 -> 0.006673622 | H26: =H25/H10 -> 0.0091262416 | I26: =I25/I10 -> 0.1018255 | J26: =J25/J10 -> 0.094683713 | K26: =K25/K10 -> 0.028981057
B28: Finance income | E28: 42 | F28: 117 | G28: =G520 -> 67.436579 | H28: =H520 -> 85.752818 | I28: =I520 -> 82.851666 | J28: =J520 -> 90.089176 | K28: =K520 -> 122.33822
B29: Finance costs - lease liabilities | E29: -940 | F29: -911 | G29: =G343 -> -827.63848 | H29: =H343 -> -767.72472 | I29: =I343 -> -763.92235 | J29: =J343 -> -708.69165 | K29: =K343 -> -820.20563
B30: Finance costs | E30: -541 | F30: -506 | G30: =-G514 -> -222.7536 | H30: =-H514 -> -222.7536 | I30: =-I514 -> -222.7536 | J30: =-J514 -> -222.7536 | K30: =-K514 -> -222.7536
B31: Net finance costs | E31: =SUM(E28:E30) -> -1439 | F31: =SUM(F28:F30) -> -1300 | G31: =SUM(G28:G30) -> -982.9555 | H31: =SUM(H28:H30) -> -904.7255 | I31: =SUM(I28:I30) -> -903.82429 | J31: =SUM(J28:J30) -> -841.35608 | K31: =SUM(K28:K30) -> -920.62101
B33: Depreciation on ROU asset - non operating aircraft | E33: -396 | F33: -419
B34: Finance costs - lease liabilities - non operating aircraft | E34: -245 | F34: -239
B35: Net foreign exchange gain/(loss) | E35: 279 | F35: 1370
B36: Share of results of associates | E36: 4 | F36: 26 | G36: =F36 -> 26 | H36: =G36 -> 26 | I36: =H36 -> 26 | J36: =I36 -> 26 | K36: =J36 -> 26
B37: Derivatives | E37: 5 | F37: -16 | G37: =F37 -> -16 | H37: =G37 -> -16 | I37: =H37 -> -16 | J37: =I37 -> -16 | K37: =J37 -> -16
B38: Profit before taxation | E38: =E25+E31+SUM(E33:E37) -> -905 | F38: =F25+F31+SUM(F33:F37) -> 2040 | G38: =G25+G31+SUM(G33:G37) -> -810.31538 | H38: =H25+H31+SUM(H33:H37) -> -651.96271 | I38: =I25+I31+SUM(I33:I37) -> 2048.4263 | J38: =J25+J31+SUM(J33:J37) -> 2126.1694 | K38: =K25+K31+SUM(K33:K37) -> 67.965021
B40: Taxation | E40: -109 | F40: -78 | G40: =-G549 -> 0 | H40: =-H549 -> 0 | I40: =-I549 -> -491.62232 | J40: =-J549 -> -510.28065 | K40: =-K549 -> -16.311605
B41: Net Profit | E41: =E38+SUM(E40:E40) -> -1014 | F41: =F38+SUM(F40:F40) -> 1962 | G41: =G38+SUM(G40:G40) -> -810.31538 | H41: =H38+SUM(H40:H40) -> -651.96271 | I41: =I38+SUM(I40:I40) -> 1556.804 | J41: =J38+SUM(J40:J40) -> 1615.8887 | K41: =K38+SUM(K40:K40) -> 51.653416
B42: Net Profit Margin | E42: =E41/E10 -> -0.045714801 | F42: =F41/F10 -> 0.088294856 | G42: =G41/G10 -> -0.03324972 | H42: =H41/H10 -> -0.024509395 | I42: =I41/I10 -> 0.053877922 | J42: =J41/J10 -> 0.051731877 | K42: =K41/K10 -> 0.0015297281
B44: Earning per share
B45: - Basic | C45: sen per share | G45: =G41*100000000/G600 -> -24.110599 | H45: =H41*100000000/H600 -> -19.398881 | I45: =I41*100000000/I600 -> 46.32206 | J45: =J41*100000000/J600 -> 48.080101 | K45: =K41*100000000/K600 -> 1.536926
B46: - Diluted | C46: sen per share | G46: =G41*100000000/G602 -> -24.110599 | H46: =H41*100000000/H602 -> -19.398881 | I46: =I41*100000000/I602 -> 46.32206 | J46: =J41*100000000/J602 -> 48.080101 | K46: =K41*100000000/K602 -> 1.536926
B49: Air Asia Group
B50: Financial Statements - Balance Sheet
B52: RM millions, unless otherwise stated
E54: 2024 | F54: 2025 | G54: =F54+1 -> 2026 | H54: =G54+1 -> 2027 | I54: =H54+1 -> 2028 | J54: =I54+1 -> 2029 | K54: =J54+1 -> 2030
E55: PF = Pro forma | K55: F = Forecast
B56: Assets
B58: PP&E | F58: =Sheet1!F13 -> 1206199.7 | G58: =G385 * 1000 -> 1310639.2 | H58: =H385 * 1000 -> 1386338.9 | I58: =I385 * 1000 -> 1431861.8 | J58: =J385 * 1000 -> 1445699 | K58: =K385 * 1000 -> 1426266.4
B59: ROU assets | F59: =Sheet1!F14 -> 11204943 | G59: =G334*1000 -> 10544647 | H59: =H334*1000 -> 10693962 | I59: =I334*1000 -> 9699833.7 | J59: =J334*1000 -> 11313280 | K59: =K334*1000 -> 13481361
B60: Finance lease receivables | F60: =Sheet1!F15 -> 154490 | G60: =F60 -> 154490 | H60: =G60 -> 154490 | I60: =H60 -> 154490 | J60: =I60 -> 154490 | K60: =J60 -> 154490
B61: Investment in associates | F61: =Sheet1!F16 -> 449244 | G61: =F61 -> 449244 | H61: =G61 -> 449244 | I61: =H61 -> 449244 | J61: =I61 -> 449244 | K61: =J61 -> 449244
B62: Investment securities | F62: =Sheet1!F17 -> 122 | G62: =F62 -> 122 | H62: =G62 -> 122 | I62: =H62 -> 122 | J62: =I62 -> 122 | K62: =J62 -> 122
B63: Intangible assets | F63: =Sheet1!F18 -> 13953159 | G63: =G422 * 1000 -> 13740584 | H63: =H422 * 1000 -> 13525618 | I63: =I422 * 1000 -> 13307051 | J63: =J422 * 1000 -> 13083491 | K63: =K422 * 1000 -> 12854534
B64: Deferred tax assets | F64: =Sheet1!F19 -> 1706569 | G64: =G569*1000 -> 1706569 | H64: =H569*1000 -> 1706569 | I64: =I569*1000 -> 1399305.1 | J64: =J569*1000 -> 1186688.1 | K64: =K569*1000 -> 1183969.5
B65: Receivables and prepayments | F65: =Sheet1!F20 -> 5910344.7 | G65: =F65 -> 5910344.7 | H65: =G65 -> 5910344.7 | I65: =H65 -> 5910344.7 | J65: =I65 -> 5910344.7 | K65: =J65 -> 5910344.7
B66: Deposits on aircraft purchases | F66: =Sheet1!F21 -> 607213 | G66: =F66 -> 607213 | H66: =G66 -> 607213 | I66: =H66 -> 607213 | J66: =I66 -> 607213 | K66: =J66 -> 607213
B67: Amount due from associates | F67: =Sheet1!F22 -> 27825 | G67: =F67 -> 27825 | H67: =G67 -> 27825 | I67: =H67 -> 27825 | J67: =I67 -> 27825 | K67: =J67 -> 27825
B68: Derivatives | F68: =Sheet1!F23 -> 891 | G68: =F68 -> 891 | H68: =G68 -> 891 | I68: =H68 -> 891 | J68: =I68 -> 891 | K68: =J68 -> 891
B69: Non-current assets | F69: =SUM(F58:F68) -> 35221000 | G69: =SUM(G58:G68) -> 34452569 | H69: =SUM(H58:H68) -> 34462618 | I69: =SUM(I58:I68) -> 32988182 | J69: =SUM(J58:J68) -> 34179288 | K69: =SUM(K58:K68) -> 36096261
B71: Inventories | F71: =Sheet1!F27 -> 179208.1 | G71: =G465*1000 -> 221699.27 | H71: =H465*1000 -> 238985.63 | I71: =I465*1000 -> 226499.93 | J71: =J465*1000 -> 240661.49 | K71: =K465*1000 -> 273567.81
B72: Receivables and prepayments | F72: =Sheet1!F28 -> 1488607.9 | G72: =G460 * 1000 -> 1632611.4 | H72: =H460 * 1000 -> 1781996.7 | I72: =I460 * 1000 -> 1935708 | J72: =J460 * 1000 -> 2092521.6 | K72: =K460 * 1000 -> 2262046.5
B73: Finance lease receivables | F73: =Sheet1!F29 -> 27776 | G73: =F73 -> 27776 | H73: =G73 -> 27776 | I73: =H73 -> 27776 | J73: =I73 -> 27776 | K73: =J73 -> 27776
B74: Amounts due from related parties | F74: =Sheet1!F30 -> 1262127 | G74: =F74 -> 1262127 | H74: =G74 -> 1262127 | I74: =H74 -> 1262127 | J74: =I74 -> 1262127 | K74: =J74 -> 1262127
B75: Amount due from associates | F75: =Sheet1!F31 -> 174471 | G75: =F75 -> 174471 | H75: =G75 -> 174471 | I75: =H75 -> 174471 | J75: =I75 -> 174471 | K75: =J75 -> 174471
B76: Derivatives | F76: =Sheet1!F32 -> 17159 | G76: =F76 -> 17159 | H76: =G76 -> 17159 | I76: =H76 -> 17159 | J76: =I76 -> 17159 | K76: =J76 -> 17159
B77: Tax recoverable | F77: =Sheet1!F33 -> 16765 | G77: =F77 -> 16765 | H77: =G77 -> 16765 | I77: =H77 -> 16765 | J77: =I77 -> 16765 | K77: =J77 -> 16765
B78: Cash | F78: =Sheet1!F34 -> 2247886 | G78: =G164*1000 -> 2858427.3 | H78: =H164*1000 -> 2761722.2 | I78: =I164*1000 -> 3002972.5 | J78: =J164*1000 -> 4077940.7 | K78: =K164*1000 -> 6606780.1
B79: Total current assets | F79: =SUM(F71:F78) -> 5414000 | G79: =SUM(G71:G78) -> 6211035.9 | H79: =SUM(H71:H78) -> 6281002.5 | I79: =SUM(I71:I78) -> 6663478.4 | J79: =SUM(J71:J78) -> 7909421.7 | K79: =SUM(K71:K78) -> 10640692
B81: Total assets | F81: =F69+F79 -> 40635000 | G81: =G69+G79 -> 40663605 | H81: =H69+H79 -> 40743620 | I81: =I69+I79 -> 39651660 | J81: =J69+J79 -> 42088709 | K81: =K69+K79 -> 46736953
B83: Liabilities
B85: Aircraft maintenance provision | F85: =Sheet1!F43 -> 7193542.2 | G85: =G442*1000 -> 7064190.9 | H85: =H442*1000 -> 6944394.6 | I85: =I442*1000 -> 6834321.5 | J85: =J442*1000 -> 6737904.9 | K85: =K442*1000 -> 6662710.9
B86: Borrowings | F86: =Sheet1!F44 -> 2537062 | G86: =G528*1000 -> 2537062 | H86: =H528*1000 -> 2537062 | I86: =I528*1000 -> 2537062 | J86: =J528*1000 -> 2537062 | K86: =K528*1000 -> 2537062
B87: Long-term debentures | F87: =Sheet1!F45 -> 930421 | G87: =G536*1000 -> 930421 | H87: =H536*1000 -> 930421 | I87: =I536*1000 -> 930421 | J87: =J536*1000 -> 930421 | K87: =K536*1000 -> 930421
B88: Lease liabilities | F88: =Sheet1!F46 -> 12651278 | G88: =G354*1000 -> 10082408 | H88: =H354*1000 -> 9897904.9 | I88: =I354*1000 -> 8518033 | J88: =J354*1000 -> 9940582.9 | K88: =K354*1000 -> 12982352
B89: Deferred tax liabilities | F89: =Sheet1!F47 -> 739697 | G89: =F89 -> 739697 | H89: =G89 -> 739697 | I89: =H89 -> 739697 | J89: =I89 -> 739697 | K89: =J89 -> 739697
B90: Non-current liabilities | F90: =SUM(F85:F89) -> 24052000 | G90: =SUM(G85:G89) -> 21353779 | H90: =SUM(H85:H89) -> 21049480 | I90: =SUM(I85:I89) -> 19559535 | J90: =SUM(J85:J89) -> 20885668 | K90: =SUM(K85:K89) -> 23852243
B92: Trade and other payables | F92: =Sheet1!F51 -> 7573363 | G92: =G470*1000 -> 9369046.7 | H92: =H470*1000 -> 10099571 | I92: =I470*1000 -> 9571923.2 | J92: =J470*1000 -> 10170393 | K92: =K470*1000 -> 11561020
B93: Aircraft maintenance provision | F93: =Sheet1!F52 -> 3537476.7 | G93: =G441*1000 -> 3473867.3 | H93: =H441*1000 -> 3414956.6 | I93: =I441*1000 -> 3360827.4 | J93: =J441*1000 -> 3313413.8 | K93: =K441*1000 -> 3276436.6
B94: Sales in advance | F94: =Sheet1!F53 -> 2426784.4 | G94: =G475*1000 -> 2661544.2 | H94: =H475*1000 -> 2905077.7 | I94: =I475*1000 -> 3155663.6 | J94: =J475*1000 -> 3411307 | K94: =K475*1000 -> 3687672.9
B95: Amounts due to related parties | F95: =Sheet1!F54 -> 1147738 | G95: =F95 -> 1147738 | H95: =G95 -> 1147738 | I95: =H95 -> 1147738 | J95: =I95 -> 1147738 | K95: =J95 -> 1147738
B96: Amounts due to associates | F96: =Sheet1!F55 -> 57311 | G96: =F96 -> 57311 | H96: =G96 -> 57311 | I96: =H96 -> 57311 | J96: =I96 -> 57311 | K96: =J96 -> 57311
B97: Borrowings | F97: =Sheet1!F56 -> 691757 | G97: =G527*1000 -> 691757 | H97: =H527*1000 -> 691757 | I97: =I527*1000 -> 691757 | J97: =J527*1000 -> 691757 | K97: =K527*1000 -> 691757
B98: Current debentures | F98: =Sheet1!F57 -> 295832 | G98: =G535*1000 -> 295832 | H98: =H535*1000 -> 295832 | I98: =I535*1000 -> 295832 | J98: =J535*1000 -> 295832 | K98: =K535*1000 -> 295832
B99: Lease liabilities | F99: =Sheet1!F58 -> 1142696.8 | G99: =G353*1000 -> 2713004 | H99: =H353*1000 -> 2834134.3 | I99: =I353*1000 -> 3293494.6 | J99: =J353*1000 -> 3729511 | K99: =K353*1000 -> 3729511
B100: Tax provision | F100: =Sheet1!F59 -> 187041 | G100: =G562 * 1000 -> 187041 | H100: =H562 * 1000 -> 187041 | I100: =I562 * 1000 -> 187041 | J100: =J562 * 1000 -> 187041 | K100: =K562 * 1000 -> 187041
B101: Current liabilities | F101: =SUM(F92:F100) -> 17060000 | G101: =SUM(G92:G100) -> 20597141 | H101: =SUM(H92:H100) -> 21633419 | I101: =SUM(I92:I100) -> 21761588 | J101: =SUM(J92:J100) -> 23004304 | K101: =SUM(K92:K100) -> 24634319
B103: Total Liabilities | F103: =F90+F101 -> 41112000 | G103: =G90+G101 -> 41950920 | H103: =H90+H101 -> 42682898 | I103: =I90+I101 -> 41321122 | J103: =J90+J101 -> 43889972 | K103: =K90+K101 -> 48486562
B105: Equity
B107: Share capital | F107: =Sheet1!F68 -> 4893876 | G107: =F107 -> 4893876 | H107: =G107 -> 4893876 | I107: =H107 -> 4893876 | J107: =I107 -> 4893876 | K107: =J107 -> 4893876
B108: Acquisition reserve | F108: =Sheet1!F69 -> 1165374 | G108: =F108 -> 1165374 | H108: =G108 -> 1165374 | I108: =H108 -> 1165374 | J108: =I108 -> 1165374 | K108: =J108 -> 1165374
B109: Currency translation reserve | F109: =Sheet1!F70 -> 1211801 | G109: =F109 -> 1211801 | H109: =G109 -> 1211801 | I109: =H109 -> 1211801 | J109: =I109 -> 1211801 | K109: =J109 -> 1211801
B110: Warrant reserve | F110: =Sheet1!F71 -> 22 | G110: =F110 -> 22 | H110: =G110 -> 22 | I110: =H110 -> 22 | J110: =I110 -> 22 | K110: =J110 -> 22
B111: (Accumulated losses)/Retained earnings | F111: =Sheet1!F72 -> -6957283 | G111: =G593*1000 -> -7767598.4 | H111: =H593*1000 -> -8419561.1 | I111: =I593*1000 -> -8149745.3 | J111: =J593*1000 -> -8281545.4 | K111: =K593*1000 -> -8229892
B112: Shareholders equity | F112: =SUM(F107:F111) -> 313790 | G112: =SUM(G107:G111) -> -496525.38 | H112: =SUM(H107:H111) -> -1148488.1 | I112: =SUM(I107:I111) -> -878672.32 | J112: =SUM(J107:J111) -> -1010472.4 | K112: =SUM(K107:K111) -> -958819.02
B113: Non-controlling interests | F113: =Sheet1!F74 -> -790790 | G113: =F113 -> -790790 | H113: =G113 -> -790790 | I113: =H113 -> -790790 | J113: =I113 -> -790790 | K113: =J113 -> -790790
B114: Total equity | F114: =SUM(F112:F113) -> -477000 | G114: =SUM(G112:G113) -> -1287315.4 | H114: =SUM(H112:H113) -> -1939278.1 | I114: =SUM(I112:I113) -> -1669462.3 | J114: =SUM(J112:J113) -> -1801262.4 | K114: =SUM(K112:K113) -> -1749609
B116: Total liabilities and equity | F116: =F114+F103 -> 40635000 | G116: =G114+G103 -> 40663605 | H116: =H114+H103 -> 40743620 | I116: =I114+I103 -> 39651660 | J116: =J114+J103 -> 42088709 | K116: =K114+K103 -> 46736953
B117: Balance? | F117: =F81-F116 -> 0 | G117: =G81-G116 -> 0 | H117: =H81-H116 -> 0 | I117: =I81-I116 -> 0 | J117: =J81-J116 -> 0 | K117: =K81-K116 -> 0
B120: Air Asia Group
B121: Financial Statements - Cash Flow Statement
B123: RM millions, unless otherwise stated
E125: 2024 | F125: 2025 | G125: =F125+1 -> 2026 | H125: =G125+1 -> 2027 | I125: =H125+1 -> 2028 | J125: =I125+1 -> 2029 | K125: =J125+1 -> 2030
E126: PF = Pro forma | K126: F = Forecast
B128: Cash Flow from Operations (CFO)
B130: Net income | G130: =G41 -> -810.31538 | H130: =H41 -> -651.96271 | I130: =I41 -> 1556.804 | J130: =J41 -> 1615.8887 | K130: =K41 -> 51.653416
...

Sheet Sheet1
B1: =Cover!$B$2 -> Air Asia
B2: Financial Statements - Balance Sheet Reconciliation
C5: Units / RM'000 | E5: 2026 Q1 | F5: 2025 PF | G5: Notes
B6: Income Statement Anchors
B8: Revenue | E8: 5950000 | F8: 22200000
B9: Annualized Revenue | E9: =4*E8 -> 23800000 | F9: =F8 -> 22200000
B11: Assets
B13: PP&E | E13: 1293133 | F13: =($F$9/$E$9)*E13 -> 1206199.7 | G13: Adjusted based on annualized revenue
B14: ROU assets | E14: 12012506 | F14: =($F$9/$E$9)*E14 -> 11204943 | G14: Adjusted based on annualized revenue
B15: Finance lease receivables | E15: 154490 | F15: =E15 -> 154490 | G15: Hold flat
B16: Investment in associates | E16: 449244 | F16: =E16 -> 449244 | G16: Held flat
B17: Investment securities | E17: 122 | F17: =E17 -> 122 | G17: Held flat - as immaterial
B18: Intangible assets | E18: 13953159 | F18: =E18 -> 13953159 | G18: Held flat - as goodwill tends to be impaired
B19: Deferred tax assets | E19: 1706569 | F19: =E19 -> 1706569 | G19: Held flat
B20: Receivables and prepayments | E20: 8070813 | F20: 5910344.7 | G20: Adjusted for the first pass to allow for reconciliation
B21: Deposits on aircraft purchases | E21: 607213 | F21: =E21 -> 607213 | G21: Have assumed no change
B22: Amount due from associates | E22: 27825 | F22: =E22 -> 27825 | G22: Held flat
B23: Derivatives | E23: 891 | F23: =E23 -> 891 | G23: Held flat
B24: Non-current assets | E24: =SUM(E13:E23) -> 38275965 | F24: =SUM(F13:F23) -> 35221000
B25: Non current assets - actuals | F25: 35221000
B27: Inventories | E27: 192124 | F27: =($F$9/$E$9)*E27 -> 179208.1 | G27: Adjusted based on annualized revenue
B28: Receivables and prepayments | E28: 1595895 | F28: =($F$9/$E$9)*E28 -> 1488607.9 | G28: Adjusted based on annualized revenue
B29: Finance lease receivables | E29: 27776 | F29: =E29 -> 27776 | G29: Held flat
B30: Amounts due from related parties | E30: 1262127 | F30: =E30 -> 1262127 | G30: Held flat
B31: Amount due from associates | E31: 174471 | F31: =E31 -> 174471 | G31: Held flat
B32: Derivatives | E32: 17159 | F32: =E32 -> 17159 | G32: Held flat
B33: Tax recoverable | E33: 16765 | F33: =E33 -> 16765 | G33: Held flat
B34: Cash | E34: 1085766 | F34: =F36-SUM(F27:F33) -> 2247886
B35: Total current assets | E35: =SUM(E27:E34) -> 4372083 | F35: =SUM(F27:F34) -> 5414000
B36: Current assets - actuals | F36: 5414000
B38: Total assets | E38: =E24+E35 -> 42648048 | F38: =F24+F35 -> 40635000
B39: Total assets - actuals | F39: =F25+F36 -> 40635000
B41: Liabilities
B43: Aircraft maintenance provision | E43: 6689552 | F43: 7193542.2 | G43: Manually adjusted for first pass
B44: Borrowings | E44: 2537062 | F44: =E44 -> 2537062
B45: Long-term debentures | E45: 930421 | F45: =E45 -> 930421
B46: Lease liabilities | E46: 12338502 | F46: 12651278 | G46: Manually adjusted for first pass
B47: Deferred tax liabilities | E47: 739697 | F47: =E47 -> 739697
B48: Non-current liabilities | E48: =SUM(E43:E47) -> 23235234 | F48: =SUM(F43:F47) -> 24052000
B49: Non-current liabilities - actuals | F49: 24052000
B51: Trade and other payables | E51: 8119191 | F51: =($F$9/$E$9)*E51 -> 7573363
B52: Aircraft maintenance provision | E52: 3792430 | F52: =($F$9/$E$9)*E52 -> 3537476.7
B53: Sales in advance | E53: 2589895 | F53: 2426784.4
B54: Amounts due to related parties | E54: 1147738 | F54: =E54 -> 1147738
B55: Amounts due to associates | E55: 57311 | F55: =E55 -> 57311
B56: Borrowings | E56: 691757 | F56: =E56 -> 691757
B57: Current debentures | E57: 295832 | F57: =E57 -> 295832
B58: Lease liabilities | E58: 2449633 | F58: 1142696.8 | G58: Manually adjusted for first pass
B59: Tax provision | E59: 187041 | F59: =E59 -> 187041
B60: Current liabilities | E60: =SUM(E51:E59) -> 19330828 | F60: =SUM(F51:F59) -> 17060000
B61: Current liabilities - actuals | F61: 17049000
B63: Total Liabilities | E63: =E48+E60 -> 42566062 | F63: =F48+F60 -> 41112000
B64: Total liabilties - actuals | F64: =F49+F61 -> 41101000
B66: Equity
B68: Share capital | E68: 4893876 | F68: =E68 -> 4893876
B69: Acquisition reserve | E69: 1165374 | F69: =E69 -> 1165374
B70: Currency translation reserve | E70: 1211801 | F70: =E70 -> 1211801
B71: Warrant reserve | E71: 22 | F71: =E71 -> 22
B72: (Accumulated losses)/Retained earnings | E72: -6398596 | F72: -6957283
B73: Shareholders equity | E73: =SUM(E68:E72) -> 872477 | F73: =SUM(F68:F72) -> 313790
B74: Non-controlling interests | E74: -790790 | F74: =E74 -> -790790
B75: Total equity | E75: =SUM(E73:E74) -> 81687 | F75: =SUM(F73:F74) -> -477000
B76: Total equity - actuals | F76: -477000
B79: Balance check | E79: =E75+E63-E38 -> -299 | F79: =F75+F63-F38 -> 0
B80: * Note that there are minor differences - suspected to be due to rounding in the final presentation -deemed immaterial
