Workbook

Sheet Cover
B2: ASOS PLC
B5: =DATE(2026, 10, 19) -> 46314

Sheet Assumptions
B2: =Cover!$B$2 -> ASOS PLC
B3: Assumptions | L3: ="Currently Running: "&CHOOSE(Assumptions!$B$10,Assumptions!$F$15,Assumptions!$F$16,Assumptions!$F$17)&"Scenario" -> Currently Running: Base Scenario
F5: Fiscal Years Ending December 31
F6: 2024 | G6: =F6+1 -> 2025 | H6: =G6+1 -> 2026 | I6: =H6+1 -> 2027 | J6: =I6+1 -> 2028 | K6: =J6+1 -> 2029 | L6: =K6+1 -> 2030
B7: £ in millions, unless stated | F7: H = Historical | L7: F = Forecast
B9: Scenario Selector:
B10: 1
B12: Macro Assumptions
B14: Inflation | F14: Selected | H14: =CHOOSE($B$10,H15,H16,H17) -> 0.04 | I14: =CHOOSE($B$10,I15,I16,I17) -> 0.035 | J14: =CHOOSE($B$10,J15,J16,J17) -> 0.03 | K14: =CHOOSE($B$10,K15,K16,K17) -> 0.02 | L14: =CHOOSE($B$10,L15,L16,L17) -> 0.02 | N14: Current forecasts suggests inflation trending upwards, but will recover throughout 2027. Downside assumes inflation from fuel prices remains high and no immediate end to iran conflict. Upside assumes inflation is transitory
F15: Base | H15: 0.04 | I15: 0.035 | J15: 0.03 | K15: 0.02 | L15: 0.02
F16: Upside | H16: 0.035 | I16: 0.03 | J16: 0.025 | K16: 0.02 | L16: 0.02
F17: Downside | H17: 0.04 | I17: 0.05 | J17: 0.045 | K17: 0.035 | L17: 0.03
B19: Wage Inflation | F19: Selected | H19: =CHOOSE($B$10,H20,H21,H22) -> 0.035 | I19: =CHOOSE($B$10,I20,I21,I22) -> 0.03 | J19: =CHOOSE($B$10,J20,J21,J22) -> 0.03 | K19: =CHOOSE($B$10,K20,K21,K22) -> 0.03 | L19: =CHOOSE($B$10,L20,L21,L22) -> 0.03 | N19: Wage inflation remains slightly below inflation - according to ONS.
F20: Base | H20: 0.035 | I20: 0.03 | J20: 0.03 | K20: 0.03 | L20: 0.03
F21: Upside | H21: 0.03 | I21: 0.025 | J21: 0.02 | K21: 0.02 | L21: 0.02
F22: Downside | H22: 0.035 | I22: 0.045 | J22: 0.045 | K22: 0.04 | L22: 0.03
B24: Supplier cost inflation | F24: Selected | H24: =CHOOSE($B$10,H25,H26,H27) -> 0.035 | I24: =CHOOSE($B$10,I25,I26,I27) -> 0.03 | J24: =CHOOSE($B$10,J25,J26,J27) -> 0.03 | K24: =CHOOSE($B$10,K25,K26,K27) -> 0.03 | L24: =CHOOSE($B$10,L25,L26,L27) -> 0.03
F25: Base | H25: 0.035 | I25: 0.03 | J25: 0.03 | K25: 0.03 | L25: 0.03
F26: Upside | H26: 0.03 | I26: 0.025 | J26: 0.02 | K26: 0.02 | L26: 0.02
F27: Downside | H27: 0.035 | I27: 0.045 | J27: 0.045 | K27: 0.04 | L27: 0.03
B30: Revenue Assumptions
B32: Customer Acquisition | F32: Selected | H32: =CHOOSE($B$10,H33,H34,H35) -> 1500000 | I32: =CHOOSE($B$10,I33,I34,I35) -> 1500000 | J32: =CHOOSE($B$10,J33,J34,J35) -> 1500000 | K32: =CHOOSE($B$10,K33,K34,K35) -> 1500000 | L32: =CHOOSE($B$10,L33,L34,L35) -> 1500000
F33: Base | H33: 1500000 | I33: 1500000 | J33: 1500000 | K33: 1500000 | L33: 1500000
F34: Upside | H34: 2000000 | I34: 2000000 | J34: 2000000 | K34: 2000000 | L34: 2000000
F35: Downside | H35: 1000000 | I35: 1000000 | J35: 1000000 | K35: 1000000 | L35: 1000000
B37: Customer Churn | F37: Selected | H37: =CHOOSE($B$10,H38,H39,H40) -> -2000000 | I37: =CHOOSE($B$10,I38,I39,I40) -> -2000000 | J37: =CHOOSE($B$10,J38,J39,J40) -> -1500000 | K37: =CHOOSE($B$10,K38,K39,K40) -> -1250000 | L37: =CHOOSE($B$10,L38,L39,L40) -> -1000000
F38: Base | H38: -2000000 | I38: -2000000 | J38: -1500000 | K38: -1250000 | L38: -1000000 | N38: Used historical rates - downside assumes it continues to decline
F39: Upside | H39: -1500000 | I39: -1000000 | J39: -500000 | K39: -500000 | L39: -500000
F40: Downside | H40: -4000000 | I40: -3000000 | J40: -2000000 | K40: -1000000 | L40: -1000000
B42: Average Order Volume by Customer | F42: Selected | H42: =CHOOSE($B$10,H43,H44,H45) -> 3.3529412 | I42: =CHOOSE($B$10,I43,I44,I45) -> 3.3529412 | J42: =CHOOSE($B$10,J43,J44,J45) -> 3.3529412 | K42: =CHOOSE($B$10,K43,K44,K45) -> 3.3529412 | L42: =CHOOSE($B$10,L43,L44,L45) -> 3.3529412
F43: Base | H43: 3.3529412 | I43: 3.3529412 | J43: 3.3529412 | K43: 3.3529412 | L43: 3.3529412
F44: Upside | H44: 3.35 | I44: 3.5 | J44: 3.75 | K44: 3.75 | L44: 3.75
F45: Downside | H45: 3.25 | I45: 3.1 | J45: 3 | K45: 3 | L45: 3
B47: Basket Price Improvements | F47: Selected | H47: =CHOOSE($B$10,H48,H49,H50) -> 0.034 | I47: =CHOOSE($B$10,I48,I49,I50) -> 0.034 | J47: =CHOOSE($B$10,J48,J49,J50) -> 0.034 | K47: =CHOOSE($B$10,K48,K49,K50) -> 0.034 | L47: =CHOOSE($B$10,L48,L49,L50) -> 0.034
F48: Base | H48: 0.034 | I48: 0.034 | J48: 0.034 | K48: 0.034 | L48: 0.034
F49: Upside | H49: 0.034 | I49: 0.0375 | J49: 0.04 | K49: 0.0375 | L49: 0.035
F50: Downside | H50: 0.03 | I50: 0.0275 | J50: 0.025 | K50: 0.02 | L50: 0.02

Sheet Model
B3: =Cover!$B$2 -> ASOS PLC
B4: Financial Statements - Income Statement | L4: ="Currently Running: "&CHOOSE(Assumptions!$B$10,Assumptions!$F$15,Assumptions!$F$16,Assumptions!$F$17)&"Scenario" -> Currently Running: Base Scenario
F6: Fiscal Year ending August 30
F7: 2024 | G7: =F7+1 -> 2025 | H7: =G7+1 -> 2026 | I7: =H7+1 -> 2027 | J7: =I7+1 -> 2028 | K7: =J7+1 -> 2029 | L7: =K7+1 -> 2030
B8: £ in millions, unless stated | F8: H = Historical | L8: F = Forecast
B10: Revenue | F10: 2905800000 | G10: 2477800000 | H10: =H218 -> 2.4691272e+09 | I10: =I218 -> 2.4753427e+09 | J10: =J218 -> 2.5548021e+09 | K10: =K218 -> 2.6760048e+09 | L10: =L218 -> 2.8430248e+09
B11: Cost of Sales | F11: -1743300000 | G11: -1311100000 | H11: =-H244 -> -1.3205554e+09 | I11: =-I244 -> -1.3189547e+09 | J11: =-J244 -> -1.3585233e+09 | K11: =-K244 -> -1.4211428e+09 | L11: =-L244 -> -1.5088163e+09
B12: Gross profit | F12: =SUM(F10:F11) -> 1162500000 | G12: =SUM(G10:G11) -> 1166700000 | H12: =SUM(H10:H11) -> 1.1485718e+09 | I12: =SUM(I10:I11) -> 1.156388e+09 | J12: =SUM(J10:J11) -> 1.1962788e+09 | K12: =SUM(K10:K11) -> 1.2548621e+09 | L12: =SUM(L10:L11) -> 1.3342085e+09
B13: Gross profit margin | F13: =F12/F10 -> 0.40006195 | G13: =G12/G10 -> 0.47086125 | H13: =H12/H10 -> 0.46517321 | I13: =I12/I10 -> 0.46716279 | J13: =J12/J10 -> 0.46824715 | K13: =K12/K10 -> 0.46893117 | L13: =L12/L10 -> 0.46929189
B15: Distribution expenses | F15: -326100000 | G15: -262300000 | H15: =H272 -> -2.6349578e+08 | I15: =I272 -> -2.6317639e+08 | J15: =J272 -> -2.7107168e+08 | K15: =K272 -> -2.8356639e+08 | L15: =L272 -> -3.0106026e+08
B16: Administration expenses | F16: -1170300000 | G16: -1133200000 | H16: =H305 -> -1.014767e+09 | I16: =I305 -> -1.0396751e+09 | J16: =J305 -> -1.0762408e+09 | K16: =K305 -> -1.1170886e+09 | L16: =L305 -> -1.1668067e+09
B17: Other income | F17: 2000000 | G17: 16500000 | H17: =G17 -> 16500000 | I17: =H17 -> 16500000 | J17: =I17 -> 16500000 | K17: =J17 -> 16500000 | L17: =K17 -> 16500000
B18: EBIT | F18: =F12+SUM(F15:F17) -> -331900000 | G18: =G12+SUM(G15:G17) -> -212300000 | H18: =SUM(H15:H17)+H12 -> -1.1319096e+08 | I18: =SUM(I15:I17)+I12 -> -1.2996348e+08 | J18: =SUM(J15:J17)+J12 -> -1.3453365e+08 | K18: =SUM(K15:K17)+K12 -> -1.2929293e+08 | L18: =SUM(L15:L17)+L12 -> -1.1715842e+08
B19: EBIT Margin | F19: =F18/F10 -> -0.11421984 | G19: =G18/G10 -> -0.085680846 | H19: =H18/H10 -> -0.0458425 | I19: =I18/I10 -> -0.052503227 | J19: =J18/J10 -> -0.052659128 | K19: =K18/K10 -> -0.048315656 | L19: =L18/L10 -> -0.041209073
B21: Depreciation of PP&E | F21: 28900000 | G21: 26700000 | H21: =H442 -> 32655302 | I21: =I442 -> 36610878 | J21: =J442 -> 40634993 | K21: =K442 -> 44819639 | L21: =L442 -> 49234863
B22: Depreciation of ROU assets | F22: 25100000 | G22: 24000000 | H22: =H395 -> 17210000 | I22: =I395 -> 17210000 | J22: =J395 -> 17210000 | K22: =K395 -> 17210000 | L22: =L395 -> 17210000
B23: Amortisation | F23: 117300000 | G23: 115500000 | H23: =H469 -> 95890948 | I23: =I469 -> 1.1245366e+08 | J23: =J469 -> 1.2930337e+08 | K23: =K469 -> 1.4682524e+08 | L23: =L469 -> 1.6531259e+08
B24: Depreciation and Amortization | F24: =SUM(F21:F23) -> 171300000 | G24: =SUM(G21:G23) -> 166200000 | H24: =SUM(H21:H23) -> 1.4575625e+08 | I24: =SUM(I21:I23) -> 1.6627454e+08 | J24: =SUM(J21:J23) -> 1.8714836e+08 | K24: =SUM(K21:K23) -> 2.0885488e+08 | L24: =SUM(L21:L23) -> 2.3175745e+08
B25: EBITDA | F25: =F18+F24 -> -160600000 | G25: =G18+G24 -> -46100000 | H25: =H18+H24 -> 32565288 | I25: =I18+I24 -> 36311063 | J25: =J18+J24 -> 52614712 | K25: =K18+K24 -> 79561955 | L25: =L18+L24 -> 1.1459904e+08
B26: EBITDA Margin | F26: =F25/F10 -> -0.055268773 | G26: =G25/G10 -> -0.018605214 | H26: =H25/H10 -> 0.013188988 | I26: =I25/I10 -> 0.014669105 | J26: =J25/J10 -> 0.020594437 | K26: =K25/K10 -> 0.029731618 | L26: =L25/L10 -> 0.040308841
B28: Finance income | F28: 12000000 | G28: 4800000 | H28: =H596 -> 3189000 | I28: =I596 -> 1202999.1 | J28: =J596 -> 300000 | K28: =K596 -> 300000 | L28: =L596 -> 300000
B29: Finance expense | F29: -59400000 | G29: -74100000 | H29: =-H594+H407 -> -55039600 | I29: =-I594+I407 -> -53478550 | J29: =-J594+J407 -> -59082485 | K29: =-K594+K407 -> -74242495 | L29: =-L594+L407 -> -89319113
B30: Net finance costs | F30: =SUM(F28:F29) -> -47400000 | G30: =SUM(G28:G29) -> -69300000 | H30: =SUM(H28:H29) -> -51850600 | I30: =SUM(I28:I29) -> -52275551 | J30: =SUM(J28:J29) -> -58782485 | K30: =SUM(K28:K29) -> -73942495 | L30: =SUM(L28:L29) -> -89019113
B31: Profit / (loss) for the year | F31: =F18+F30 -> -379300000 | G31: =G18+G30 -> -281600000 | H31: =H18+H30 -> -1.6504156e+08 | I31: =I18+I30 -> -1.8223903e+08 | J31: =J18+J30 -> -1.9331614e+08 | K31: =K18+K30 -> -2.0323542e+08 | L31: =L18+L30 -> -2.0617753e+08
B33: Income tax (charge) / credit | F33: 40600000 | G33: -16800000 | H33: =H649 -> 0 | I33: =-I649 -> 0 | J33: =-J649 -> 0 | K33: =-K649 -> 0 | L33: =-L649 -> 0
B34: Net Profit | F34: =F31+F33 -> -338700000 | G34: =G31+G33 -> -298400000 | H34: =H31+H33 -> -1.6504156e+08 | I34: =I31+I33 -> -1.8223903e+08 | J34: =J31+J33 -> -1.9331614e+08 | K34: =K31+K33 -> -2.0323542e+08 | L34: =L31+L33 -> -2.0617753e+08
B35: Net Profit Margin | F35: =F34/F10 -> -0.11655998 | G35: =G34/G10 -> -0.12042941 | H35: =H34/H10 -> -0.066842067 | I35: =I34/I10 -> -0.073621738 | J35: =J34/J10 -> -0.075667753 | K35: =K34/K10 -> -0.075947331 | L35: =L34/L10 -> -0.072520482
B37: Earnings per share (basic) | E37: pence per share | F37: -284.4 | G37: -250.1 | H37: =H34/H38*100 -> -138.34163 | I37: =I34/I38*100 -> -152.75694 | J37: =J34/J38*100 -> -162.04203 | K37: =K34/K38*100 -> -170.3566 | L37: =L34/L38*100 -> -172.82274
B38: Weighted average shares outstanding | E38: million | F38: 119100000 | G38: 119300000 | H38: =G38 -> 119300000 | I38: =H38 -> 119300000 | J38: =I38 -> 119300000 | K38: =J38 -> 119300000 | L38: =K38 -> 119300000
B42: =Cover!$B$2 -> ASOS PLC
B43: Financial Statements - Balance Sheet | L43: ="Currently Running: "&CHOOSE(Assumptions!$B$10,Assumptions!$F$15,Assumptions!$F$16,Assumptions!$F$17)&"Scenario" -> Currently Running: Base Scenario
F45: Fiscal Year ending August 30
F46: =F7 -> 2024 | G46: =F46+1 -> 2025 | H46: =G46+1 -> 2026 | I46: =H46+1 -> 2027 | J46: =I46+1 -> 2028 | K46: =J46+1 -> 2029 | L46: =K46+1 -> 2030
B47: £ in millions, unless stated | F47: H = Historical | L47: F = Forecast
B49: Assets
B51: Inventories | F51: 520300000 | G51: 402300000 | H51: =H255 -> 3.2561639e+08 | I51: =I255 -> 3.252217e+08 | J51: =J255 -> 3.3497835e+08 | K51: =K255 -> 3.5041876e+08 | L51: =L255 -> 3.720369e+08
B52: Assets held for sale | F52: 165500000 | G52: 0 | H52: =G52 -> 0 | I52: =H52 -> 0 | J52: =I52 -> 0 | K52: =J52 -> 0 | L52: =K52 -> 0
B53: Trade and other receivables | F53: 53400000 | G53: 49200000 | H53: =H344 -> 49382543 | I53: =I344 -> 49506854 | J53: =J344 -> 51096043 | K53: =K344 -> 53520097 | L53: =L344 -> 56860497
B54: Derivative financial assets | F54: 9500000 | G54: 1200000 | H54: =G54 -> 1200000 | I54: =H54 -> 1200000 | J54: =I54 -> 1200000 | K54: =J54 -> 1200000 | L54: =K54 -> 1200000 | N54: Held flat
B55: Cash and cash equivalents | F55: 391000000 | G55: 318900000 | H55: =H143 -> 1.2029991e+08 | I55: =I143 -> 30000000 | J55: =J143 -> 30000000 | K55: =K143 -> 30000000 | L55: =L143 -> 30000000
B56: Current tax assets | F56: 6700000 | G56: 3700000 | H56: =H658 -> 3700000 | I56: =I658 -> 3700000 | J56: =J658 -> 3700000 | K56: =K658 -> 3700000 | L56: =L658 -> 3700000
B57: Current Assets | F57: =SUM(F51:F56) -> 1146400000 | G57: =SUM(G51:G56) -> 775300000 | H57: =SUM(H51:H56) -> 5.0019884e+08 | I57: =SUM(I51:I56) -> 4.0962856e+08 | J57: =SUM(J51:J56) -> 4.209744e+08 | K57: =SUM(K51:K56) -> 4.3883886e+08 | L57: =SUM(L51:L56) -> 4.637974e+08
B59: PP&E, net | F59: 283200000 | G59: 153400000 | H59: =H451 -> 1.4049772e+08 | I59: =I451 -> 1.2368958e+08 | J59: =J451 -> 1.03493e+08 | K59: =K451 -> 80081403 | L59: =L451 -> 53590739
B60: Goodwill and intangible assets | F60: 514000000 | G60: 473600000 | H60: =H481 -> 4.6041853e+08 | I60: =I481 -> 4.3088255e+08 | J60: =J481 -> 3.8715856e+08 | K60: =K481 -> 3.2997267e+08 | L60: =L481 -> 2.5989419e+08
B61: Right-of-use assets | F61: 254000000 | G61: 172100000 | H61: =H401 -> 154890000 | I61: =I401 -> 137680000 | J61: =J401 -> 120470000 | K61: =K401 -> 103260000 | L61: =L401 -> 86050000
B62: Investment properties | F62: 7100000 | G62: 6200000 | H62: =G62 -> 6200000 | I62: =H62 -> 6200000 | J62: =I62 -> 6200000 | K62: =J62 -> 6200000 | L62: =K62 -> 6200000
B63: Investments in associates | F63: 0 | G63: 44900000 | H63: =G63 -> 44900000 | I63: =H63 -> 44900000 | J63: =I63 -> 44900000 | K63: =J63 -> 44900000 | L63: =K63 -> 44900000
B64: Trade and other receivables | F64: 3700000 | G64: 1800000 | H64: =G64 -> 1800000 | I64: =H64 -> 1800000 | J64: =I64 -> 1800000 | K64: =J64 -> 1800000 | L64: =K64 -> 1800000 | N64: Held flat
B65: Derivative financial assets | F65: 300000 | G65: 100000 | H65: =G65 -> 100000 | I65: =H65 -> 100000 | J65: =I65 -> 100000 | K65: =J65 -> 100000 | L65: =K65 -> 100000 | N65: Held flat
B66: Deferred tax asset | F66: 62500000 | G66: 44700000 | H66: =H672 -> 44700000 | I66: =I672 -> 44700000 | J66: =J672 -> 44700000 | K66: =K672 -> 44700000 | L66: =L672 -> 44700000
B67: Total Assets | F67: =SUM(F59:F66)+F57 -> 2271200000 | G67: =SUM(G59:G66)+G57 -> 1672100000 | H67: =SUM(H57)+SUM(H59:H66) -> 1.3537051e+09 | I67: =SUM(I57)+SUM(I59:I66) -> 1.1995807e+09 | J67: =SUM(J57)+SUM(J59:J66) -> 1.129796e+09 | K67: =SUM(K57)+SUM(K59:K66) -> 1.0498529e+09 | L67: =SUM(L57)+SUM(L59:L66) -> 9.6103233e+08
B69: Liabilities and Shareholders Equity
B71: Trade and other payables | F71: -671700000 | G71: -619300000 | H71: =-H348 -> -5.9424991e+08 | I71: =-I348 -> -5.9352961e+08 | J71: =-J348 -> -6.113355e+08 | K71: =-K348 -> -6.3951424e+08 | L71: =-L348 -> -6.7896735e+08
B72: Derivative financial liabilities | F72: -6600000 | G72: -9800000 | H72: =G72 -> -9800000 | I72: =H72 -> -9800000 | J72: =I72 -> -9800000 | K72: =J72 -> -9800000 | L72: =K72 -> -9800000
B73: Lease liabilities | F73: -27200000 | G73: -27500000 | H73: =H416 -> -26125950 | I73: =I416 -> -26909728 | J73: =J416 -> -27717020 | K73: =K416 -> -28548531 | L73: =L416 -> 0
B74: Provisions | F74: -2700000 | G74: -4400000 | H74: =H329 -> -3580348.8 | I74: =I329 -> -3323649.9 | J74: =J329 -> -3066951 | K74: =K329 -> -2810252.1 | L74: =L329 -> -2553553.2
B75: Current tax liabilities | F75: -4200000 | G75: 0 | H75: =(H666)+(H666) -> 0 | I75: =0+((I666)+(I666)) -> 0 | J75: =0+((J666)+(J666)) -> 0 | K75: =0+((K666)+(K666)) -> 0 | L75: =0+((L666)+(L666)) -> 0
B76: Total Current Liabilities | F76: =SUM(F71:F75) -> -712400000 | G76: =SUM(G71:G75) -> -661000000 | H76: =SUM(H71:H75) -> -6.3375621e+08 | I76: =SUM(I71:I75) -> -6.3356299e+08 | J76: =SUM(J71:J75) -> -6.5191947e+08 | K76: =SUM(K71:K75) -> -6.8067303e+08 | L76: =SUM(L71:L75) -> -6.913209e+08
B78: Borrowings - Current | F78: -1600000 | G78: -96400000
B79: Borrowings - Non Current | F79: -686500000 | G79: -407200000
B80: Total Debt | F80: =SUM(F78,F79) -> -688100000 | G80: =SUM(G78,G79) -> -503600000 | H80: =-H560 -> -419700000 | I80: =-I560 -> -4.806233e+08 | J80: =-J560 -> -6.1922096e+08 | K80: =-K560 -> -7.4801405e+08 | L80: =-L560 -> -8.6042881e+08
B82: Provisions | F82: -86500000 | G82: -97800000 | H82: =H330 -> -79581389 | I82: =I330 -> -73875673 | J82: =J330 -> -68169956 | K82: =K330 -> -62464240 | L82: =L330 -> -56758524
B83: Derivative financial liabilities | F83: -500000 | G83: -300000 | H83: =G83 -> -300000 | I83: =H83 -> -300000 | J83: =I83 -> -300000 | K83: =J83 -> -300000 | L83: =K83 -> -300000
B84: Lease liabilities | F84: -262400000 | G84: -197000000 | H84: =H417 -> -173009050 | I84: =I417 -> -1.4609932e+08 | J84: =J417 -> -1.183823e+08 | K84: =K417 -> -89833770 | L84: =L417 -> -89833770
B85: Total Non-current liabilties | F85: =SUM(F80:F84) -> -1037500000 | G85: =SUM(G80:G84) -> -798700000 | H85: =SUM(H80:H84) -> -6.7259044e+08 | I85: =SUM(I80:I84) -> -7.008983e+08 | J85: =SUM(J80:J84) -> -8.0607322e+08 | K85: =SUM(K80:K84) -> -9.0061206e+08 | L85: =SUM(L80:L84) -> -1.0073211e+09
B87: Total Liabilities | F87: =F85+F76 -> -1749900000 | G87: =G85+G76 -> -1459700000 | H87: =H85+H76 -> -1.3063466e+09 | I87: =I85+I76 -> -1.3344613e+09 | J87: =J85+J76 -> -1.4579927e+09 | K87: =K85+K76 -> -1.5812851e+09 | L87: =L85+L76 -> -1.698642e+09
B89: Share capital | F89: 4200000 | G89: 4200000 | H89: =G89 -> 4200000 | I89: =H89 -> 4200000 | J89: =I89 -> 4200000 | K89: =J89 -> 4200000 | L89: =K89 -> 4200000
B90: Share premium | F90: 322600000 | G90: 322600000 | H90: =G90 -> 322600000 | I90: =H90 -> 322600000 | J90: =I90 -> 322600000 | K90: =J90 -> 322600000 | L90: =K90 -> 322600000
B91: Other reserves | F91: 61900000 | G91: 3600000 | H91: =G91 -> 3600000 | I91: =H91 -> 3600000 | J91: =I91 -> 3600000 | K91: =J91 -> 3600000 | L91: =K91 -> 3600000
B92: Retained earnings | F92: 132600000 | G92: -118000000 | H92: =H697 -> -2.8304156e+08 | I92: =I697 -> -4.6528059e+08 | J92: =J697 -> -6.5859673e+08 | K92: =K697 -> -8.6183215e+08 | L92: =L697 -> -1.0680097e+09
B93: Total Liabilities and Equity | F93: =SUM(F89:F92)-F87 -> 2271200000 | G93: =SUM(G89:G92)-G87 -> 1672100000 | H93: =SUM(H89:H92)-H87 -> 1.3537051e+09 | I93: =SUM(I89:I92)-I87 -> 1.1995807e+09 | J93: =SUM(J89:J92)-J87 -> 1.129796e+09 | K93: =SUM(K89:K92)-K87 -> 1.0498529e+09 | L93: =SUM(L89:L92)-L87 -> 9.6103233e+08
F94: =F67-F93 -> 0 | G94: =G67-G93 -> 0 | H94: =H67-H93 -> 0 | I94: =I67-I93 -> 0 | J94: =J67-J93 -> 0 | K94: =K67-K93 -> 0 | L94: =L67-L93 -> 0
B101: =Cover!$B$2 -> ASOS PLC
B102: Financial Statements - Cash Flow Statement | L102: ="Currently Running: "&CHOOSE(Assumptions!$B$10,Assumptions!$F$15,Assumptions!$F$16,Assumptions!$F$17)&"Scenario" -> Currently Running: Base Scenario
F104: Fiscal Year ending August 30
F105: =F46 -> 2024 | G105: =F105+1 -> 2025 | H105: =G105+1 -> 2026 | I105: =H105+1 -> 2027 | J105: =I105+1 -> 2028 | K105: =J105+1 -> 2029 | L105: =K105+1 -> 2030
B106: £ in millions, unless stated | F106: H = Historical | L106: F = Forecast
B108: Operating Activities
B110: Net Profit / (Loss) | H110: =H34 -> -1.6504156e+08 | I110: =I34 -> -1.8223903e+08 | J110: =J34 -> -1.9331614e+08 | K110: =K34 -> -2.0323542e+08 | L110: =L34 -> -2.0617753e+08
B111: PP&E depreciation | H111: =H442 -> 32655302 | I111: =I442 -> 36610878 | J111: =J442 -> 40634993 | K111: =K442 -> 44819639 | L111: =L442 -> 49234863
B112: ROU depreciation | H112: =H395 -> 17210000 | I112: =I395 -> 17210000 | J112: =J395 -> 17210000 | K112: =K395 -> 17210000 | L112: =L395 -> 17210000
B113: Amortization of Intangible Assets | H113: =H469 -> 95890948 | I113: =I469 -> 1.1245366e+08 | J113: =J469 -> 1.2930337e+08 | K113: =K469 -> 1.4682524e+08 | L113: =L469 -> 1.6531259e+08
B114: (Increase) / decrease in working capital | H114: =-H352 -> 51450978 | I114: =-I352 -> -449927.17 | J114: =-J352 -> 6460048.1 | K114: =-K352 -> 10314283 | L114: =-L352 -> 14494567
B115: Add back total tax expense | H115: =-H33 -> 0 | I115: =-I33 -> 0 | J115: =-J33 -> 0 | K115: =-K33 -> 0 | L115: =-L33 -> 0
B116: Minus cash paid | H116: =-H652 -> 0 | I116: =-I652 -> 0 | J116: =-J652 -> 0 | K116: =-K652 -> 0 | L116: =-L652 -> 0
B117: Change in DTA
B118: (Increase) / decrease in provisions | H118: =-H325 -> -19038262 | I118: =-I325 -> -5962415.4 | J118: =-J325 -> -5962415.4 | K118: =-K325 -> -5962415.4 | L118: =-L325 -> -5962415.4
B120: Cash Flow from Operations | H120: =SUM(H110:H113)+SUM(H114:H118) -> 13127404 | I120: =SUM(I110:I113)+SUM(I114:I118) -> -22376830 | J120: =SUM(J110:J113)+SUM(J114:J118) -> -5670140.2 | K120: =SUM(K110:K113)+SUM(K114:K118) -> 9971327.1 | L120: =SUM(L110:L113)+SUM(L114:L118) -> 34112074
B122: Investing Activities
B124: Capital expenditure on PP&E | H124: =-H428 -> -19753017 | I124: =-I428 -> -19802742 | J124: =-J428 -> -20438417 | K124: =-K428 -> -21408039 | L124: =-L428 -> -22744199
B125: Additions to intangibles | H125: =-H455 -> -82709482 | I125: =-I455 -> -82917686 | J125: =-J455 -> -85579376 | K125: =-K455 -> -89639358 | L125: =-L455 -> -95234104
B127: Cash flow from investing | H127: =H124+H125 -> -1.024625e+08 | I127: =I124+I125 -> -1.0272043e+08 | J127: =J124+J125 -> -1.0601779e+08 | K127: =K124+K125 -> -1.110474e+08 | L127: =L124+L125 -> -1.179783e+08
B129: Financing Activities
B131: Borrowing Issuance | H131: =H557 -> 150000000 | I131: =I557 -> 60923303 | J131: =J557 -> 1.3859766e+08 | K131: =K557 -> 3.9849309e+08 | L131: =L557 -> 1.1241476e+08
B132: Borrowing Repayments | H132: =H558 -> -233900000 | I132: =I558 -> 0 | J132: =J558 -> 0 | K132: =K558 -> -269700000 | L132: =L558 -> 0
B133: Lease principal payments | H133: =-H415 -> -25365000 | I133: =-I415 -> -26125950 | J133: =-J415 -> -26909728 | K133: =-K415 -> -27717020 | L133: =-L415 -> -28548531
B134: Dividends | H134: =-H688 -> 0 | I134: =-I688 -> 0 | J134: =-J688 -> 0 | K134: =-K688 -> 0 | L134: =-L688 -> 0
B135: Share buybacks | H135: =H695 -> 0 | I135: =I695 -> 0 | J135: =J695 -> 0 | K135: =K695 -> 0 | L135: =L695 -> 0
B137: Cash flow from financing | H137: =SUM(H131:H135) -> -109265000 | I137: =SUM(I131:I135) -> 34797353 | J137: =SUM(J131:J135) -> 1.1168793e+08 | K137: =SUM(K131:K135) -> 1.0107607e+08 | L137: =SUM(L131:L135) -> 83866229
B139: Financing Activities
...

Sheet Charts
B2: Index | C2: 2024 | D2: 2025 | E2: 2026 | F2: 2027 | G2: 2028 | H2: 2029 | I2: 2030
B3: Active Customers | C3: =Model!F157/Model!$F$157*100 -> 100 | D3: =Model!G157/Model!$F$157*100 -> 86.294416 | E3: =Model!H157/Model!$F$157*100 -> 83.756345 | F3: =Model!I157/Model!$F$157*100 -> 81.218274 | G3: =Model!J157/Model!$F$157*100 -> 81.218274 | H3: =Model!K157/Model!$F$157*100 -> 82.48731 | I3: =Model!L157/Model!$F$157*100 -> 85.025381
B4: Orders | C4: =Model!F158/Model!$F$158*100 -> 100 | D4: =Model!G158/Model!$F$158*100 -> 83.823529 | E4: =Model!H158/Model!$F$158*100 -> 81.358131 | F4: =Model!I158/Model!$F$158*100 -> 78.892734 | G4: =Model!J158/Model!$F$158*100 -> 78.892734 | H4: =Model!K158/Model!$F$158*100 -> 80.125433 | I4: =Model!L158/Model!$F$158*100 -> 82.59083
B5: GMV | C5: =Model!F159/Model!$F$159*100 -> 100 | D5: =Model!G159/Model!$F$159*100 -> 84.183289 | E5: =Model!H159/Model!$F$159*100 -> 84.087404 | F5: =Model!I159/Model!$F$159*100 -> 84.311637 | G5: =Model!J159/Model!$F$159*100 -> 87.178232 | H5: =Model!K159/Model!$F$159*100 -> 91.550766 | I5: =Model!L159/Model!$F$159*100 -> 97.576215

Sheet DCF
B2: =Cover!$B$2 -> ASOS PLC
B3: Discounted Cash Flow | J3: ="Currently Running: "&CHOOSE(Assumptions!$B$10,Assumptions!$F$15,Assumptions!$F$16,Assumptions!$F$17)&"Scenario" -> Currently Running: Base Scenario
F6: 2026 | G6: =F6+1 -> 2027 | H6: =G6+1 -> 2028 | I6: =H6+1 -> 2029 | J6: =I6+1 -> 2030
B7: £ in millions, unless stated | J7: F = Forecast
B9: Unlevered free cash flow
B11: EBIT | F11: =Model!H18 -> -1.1319096e+08 | G11: =Model!I18 -> -1.2996348e+08 | H11: =Model!J18 -> -1.3453365e+08 | I11: =Model!K18 -> -1.2929293e+08 | J11: =Model!L18 -> -1.1715842e+08
B12: Tax Rate | F12: =IF(F11<0, 0, Model!H647) -> 0 | G12: =IF(G11<0, 0, Model!I647) -> 0 | H12: =IF(H11<0, 0, Model!J647) -> 0 | I12: =IF(I11<0, 0, Model!K647) -> 0 | J12: =IF(J11<0, 0, Model!L647) -> 0
B13: NOPAT | F13: =(1-F12)*F11 -> -1.1319096e+08 | G13: =(1-G12)*G11 -> -1.2996348e+08 | H13: =(1-H12)*H11 -> -1.3453365e+08 | I13: =(1-I12)*I11 -> -1.2929293e+08 | J13: =(1-J12)*J11 -> -1.1715842e+08
B14: Depreciation and Amortization | F14: =Model!H24 -> 1.4575625e+08 | G14: =Model!I24 -> 1.6627454e+08 | H14: =Model!J24 -> 1.8714836e+08 | I14: =Model!K24 -> 2.0885488e+08 | J14: =Model!L24 -> 2.3175745e+08
B15: CFI (Capex + Additions to Intangibles) | F15: =Model!H127 -> -1.024625e+08 | G15: =Model!I127 -> -1.0272043e+08 | H15: =Model!J127 -> -1.0601779e+08 | I15: =Model!K127 -> -1.110474e+08 | J15: =Model!L127 -> -1.179783e+08
B16: Change in NWC | F16: =Model!H352 -> -51450978 | G16: =Model!I352 -> 449927.17 | H16: =Model!J352 -> -6460048.1 | I16: =Model!K352 -> -10314283 | J16: =Model!L352 -> -14494567
B17: Unlevered Free Cash Flow | F17: =SUM(F13:F15)-F16 -> -18446233 | G17: =SUM(G13:G15)-G16 -> -66859292 | H17: =SUM(H13:H15)-H16 -> -46943033 | I17: =SUM(I13:I15)-I16 -> -21171159 | J17: =SUM(J13:J15)-J16 -> 11115300
B18: Discount Factor | F18: =1/(1+$J$24)^F19 -> 0.89227856 | G18: =1/(1+$J$24)^G19 -> 0.79616104 | H18: =1/(1+$J$24)^H19 -> 0.71039743 | I18: =1/(1+$J$24)^I19 -> 0.6338724 | J18: =1/(1+$J$24)^J19 -> 0.56559075
B19: Discount period (years from valuation date) | F19: 1 | G19: =F19+1 -> 2 | H19: =G19+1 -> 3 | I19: =H19+1 -> 4 | J19: =I19+1 -> 5
B21: Weighted Average Cost of Capital and DCF
B23: Weighted Average Cost of Capital | G23: Discounted Cash Flow
B24: Cost of Debt | E24: 0.12 | G24: WACC | J24: =E33 -> 0.12072624
B25: Cost of Equity | E25: =E29+(E31*E30) -> 0.1444 | G25: Terminal growth | J25: 0.025
B26: Debt-to-Equity Ratio | E26: =-Model!F87/Model!F93 -> 0.77047376 | G26: PV explicit FCF | J26: =SUMPRODUCT(F17:J17,F18:J18) -> -1.1017125e+08
B27: Weight of Debt | E27: =E26/(1+E26) -> 0.43517943 | G27: Terminal value | J27: =J17*(1+J25)/(J24-J25) -> 1.1901839e+08
B28: Weight of Equity | E28: =1-E27 -> 0.56482057 | G28: PV terminal value | J28: =J18*J27 -> 67315699
B29: Risk-free rate | E29: 0.052 | G29: Enterprise Value | J29: =J26+J28 -> -42855554
B30: Equity risk premium | E30: 0.042 | G30: Less Net Debt | J30: =Model!H622 -> 4.9853509e+08
B31: Market beta | E31: 2.2 | G31: Equity Value | J31: =J29-J30 -> -5.4139065e+08
B32: Tax Rate | E32: =Model!$H$647 -> 0.25
B33: Weighted Average Cost of Capital (WACC) | E33: =(E28*E25)+(E27*E24*(1-E32)) -> 0.12072624

Sheet LBO
B2: =Cover!$B$2 -> ASOS PLC
B3: LBO Returns | F3: ="Currently Running: "&CHOOSE(Assumptions!$B$10,Assumptions!$F$15,Assumptions!$F$16,Assumptions!$F$17)&"Scenario" -> Currently Running: Base Scenario | I3: ="Currently Running: "&CHOOSE(Assumptions!$B$10,Assumptions!$F$15,Assumptions!$F$16,Assumptions!$F$17)&"Scenario" -> Currently Running: Base Scenario
B5: £ in millions, unless stated
B7: Entry and Sources
B9: Entry Assumptions & Valuation
B10: Entry EBITDA | F10: =Model!H25 -> 32565288
B11: Entry multiple | F11: =F39 -> 4.5
B12: Net Debt | F12: =Model!H622 -> 4.9853509e+08
B13: Implied Enterprise Value | F13: =F10*F11 -> 1.465438e+08
B15: Uses of Funds
B16: Purchase enterprise value | F16: =SUM(F12:F13) -> 6.4507889e+08
B17: Transaction fees | F17: =F16*F40 -> 12901578
B18: Minimum Cash Required | F18: =Model!H498 -> 30000000
B20: Total Uses | F20: =SUM(F16:F18) -> 6.8798047e+08
B21: New debt | F21: =F10*F41 -> 97695863
B22: Sponsor equity | F22: =F20-F21 -> 5.902846e+08
B24: Exit Valuation
B26: Exit Assumptions & Valuation
B27: Exit EBITDA | F27: =Model!L25 -> 1.1459904e+08
B28: Exit Multiple | F28: =F44 -> 6
B29: Exit enterprise value | F29: =F28*F27 -> 6.8759422e+08
B30: Less exit net debt (LBO capital structure) | F30: ='LBO Debt'!J22 -> 2.530929e+08
B32: Exit equity value | F32: =F29-F30 -> 4.3450131e+08
B33: MOIC | F33: =F32/F22 -> 0.73608783
B34: IRR | F34: =F33^(1/5)-1 -> -0.059441252
B37: LBO Inputs
B39: Entry multiple (x 2026 EBITDA) | F39: 4.5
B40: Transaction Fees | F40: 0.02
B41: Entry Leverage | F41: 3
B42: LBO debt interest rate | F42: 0.09
B43: Mandatory Amortization | F43: 0.01
B44: Exit multiple (x 2030 EBITDA) | F44: 6

Sheet LBO Debt
B2: =Cover!$B$2 -> ASOS PLC
B3: LBO Debt Schedule | J3: ="Currently Running: "&CHOOSE(Assumptions!$B$10,Assumptions!$F$15,Assumptions!$F$16,Assumptions!$F$17)&"Scenario" -> Currently Running: Base Scenario
F5: Fiscal Year ending August 30
F6: 2026 | G6: =F6+1 -> 2027 | H6: =G6+1 -> 2028 | I6: =H6+1 -> 2029 | J6: =I6+1 -> 2030
B7: £ in millions, unless stated | J7: F = Forecast
B9: LBO Debt Schedule
B11: Opening LBO Debt | F11: =LBO!F21 -> 97695863 | G11: =F20 -> 96718905 | H11: =G20 -> 95751716 | I11: =H20 -> 94794199 | J11: =I20 -> 93846257
B12: Mandatory amortization | F12: =F11*LBO!$F$43 -> 976958.63 | G12: =G11*LBO!$F$43 -> 967189.05 | H12: =H11*LBO!$F$43 -> 957517.16 | I12: =I11*LBO!$F$43 -> 947941.99 | J12: =J11*LBO!$F$43 -> 938462.57
B13: Interest expense (debt and revolver, on opening balances) | F13: =F11*LBO!$F$42 -> 8792627.7 | G13: =G11*LBO!$F$42 -> 8704701.4 | H13: =H11*LBO!$F$42 -> 8617654.4 | I13: =I11*LBO!$F$42 -> 8531477.9 | J13: =J11*LBO!$F$42 -> 8446163.1
B14: After-tax interest | F14: =IF(Model!F18>0, F13*(1-Model!H647), F13) -> 8792627.7 | G14: =IF(Model!G18>0, G13*(1-Model!I647), G13) -> 8704701.4 | H14: =IF(Model!H18>0, H13*(1-Model!J647), H13) -> 8617654.4 | I14: =IF(Model!I18>0, I13*(1-Model!K647), I13) -> 8531477.9 | J14: =IF(Model!J18>0, J13*(1-Model!L647), J13) -> 8446163.1
B15: Minimum cash requirement | F15: =Model!H498 -> 30000000 | G15: =Model!I498 -> 30000000 | H15: =Model!J498 -> 30000000 | I15: =Model!K498 -> 30000000 | J15: =Model!L498 -> 30000000
B16: Opening cash | F16: =LBO!$F$18 -> 30000000 | G16: =F21 -> 1784181 | H16: =G21 -> -74747002 | I16: =H21 -> -1.3126521e+08 | J16: =I21 -> -1.6191578e+08
B17: Unlevered free cash flow | F17: =DCF!F17 -> -18446233 | G17: =DCF!G17 -> -66859292 | H17: =DCF!H17 -> -46943033 | I17: =DCF!I17 -> -21171159 | J17: =DCF!J17 -> 11115300
B18: Cash before sweep | F18: =F16+F17-F14-F12 -> 1784181 | G18: =G16+G17-G14-G12 -> -74747002 | H18: =H16+H17-H14-H12 -> -1.3126521e+08 | I18: =I16+I17-I14-I12 -> -1.6191578e+08 | J18: =J16+J17-J14-J12 -> -1.6018511e+08
B19: Optional repayment (cash sweep) | F19: =MIN(MAX(0,F18-F15), F11-F12) -> 0 | G19: =MIN(MAX(0,G18-G15), G11-G12) -> 0 | H19: =MIN(MAX(0,H18-H15), H11-H12) -> 0 | I19: =MIN(MAX(0,I18-I15), I11-I12) -> 0 | J19: =MIN(MAX(0,J18-J15), J11-J12) -> 0
B20: Ending LBO Debt | F20: =F11-F12-F19 -> 96718905 | G20: =G11-G12-G19 -> 95751716 | H20: =H11-H12-H19 -> 94794199 | I20: =I11-I12-I19 -> 93846257 | J20: =J11-J12-J19 -> 92907794
B21: Ending cash | F21: =F18-F19 -> 1784181 | G21: =G18-G19 -> -74747002 | H21: =H18-H19 -> -1.3126521e+08 | I21: =I18-I19 -> -1.6191578e+08 | J21: =J18-J19 -> -1.6018511e+08
B22: Net debt (debt + revolver - cash) | F22: =F20-F21 -> 94934724 | G22: =G20-G21 -> 1.7049872e+08 | H22: =H20-H21 -> 2.260594e+08 | I22: =I20-I21 -> 2.5576204e+08 | J22: =J20-J21 -> 2.530929e+08
