Workbook

Sheet Cover
B2: Greggs
B4: Modelled by Peter Hopkinson
B5: =DATE(2026, 10, 11) -> 46306

Sheet DCF_Valuation
B2: =Cover!$B$2 -> Greggs
B3: Discounted Cash Flow - FCFF and Equity Bridge
F5: Fiscal Years Ending December 31
F6: 2024 | G6: 2025 | H6: =G6+1 -> 2026 | I6: =H6+1 -> 2027 | J6: =I6+1 -> 2028 | K6: =J6+1 -> 2029 | L6: =K6+1 -> 2030
B7: (£m in millions) | F7: H = Historical | L7: F = Forecast
B9: Unlevered Free Cash Flow
B11: EBIT | H11: =Model!H18 -> 244.63268 | I11: =Model!I18 -> 259.07778 | J11: =Model!J18 -> 282.71945 | K11: =Model!K18 -> 315.41621 | L11: =Model!L18 -> 360.24654
B12: Tax Rate | H12: =Model!H489 -> 0.26 | I12: =Model!I489 -> 0.26 | J12: =Model!J489 -> 0.26 | K12: =Model!K489 -> 0.26 | L12: =Model!L489 -> 0.26
B13: NOPAT | H13: =H11*(1-H12) -> 181.02818 | I13: =I11*(1-I12) -> 191.71755 | J13: =J11*(1-J12) -> 209.21239 | K13: =K11*(1-K12) -> 233.40799 | L13: =L11*(1-L12) -> 266.58244
B14: (+) D&A | H14: =-Model!H24 -> 147.10816 | I14: =-Model!I24 -> 174.57844 | J14: =-Model!J24 -> 200.81556 | K14: =-Model!K24 -> 226.16294 | L14: =-Model!L24 -> 251.80238
B15: (-) Capital expenditure | H15: =-Model!H115 -> 203.05822 | I15: =-Model!I115 -> 192.77425 | J15: =-Model!J115 -> 179.1654 | K15: =-Model!K115 -> 176.3646 | L15: =-Model!L115 -> 187.03805
B16: (+) Change in NWC | H16: =Model!H286 -> 6.5086943 | I16: =Model!I286 -> 11.425813 | J16: =Model!J286 -> 10.422619 | K16: =Model!K286 -> 9.4733296 | L16: =Model!L286 -> 8.3877543
B17: FCFF* | H17: =H13+H14-H15+H16 -> 131.58682 | I17: =I13+I14-I15+I16 -> 184.94756 | J17: =J13+J14-J15+J16 -> 241.28517 | K17: =K13+K14-K15+K16 -> 292.67965 | L17: =L13+L14-L15+L16 -> 339.73452
B19: Discounted Cash Flow
B20: Discount period | H20: 1 | I20: =H20+1 -> 2 | J20: =I20+1 -> 3 | K20: =J20+1 -> 4 | L20: =K20+1 -> 5
B21: PV of FCFF | H21: =H17/(1+$D$33)^H20 -> 121.57046 | I21: =I17/(1+$D$33)^I20 -> 157.86283 | J21: =J17/(1+$D$33)^J20 -> 190.27317 | K21: =K17/(1+$D$33)^K20 -> 213.23334 | L21: =L17/(1+$D$33)^L20 -> 228.67459
B23: WACC | F23: Terminal Assumptions
B25: Risk-free rate | D25: 0.05527 | F25: Terminal Growth | H25: 0.02
B26: Equity-risk premium | D26: =D77 -> 0.0498 | F26: Final Forecast Year | H26: =L6 -> 2030
B27: Beta | D27: =D71 -> 0.715331 | F27: Valuation Method | H27: Gordon Growth
B28: Cost of Equity | D28: =D25+D26*D27 -> 0.090893484 | F28: Shares outstanding | H28: =Model!D41 -> 102250000
B29: Cost of Debt | D29: 0.059
B30: Tax Rate | D30: 0.26
B31: Equity weight | D31: 0.82
B32: Debt weight | D32: 0.18
B33: WACC | D33: =D28*D31+D32*D29*(1-D30) -> 0.082391457
B36: Valuation Output
B38: PV of forecast FCFF | D38: =SUM(H21:L21) -> 911.61439
B39: Terminal Value | D39: =(L17*(1+H25))/(D33+H25) -> 3384.3567
B40: Enterprise Value | D40: =SUM(D38:D39) -> 4295.9711
B42: (+) Cash | D42: =Model!G56 -> 70.8
B43: (-) Financial Debt | D43: =-Model!G74 -> 25
B44: (-) Lease liabilities | D44: =-Model!G77-Model!G70 -> 449.8
B45: Equity Value | D45: =D40+D42-D43-D44 -> 3891.9711
B46: Implied share price | D46: =D45/H28 * 1000000 -> 38.063287
B49: =Cover!$B$2 -> Greggs
B50: Discounted Cash Flow - WACC Components
B52: (£m in millions)
B54: Comparable Company Beta
B56: Company | D56: Ticker | E56: Levered ϐ | F56: Market Cap | G56: Debt | H56: D/E | I56: Tax | J56: Unlevered ϐ | K56: Observation Date
B58: Mitchells & Butlers | D58: MAB | E58: 1.23 | F58: 1749000000 | G58: =1292000000+216000000 -> 1508000000 | H58: =G58/F58 -> 0.86220698 | I58: 0.25 | J58: =E58/(1+(1-I58)*(H58)) -> 0.74696875 | K58: 46308
B59: J D Weatherspoon | D59: JDW | E59: 1.13 | F59: 929971000 | G59: =49582000+1087794000 -> 1137376000 | H59: =G59/F59 -> 1.2230231 | I59: 0.25 | J59: =E59/(1+(1-I59)*(H59)) -> 0.58938052 | K59: 46308
B60: Domino's Pizza Group | D60: DOM | E60: 1.21 | F60: 876663000 | G60: =526000000+22900000 -> 548900000 | H60: =G60/F60 -> 0.62612429 | I60: 0.25 | J60: =E60/(1+(1-I60)*(H60)) -> 0.82335709 | K60: 46308
B61: Young & Co's Brewery | D61: YNGN | E61: 0.9 | F61: 427403000 | G61: =40600000+274500000 -> 315100000 | H61: =G61/F61 -> 0.7372433 | I61: 0.25 | J61: =E61/(1+(1-I61)*(H61)) -> 0.5795487 | K61: 46308
B62: Whitbread PLC | D62: WTB.L | E62: 0.67 | F62: 4268000000 | G62: =175600000+5290500000 -> 5466100000 | H62: =G62/F62 -> 1.280717 | I62: 0.25 | J62: =E62/(1+(1-I62)*(H62)) -> 0.34174298 | K62: 46308
B63: * All of the above debt figures include both financial debt and lease liabilities
B65: Metrics | D65: Values | E65: Notes
B66: Mean unlevered beta | D66: =AVERAGE(J58:J62) -> 0.61619961
B67: Median unlevered beta | D67: =MEDIAN(J58:J62) -> 0.58938052
B68: Market cap | D68: 2184000000 | E68: * Taken on the 13th October 2026
B69: Debt-to-equity | D69: =ABS((Model!G74+Model!G77+Model!G70)*1000000)/D68 -> 0.21739927
B70: Tax Rate | D70: 0.26
B71: Levered beta | D71: =D66*(1+(1-D70)*D69) -> 0.715331
B73: Equity Risk Premium
B75: Market implied ERP | D75: 0.042 | F75: Source - Damodaran, July 2026
B76: UK specific ERP | D76: 0.0078
B77: Total ERP | D77: =SUM(D75:D76) -> 0.0498

Sheet Assumptions
B2: =Cover!$B$2 -> Greggs
B3: Assumptions | L3: ="Currently Running: "&CHOOSE(Assumptions!$B$10,Assumptions!$F$15,Assumptions!$F$16,Assumptions!$F$17)&"Scenario" -> Currently Running: Base Scenario
F5: Fiscal Years Ending December 31
F6: 2024 | G6: 2025 | H6: =G6+1 -> 2026 | I6: =H6+1 -> 2027 | J6: =I6+1 -> 2028 | K6: =J6+1 -> 2029 | L6: =K6+1 -> 2030
B7: (£m in millions) | F7: H = Historical | L7: F = Forecast
B9: Scenario Selector:
B10: 1
B12: Macro Assumptions
B14: Wage Inflation | F14: Selected | H14: =CHOOSE($B$10,H15,H16,H17) -> 0.04 | I14: =CHOOSE($B$10,I15,I16,I17) -> 0.04 | J14: =CHOOSE($B$10,J15,J16,J17) -> 0.035 | K14: =CHOOSE($B$10,K15,K16,K17) -> 0.03 | L14: =CHOOSE($B$10,L15,L16,L17) -> 0.025
F15: Base | H15: 0.04 | I15: 0.04 | J15: 0.035 | K15: 0.03 | L15: 0.025
F16: Upside | H16: 0.0375 | I16: 0.03 | J16: 0.025 | K16: 0.02 | L16: 0.02
F17: Downside | H17: 0.045 | I17: 0.05 | J17: 0.0475 | K17: 0.04 | L17: 0.035
B19: Food Cost Inflation | F19: Selected | H19: =CHOOSE($B$10,H20,H21,H22) -> 0.04 | I19: =CHOOSE($B$10,I20,I21,I22) -> 0.04 | J19: =CHOOSE($B$10,J20,J21,J22) -> 0.035 | K19: =CHOOSE($B$10,K20,K21,K22) -> 0.03 | L19: =CHOOSE($B$10,L20,L21,L22) -> 0.025
F20: Base | H20: 0.04 | I20: 0.04 | J20: 0.035 | K20: 0.03 | L20: 0.025
F21: Upside | H21: 0.0375 | I21: 0.03 | J21: 0.025 | K21: 0.02 | L21: 0.02
F22: Downside | H22: 0.045 | I22: 0.05 | J22: 0.0475 | K22: 0.04 | L22: 0.035
B24: Inflation | F24: Selected | H24: =CHOOSE($B$10,H25,H26,H27) -> 0.04 | I24: =CHOOSE($B$10,I25,I26,I27) -> 0.04 | J24: =CHOOSE($B$10,J25,J26,J27) -> 0.035 | K24: =CHOOSE($B$10,K25,K26,K27) -> 0.03 | L24: =CHOOSE($B$10,L25,L26,L27) -> 0.025
F25: Base | H25: 0.04 | I25: 0.04 | J25: 0.035 | K25: 0.03 | L25: 0.025
F26: Upside | H26: 0.0375 | I26: 0.03 | J26: 0.025 | K26: 0.02 | L26: 0.02
F27: Downside | H27: 0.045 | I27: 0.05 | J27: 0.0475 | K27: 0.04 | L27: 0.035
B30: Revenue Assumptions
B33: Like-for-like sales growth rate - own stores | F33: Selected | H33: =CHOOSE($B$10,H34,H35,H36) -> 0.035 | I33: =CHOOSE($B$10,I34,I35,I36) -> 0.035 | J33: =CHOOSE($B$10,J34,J35,J36) -> 0.035 | K33: =CHOOSE($B$10,K34,K35,K36) -> 0.035 | L33: =CHOOSE($B$10,L34,L35,L36) -> 0.035
F34: Base | H34: 0.035 | I34: 0.035 | J34: 0.035 | K34: 0.035 | L34: 0.035
F35: Upside | H35: 0.05 | I35: 0.05 | J35: 0.05 | K35: 0.05 | L35: 0.05
F36: Downside | H36: 0 | I36: 0.005 | J36: 0.015 | K36: 0.02 | L36: 0.02
B38: Like-for-like sales growth rate - franchise stores | F38: Selected | H38: =CHOOSE($B$10,H39,H40,H41) -> 0.06 | I38: =CHOOSE($B$10,I39,I40,I41) -> 0.05 | J38: =CHOOSE($B$10,J39,J40,J41) -> 0.045 | K38: =CHOOSE($B$10,K39,K40,K41) -> 0.04 | L38: =CHOOSE($B$10,L39,L40,L41) -> 0.04
F39: Base | H39: 0.06 | I39: 0.05 | J39: 0.045 | K39: 0.04 | L39: 0.04
F40: Upside | H40: 0.09 | I40: 0.08 | J40: 0.065 | K40: 0.06 | L40: 0.05
F41: Downside | H41: 0.005 | I41: 0.005 | J41: 0.01 | K41: 0.015 | L41: 0.02

Sheet Model
B3: =Cover!$B$2 -> Greggs
B4: Financial Statements - Income Statement | L4: ="Currently Running: "&CHOOSE(Assumptions!$B$10,Assumptions!$F$15,Assumptions!$F$16,Assumptions!$F$17)&"Scenario" -> Currently Running: Base Scenario
F6: Fiscal Years Ending December 31
F7: 2024 | G7: 2025 | H7: =G7+1 -> 2026 | I7: =H7+1 -> 2027 | J7: =I7+1 -> 2028 | K7: =J7+1 -> 2029 | L7: =K7+1 -> 2030
B8: (£m in millions) | F8: H = Historical | L8: F = Forecast
B10: Revenue | F10: 2014.4 | G10: 2151.2 | H10: =H217 -> 2320.6653 | I10: =I217 -> 2487.4096 | J10: =J217 -> 2654.3023 | K10: =K217 -> 2821.8337 | L10: =L217 -> 2992.6089
B11: Cost of Sales | F11: -770.8 | G11: -829.1 | H11: =-H264 -> -874.83541 | I11: =-I264 -> -939.01394 | J11: =-J264 -> -999.37957 | K11: =-K264 -> -1056.1986 | L11: =-L264 -> -1109.2715
B12: Gross profit | F12: =SUM(F10:F11) -> 1243.6 | G12: =SUM(G10:G11) -> 1322.1 | H12: =SUM(H10:H11) -> 1445.8299 | I12: =SUM(I10:I11) -> 1548.3957 | J12: =SUM(J10:J11) -> 1654.9227 | K12: =SUM(K10:K11) -> 1765.6351 | L12: =SUM(L10:L11) -> 1883.3374
B13: Gross profit margin | F13: =F12/F10 -> 0.61735504 | G13: =G12/G10 -> 0.61458721 | H13: =H12/H10 -> 0.62302388 | I13: =I12/I10 -> 0.62249324 | J13: =J12/J10 -> 0.6234869 | K13: =K12/K10 -> 0.62570487 | L13: =L12/L10 -> 0.62932962
B15: Distribution and selling costs | F15: -950.1 | G15: -1036.3 | H15: =-H265 -> -1093.4651 | I15: =-I265 -> -1173.6825 | J15: =-J265 -> -1249.1341 | K15: =-K265 -> -1320.1527 | L15: =-L265 -> -1386.489
B16: Administrative expenses | F16: -97.9 | G16: -102.1 | H16: =-H266 -> -107.73211 | I16: =-I266 -> -115.63542 | J16: =-J266 -> -123.06918 | K16: =-K266 -> -130.06619 | L16: =-L266 -> -136.60188
B17: Other income | F17: 13.8 | G17: 0 | H17: =G17 -> 0 | I17: =H17 -> 0 | J17: =I17 -> 0 | K17: =J17 -> 0 | L17: =K17 -> 0
B18: EBIT | F18: =SUM(F15:F17)+F12 -> 209.4 | G18: =SUM(G15:G17)+G12 -> 183.7 | H18: =SUM(H15:H17)+H12 -> 244.63268 | I18: =SUM(I15:I17)+I12 -> 259.07778 | J18: =SUM(J15:J17)+J12 -> 282.71945 | K18: =SUM(K15:K17)+K12 -> 315.41621 | L18: =SUM(L15:L17)+L12 -> 360.24654
B19: EBIT Margin | F19: =F18/F10 -> 0.10395155 | G19: =G18/G10 -> 0.085394199 | H19: =H18/H10 -> 0.10541489 | I19: =I18/I10 -> 0.10415565 | J19: =J18/J10 -> 0.10651366 | K19: =K18/K10 -> 0.11177704 | L19: =L18/L10 -> 0.12037876
B21: Depreciation of PP&E | F21: =-F385 -> -76.6 | G21: =-G385 -> -90.7 | H21: =-H385 -> -92.492661 | I21: =-I385 -> -110.48126 | J21: =-J385 -> -127.1501 | K21: =-K385 -> -142.87305 | L21: =-L385 -> -158.86276
B22: Depreciation of ROU assets | F22: =-F331/1000000 -> -59.2 | G22: =-G331/1000000 -> -65.2 | H22: =-H331/1000000 -> -44.275 | I22: =-I331/1000000 -> -50.150625 | J22: =-J331/1000000 -> -55.862625 | K22: =-K331/1000000 -> -61.379948 | L22: =-L331/1000000 -> -66.668848
B23: Amortisation | F23: =-F407 -> -4.2 | G23: =-G407 -> -4.7 | H23: =-H407 -> -10.340499 | I23: =-I407 -> -13.946555 | J23: =-J407 -> -17.802839 | K23: =-K407 -> -21.909941 | L23: =-L407 -> -26.270773
B24: Depreciation and Amortization | F24: =SUM(F21:F23) -> -140 | G24: =SUM(G21:G23) -> -160.6 | H24: =SUM(H21:H23) -> -147.10816 | I24: =SUM(I21:I23) -> -174.57844 | J24: =SUM(J21:J23) -> -200.81556 | K24: =SUM(K21:K23) -> -226.16294 | L24: =SUM(L21:L23) -> -251.80238
B25: EBITDA | F25: =F18-F24 -> 349.4 | G25: =G18-G24 -> 344.3 | H25: =H18-H24 -> 391.74084 | I25: =I18-I24 -> 433.65621 | J25: =J18-J24 -> 483.53501 | K25: =K18-K24 -> 541.57914 | L25: =L18-L24 -> 612.04892
B26: EBITDA Margin | F26: =F25/F10 -> 0.17345115 | G26: =G25/G10 -> 0.1600502 | H26: =H25/H10 -> 0.1688054 | I26: =I25/I10 -> 0.17434049 | J26: =J25/J10 -> 0.18217029 | K26: =K25/K10 -> 0.19192454 | L26: =L25/L10 -> 0.20452019
B28: Finance income | F28: 8.1 | G28: 1.8 | H28: =H466 -> 0.708 | I28: =I466 -> 0.47724928 | J28: =J466 -> 1.0000971 | K28: =K466 -> 2.0292823 | L28: =L466 -> 3.4939014
B29: Finance expense | F29: -13.6 | G29: -18.1 | H29: =-H460+H350 -> -28.338 | I29: =-I460+I350 -> -27.37728 | J29: =-J460+J350 -> -27.700667 | K29: =-K460+K350 -> -27.936357 | L29: =-L460+L350 -> -28.059676
B30: Net finance costs | F30: =SUM(F28:F29) -> -5.5 | G30: =SUM(G28:G29) -> -16.3 | H30: =SUM(H28:H29) -> -27.63 | I30: =SUM(I28:I29) -> -26.900031 | J30: =SUM(J28:J29) -> -26.70057 | K30: =SUM(K28:K29) -> -25.907074 | L30: =SUM(L28:L29) -> -24.565775
B32: Profit before tax | F32: =F18+F30 -> 203.9 | G32: =G18+G30 -> 167.4 | H32: =H18+H30 -> 217.00268 | I32: =I18+I30 -> 232.17775 | J32: =J18+J30 -> 256.01888 | K32: =K18+K30 -> 289.50913 | L32: =L18+L30 -> 335.68076
B34: Taxation | F34: -50.5 | G34: -46.1 | H34: =-H502 -> -56.420697 | I34: =-I502 -> -60.366214 | J34: =-J502 -> -66.564909 | K34: =-K502 -> -75.272374 | L34: =-L502 -> -87.276998
B35: Net Profit | F35: =F32+F34 -> 153.4 | G35: =G32+G34 -> 121.3 | H35: =H32+H34 -> 160.58198 | I35: =I32+I34 -> 171.81153 | J35: =J32+J34 -> 189.45397 | K35: =K32+K34 -> 214.23676 | L35: =L32+L34 -> 248.40376
B36: Net Profit Margin | F36: =F35/F10 -> 0.076151708 | G36: =G35/G10 -> 0.056387133 | H36: =H35/H10 -> 0.069196528 | I36: =I35/I10 -> 0.069072472 | J36: =J35/J10 -> 0.071376186 | K36: =K35/K10 -> 0.075921114 | L36: =L35/L10 -> 0.083005757
B38: Earning per share
B39: - Basic | D39: pence per share | H39: =(H35*1000000/$D$41)*100 -> 157.0484 | I39: =(I35*1000000/$D$41)*100 -> 168.03084 | J39: =(J35*1000000/$D$41)*100 -> 185.28506 | K39: =(K35*1000000/$D$41)*100 -> 209.5225 | L39: =(L35*1000000/$D$41)*100 -> 242.93767
B41: Shares Trading | D41: 102250000
B45: =Cover!$B$2 -> Greggs
B46: Financial Statements - Balance Sheet | L46: ="Currently Running: "&CHOOSE(Assumptions!$B$10,Assumptions!$F$15,Assumptions!$F$16,Assumptions!$F$17)&"Scenario" -> Currently Running: Base Scenario
F48: Fiscal Years Ending December 31
F49: 2024 | G49: 2025 | H49: =G49+1 -> 2026 | I49: =H49+1 -> 2027 | J49: =I49+1 -> 2028 | K49: =J49+1 -> 2029 | L49: =K49+1 -> 2030
B50: (£m in millions) | F50: H = Historical | L50: F = Forecast
B52: Assets
B54: Inventories | F54: 55.2 | G54: 55.7 | H54: =H281 -> 58.772563 | I54: =I281 -> 63.084159 | J54: =J281 -> 67.1396 | K54: =K281 -> 70.956774 | L54: =L281 -> 74.522278
B55: Trade and other receivables | F55: 62.4 | G55: 69.4 | H55: =H280 -> 74.867132 | I55: =I280 -> 80.24648 | J55: =J280 -> 85.630614 | K55: =K280 -> 91.035356 | L55: =L280 -> 96.544745
B56: Cash and cash equivalents | F56: 125.3 | G56: 70.8 | H56: =H129 -> 47.724928 | I56: =I129 -> 100.00971 | J56: =J129 -> 202.92823 | K56: =K129 -> 349.39014 | L56: =L129 -> 532.06435
B57: Current Assets | F57: =SUM(F54:F56) -> 242.9 | G57: =SUM(G54:G56) -> 195.9 | H57: =SUM(H54:H56) -> 181.36462 | I57: =SUM(I54:I56) -> 243.34035 | J57: =SUM(J54:J56) -> 355.69845 | K57: =SUM(K54:K56) -> 511.38227 | L57: =SUM(L54:L56) -> 703.13137
B58: PP&E, gross | F58: 1142.1 | G58: 1391.2
B59: (-) Accumulated depreciation | F59: 477.4 | G59: 559.1
B60: PP&E, net | F60: =F58-F59 -> 664.7 | G60: =G58-G59 -> 832.1 | H60: =H393 -> 925.26057 | I60: =I393 -> 988.89798 | J60: =J393 -> 1021.006 | K60: =K393 -> 1033.3338 | L60: =L393 -> 1039.0646
B61: Intangible assets | F61: 24.9 | G61: 43 | H61: =H414 -> 50.064491 | I61: =I414 -> 54.773508 | J61: =J414 -> 56.877936 | K61: =K414 -> 56.131747 | L61: =L414 -> 52.305541
B62: Right-of-use assets | F62: 387.2 | G62: 413 | H62: =H340 -> 428.225 | I62: =I340 -> 436.08688 | J62: =J340 -> 436.45175 | K62: =K340 -> 429.19077 | L62: =L340 -> 414.18094
B63: Investments | F63: 0 | G63: 0 | H63: 0 | I63: 0 | J63: 0 | K63: 0 | L63: 0
B64: Total Assets | F64: =SUM(F60:F63)+F57 -> 1319.7 | G64: =SUM(G60:G63)+G57 -> 1484 | H64: =SUM(H57)+SUM(H60:H63) -> 1584.9147 | I64: =SUM(I57)+SUM(I60:I63) -> 1723.0987 | J64: =SUM(J57)+SUM(J60:J63) -> 1870.0342 | K64: =SUM(K57)+SUM(K60:K63) -> 2030.0386 | L64: =SUM(L57)+SUM(L60:L63) -> 2208.6824
B66: Liabiltiies and Shareholders Equity
B68: Trade and other payables | F68: -243.9 | G68: -272.8 | H68: =-H283 -> -287.84839 | I68: =-I283 -> -308.96515 | J68: =-J283 -> -328.82734 | K68: =-K283 -> -347.52259 | L68: =-L283 -> -364.98523
B69: Current tax liabilities | F69: -9.1 | G69: -2.1 | H69: =G69 -> -2.1 | I69: =H69 -> -2.1 | J69: =I69 -> -2.1 | K69: =J69 -> -2.1 | L69: =K69 -> -2.1
B70: Lease liabilities | F70: -53.8 | G70: -62.5 | H70: =H354 -> -52.62272 | I70: =I354 -> -52.299333 | J70: =J354 -> -52.063643 | K70: =K354 -> -51.940324 | L70: =L354 -> -51.940324
B71: Short-term provisions | F71: -3.4 | G71: -10.3 | H71: =G71 -> -10.3 | I71: =H71 -> -10.3 | J71: =I71 -> -10.3 | K71: =J71 -> -10.3 | L71: =K71 -> -10.3
B72: Total Current Liabilities | F72: =SUM(F68:F71) -> -310.2 | G72: =SUM(G68:G71) -> -347.7 | H72: =SUM(H68:H71) -> -352.87111 | I72: =SUM(I68:I71) -> -373.66448 | J72: =SUM(J68:J71) -> -393.29098 | K72: =SUM(K68:K71) -> -411.86291 | L72: =SUM(L68:L71) -> -429.32556
B73: Borrowings | F73: 0 | G73: -25 | H73: =-H442 -> 0 | I73: =-I442 -> 0 | J73: =-J442 -> 0 | K73: =-K442 -> 0 | L73: =-L442 -> 0
B74: Total Debt | F74: =SUM(F73) -> 0 | G74: =SUM(G73) -> -25 | H74: =SUM(H73) -> 0 | I74: =SUM(I73) -> 0 | J74: =SUM(J73) -> 0 | K74: =SUM(K73) -> 0 | L74: =SUM(L73) -> 0
B75: Net deferred tax liability | F75: -72.6 | G75: -93.7 | H75: =H496 -> -93.7 | I75: =I496 -> -93.7 | J75: =J496 -> -93.7 | K75: =K496 -> -93.7 | L75: =L496 -> -93.7
B76: Long term provisions | F76: -2.9 | G76: -3.4 | H76: =G76 -> -3.4 | I76: =H76 -> -3.4 | J76: =I76 -> -3.4 | K76: =J76 -> -3.4 | L76: =K76 -> -3.4
B77: Lease liabilities | F77: -361.3 | G77: -387.3 | H77: =H355 -> -403.66528 | I77: =I355 -> -409.37845 | J77: =J355 -> -413.5423 | K77: =K355 -> -415.72095 | L77: =L355 -> -415.43964
B78: Defined benefit pension liabilities | F78: -0.4 | G78: -0.3 | H78: =G78 -> -0.3 | I78: =H78 -> -0.3 | J78: =I78 -> -0.3 | K78: =J78 -> -0.3 | L78: =K78 -> -0.3
B79: Other payables | F79: -1.8 | G79: -1.4 | H79: =G79 -> -1.4 | I79: =H79 -> -1.4 | J79: =I79 -> -1.4 | K79: =J79 -> -1.4 | L79: =K79 -> -1.4
B80: Total liabilities | F80: =SUM(F74:F79)+F72 -> -749.2 | G80: =SUM(G74:G79)+G72 -> -858.8 | H80: =SUM(H74:H79)+H72 -> -855.33639 | I80: =SUM(I74:I79)+I72 -> -881.84293 | J80: =SUM(J74:J79)+J72 -> -905.63329 | K80: =SUM(K74:K79)+K72 -> -926.38386 | L80: =SUM(L74:L79)+L72 -> -943.5652
B81: Issued Capital | F81: 2 | G81: 2 | H81: =G81 -> 2 | I81: =H81 -> 2 | J81: =I81 -> 2 | K81: =J81 -> 2 | L81: =K81 -> 2
B82: Share premium account | F82: 25.1 | G82: 25.1 | H82: =G82 -> 25.1 | I82: =H82 -> 25.1 | J82: =I82 -> 25.1 | K82: =J82 -> 25.1 | L82: =K82 -> 25.1
B83: Capital redemption reserve | F83: 0.4 | G83: 0.4 | H83: =G83 -> 0.4 | I83: =H83 -> 0.4 | J83: =I83 -> 0.4 | K83: =J83 -> 0.4 | L83: =K83 -> 0.4
B84: Retained earnings | F84: 543 | G84: 597.7 | H84: =H527 -> 702.07829 | I84: =I527 -> 813.75579 | J84: =J527 -> 936.90087 | K84: =K527 -> 1076.1548 | L84: =L527 -> 1237.6172
B85: Total Liabilities and Equity | F85: =SUM(F81:F84)-F80 -> 1319.7 | G85: =SUM(G81:G84)-G80 -> 1484 | H85: =SUM(H81:H84)-H80 -> 1584.9147 | I85: =SUM(I81:I84)-I80 -> 1723.0987 | J85: =SUM(J81:J84)-J80 -> 1870.0342 | K85: =SUM(K81:K84)-K80 -> 2030.0386 | L85: =SUM(L81:L84)-L80 -> 2208.6824
B86: Balance? | F86: =F64-F85 -> 0 | G86: =G64-G85 -> 0 | H86: =H64-H85 -> 0 | I86: =I64-I85 -> 0 | J86: =J64-J85 -> 0 | K86: =K64-K85 -> 0 | L86: =L64-L85 -> 0
B90: =Cover!$B$2 -> Greggs
B91: Financial Statements - Cash Flow Statement | L91: ="Currently Running: "&CHOOSE(Assumptions!$B$10,Assumptions!$F$15,Assumptions!$F$16,Assumptions!$F$17)&"Scenario" -> Currently Running: Base Scenario
F93: Fiscal Years Ending December 31
F94: 2024 | G94: 2025 | H94: =G94+1 -> 2026 | I94: =H94+1 -> 2027 | J94: =I94+1 -> 2028 | K94: =J94+1 -> 2029 | L94: =K94+1 -> 2030
B95: (£m in millions) | F95: H = Historical | L95: F = Forecast
B97: Operating Activities
B99: Net Profit | H99: =H35 -> 160.58198 | I99: =I35 -> 171.81153 | J99: =J35 -> 189.45397 | K99: =K35 -> 214.23676 | L99: =L35 -> 248.40376
B100: PP&E depreciation | H100: =H385 -> 92.492661 | I100: =I385 -> 110.48126 | J100: =J385 -> 127.1501 | K100: =K385 -> 142.87305 | L100: =L385 -> 158.86276
B101: ROU depreciation | H101: =H331/1000000 -> 44.275 | I101: =I331/1000000 -> 50.150625 | J101: =J331/1000000 -> 55.862625 | K101: =K331/1000000 -> 61.379948 | L101: =L331/1000000 -> 66.668848
B102: Amortization of Intangible Assets | H102: =H407 -> 10.340499 | I102: =I407 -> 13.946555 | J102: =J407 -> 17.802839 | K102: =K407 -> 21.909941 | L102: =L407 -> 26.270773
B103: Income Statement Adjustments | H103: =SUM(H100:H102) -> 147.10816 | I103: =SUM(I100:I102) -> 174.57844 | J103: =SUM(J100:J102) -> 200.81556 | K103: =SUM(K100:K102) -> 226.16294 | L103: =SUM(L100:L102) -> 251.80238
B104: (Increase) / decrease in working capital | H104: =H286 -> 6.5086943 | I104: =I286 -> 11.425813 | J104: =J286 -> 10.422619 | K104: =K286 -> 9.4733296 | L104: =L286 -> 8.3877543
B105: Increase / (decrease) in DTL | H105: =H495 -> 0 | I105: =I495 -> 0 | J105: =J495 -> 0 | K105: =K495 -> 0 | L105: =L495 -> 0
B106: (Increase) / decrease in other assets | H106: =(G63-H63) -> 0 | I106: =(H63-I63) -> 0 | J106: =(I63-J63) -> 0 | K106: =(J63-K63) -> 0 | L106: =(K63-L63) -> 0
B107: Increase / (decrease) in other liabilities | H107: =(G78-H78)+(G79-H79)+(G76-H76)+(G69-H69)+(G71-H71) -> 0 | I107: =(H78-I78)+(H79-I79)+(H76-I76)+(H69-I69)+(H71-I71) -> 0 | J107: =(I78-J78)+(I79-J79)+(I76-J76)+(I69-J69)+(I71-J71) -> 0 | K107: =(J78-K78)+(J79-K79)+(J76-K76)+(J69-K69)+(J71-K71) -> 0 | L107: =(K78-L78)+(K79-L79)+(K76-L76)+(K69-L69)+(K71-L71) -> 0
B108: Balance Sheet Adjustments | H108: =SUM(H104:H107) -> 6.5086943 | I108: =SUM(I104:I107) -> 11.425813 | J108: =SUM(J104:J107) -> 10.422619 | K108: =SUM(K104:K107) -> 9.4733296 | L108: =SUM(L104:L107) -> 8.3877543
B109: Cash Flow from Operations | H109: =SUM(H99:H102)+SUM(H104:H107) -> 314.19884 | I109: =SUM(I99:I102)+SUM(I104:I107) -> 357.81578 | J109: =SUM(J99:J102)+SUM(J104:J107) -> 400.69215 | K109: =SUM(K99:K102)+SUM(K104:K107) -> 449.87302 | L109: =SUM(L99:L102)+SUM(L104:L107) -> 508.5939
B111: Investing Activities
B113: Capital expenditure on PP&E | H113: =-H367 -> -185.65323 | I113: =-I367 -> -174.11867 | J113: =-J367 -> -159.25814 | K113: =-K367 -> -155.20085 | L113: =-L367 -> -164.59349
B114: Additions to intangibles | H114: =-H370 -> -17.40499 | I114: =-I370 -> -18.655572 | J114: =-J370 -> -19.907267 | K114: =-K370 -> -21.163753 | L114: =-L370 -> -22.444567
B115: Cash flow from investing | H115: =SUM(H113:H114) -> -203.05822 | I115: =SUM(I113:I114) -> -192.77425 | J115: =SUM(J113:J114) -> -179.1654 | K115: =SUM(K113:K114) -> -176.3646 | L115: =SUM(L113:L114) -> -187.03805
B117: Financing Activities
B119: Borrowing Issuance | H119: =H440 -> 0 | I119: =I440 -> 0 | J119: =J440 -> 0 | K119: =K440 -> 0 | L119: =L440 -> 0
B120: Borrowing Repayments | H120: =H441 -> -25 | I120: =I441 -> 0 | J120: =J441 -> 0 | K120: =K441 -> 0 | L120: =L441 -> 0
B121: Lease principal payments | H121: =-H351-H350 -> -53.012 | I121: =-I351-I350 -> -52.62272 | J121: =-J351-J350 -> -52.299333 | K121: =-K351-K350 -> -52.063643 | L121: =-L351-L350 -> -51.940324
B122: Dividends | H122: =-H518 -> -56.203694 | I122: =-I518 -> -60.134036 | J122: =-J518 -> -66.30889 | K122: =-K518 -> -74.982865 | L122: =-L518 -> -86.941318
B123: Share buybacks
B124: Share issuance
B125: Cash flow from financing | H125: =SUM(H119:H124) -> -134.21569 | I125: =SUM(I119:I124) -> -112.75676 | J125: =SUM(J119:J124) -> -118.60822 | K125: =SUM(K119:K124) -> -127.04651 | L125: =SUM(L119:L124) -> -138.88164
B127: Cash - Beginning of Period | H127: =G56 -> 70.8 | I127: =H129 -> 47.724928 | J127: =I129 -> 100.00971 | K127: =J129 -> 202.92823 | L127: =K129 -> 349.39014
B128: Cash Movement during the year | H128: =H109+H115+H125 -> -23.075072 | I128: =I109+I115+I125 -> 52.28478 | J128: =J109+J115+J125 -> 102.91852 | K128: =K109+K115+K125 -> 146.46191 | L128: =L109+L115+L125 -> 182.67421
B129: Cash - End of Period | H129: =SUM(H127:H128) -> 47.724928 | I129: =SUM(I127:I128) -> 100.00971 | J129: =SUM(J127:J128) -> 202.92823 | K129: =SUM(K127:K128) -> 349.39014 | L129: =SUM(L127:L128) -> 532.06435
B134: =Cover!$B$2 -> Greggs
...
