Workbook

Sheet Cover
B2: OSB
B4: Modelled by Peter Hopkinson
B5: =DATE(2026, 9, 29) -> 46294

Sheet Assumptions
B2: =Cover!$B$2 -> OSB
B3: Model Assumptions
C5: Units | D5: 2026 | E5: =D5+1 -> 2027 | F5: =E5+1 -> 2028 | G5: =F5+1 -> 2029 | H5: =G5+1 -> 2030
B6: Macro Assumptions
B8: Bank Rate | C8: % | D8: 0.0375 | E8: 0.045 | F8: 0.035 | G8: 0.03 | H8: 0.025
B9: SONIA | C9: % | D9: 0.039 | E9: 0.0465 | F9: 0.0365 | G9: 0.0315 | H9: 0.0265
B10: Inflation | C10: % | D10: 0.0325 | E10: 0.035 | F10: 0.0275 | G10: 0.025 | H10: 0.025
B12: Loan Book Assumptions - OSB
B14: BTL origination growth rate | C14: % | D14: -0.02 | E14: -0.02 | F14: -0.02 | G14: -0.02 | H14: 0
B15: BTL redemption rate | C15: % | D15: 0.09 | E15: 0.09 | F15: 0.09 | G15: 0.09 | H15: 0.09
B16: Residential origination growth rate | C16: % | D16: -0.5 | E16: -0.5
B17: Residential redemption rate | C17: % | D17: 0.175 | E17: 0.175 | F17: 0.175 | G17: 0.175 | H17: 0.175
B18: Residential development origination growth rate | C18: % | D18: 0.2 | E18: 0.15 | F18: 0.12 | G18: 0.08 | H18: 0.06
B19: Residential development redemption rate | C19: % | D19: 0.75 | E19: 0.75 | F19: 0.75 | G19: 0.75 | H19: 0.75
B20: Commercial origination growth rate | C20: % | D20: 0.1 | E20: 0.1 | F20: 0.08 | G20: 0.06 | H20: 0.06
B21: Commercial redemption rate | C21: % | D21: 0.15 | E21: 0.15 | F21: 0.17 | G21: 0.19 | H21: 0.2
B22: Asset Finance origination growth rate | C22: % | D22: 0.25 | E22: 0.2 | F22: 0.15 | G22: 0.12 | H22: 0.1
B23: Asset Finance redemption rate | C23: % | D23: 0.33 | E23: 0.33 | F23: 0.33 | G23: 0.33 | H23: 0.33
B25: Loan Book Assumptions - CCFS
B27: BTL origination growth rate | C27: % | D27: 0 | E27: 0 | F27: 0 | G27: 0 | H27: 0
B28: BTL redemption rate | C28: % | D28: 0.08 | E28: 0.08 | F28: 0.08 | G28: 0.08 | H28: 0.08
B29: Residential origination growth rate | C29: % | D29: 0.1 | E29: 0.1 | F29: 0.1 | G29: 0.1 | H29: 0.1
B30: Residential redemption rate | C30: % | D30: 0.175 | E30: 0.175 | F30: 0.175 | G30: 0.175 | H30: 0.175
B32: Asset Spreads over SONIA
B34: One savings bank
B36: BTL spread | C36: % | D36: 0.0225 | E36: 0.0225 | F36: 0.0225 | G36: 0.0225 | H36: 0.0225
B37: Residential spread | C37: % | D37: 0.02 | E37: 0.02 | F37: 0.02 | G37: 0.02 | H37: 0.02
B38: Residential development spread | C38: % | D38: 0.06 | E38: 0.06 | F38: 0.06 | G38: 0.06 | H38: 0.06
B39: Commercial spread | C39: % | D39: 0.04 | E39: 0.04 | F39: 0.04 | G39: 0.04 | H39: 0.04
B40: Asset Finance spread | C40: % | D40: 0.045 | E40: 0.045 | F40: 0.045 | G40: 0.045 | H40: 0.045
B42: CCFS
B44: BTL spread | C44: % | D44: 0.0225 | E44: 0.0225 | F44: 0.0225 | G44: 0.0225 | H44: 0.0225
B45: Residential spread | C45: % | D45: 0.025 | E45: 0.025 | F45: 0.025 | G45: 0.025 | H45: 0.025
B47: Funding assumptions
B49: Deposit growth rate | C49: % | D49: 0.02 | E49: 0.02 | F49: 0.02 | G49: 0.02 | H49: 0.02
B50: Retail deposit spread | C50: % | D50: 0 | E50: 0 | F50: 0 | G50: 0 | H50: 0
B51: Retail deposit cost | C51: % | D51: =D9+D50 -> 0.039 | E51: =E9+E50 -> 0.0465 | F51: =F9+F50 -> 0.0365 | G51: =G9+G50 -> 0.0315 | H51: =H9+H50 -> 0.0265
B53: Securitisation redemption | C53: % | D53: 0.2 | E53: 0.2 | F53: 0.2 | G53: 0.2 | H53: 0.2
B54: Securitisation spread | C54: % | D54: 0.01 | E54: 0.01 | F54: 0.01 | G54: 0.01 | H54: 0.01
B55: Securitisation issuance | C55: £m | D55: 0 | E55: 0 | F55: 0 | G55: 0 | H55: 0
B57: ILTR spread | C57: % | D57: 0.0015 | E57: 0.0015 | F57: 0.0015 | G57: 0.0015 | H57: 0.0015
B58: ILTR cost | C58: % | D58: =D57+D8 -> 0.039 | E58: =E57+E8 -> 0.0465 | F58: =F57+F8 -> 0.0365 | G58: =G57+G8 -> 0.0315 | H58: =H57+H8 -> 0.0265
B59: ILTR issuance | C59: £m | D59: 0 | E59: 0 | F59: 0 | G59: 0 | H59: 0
B60: ILTR redemption | C60: £m | D60: 0 | E60: 0 | F60: 0 | G60: 0 | H60: 0
B62: Senior notes - redemption | C62: £m | D62: 0 | E62: 300 | F62: 0 | G62: 400 | H62: 0
B63: Senior notes - issuance | C63: £m | D63: 0 | E63: 350 | F63: 0 | G63: 450 | H63: 0
B64: Senior notes - 2028 redemption | C64: % | D64: 0.095 | E64: 0.095 | F64: =F9+0.04985 -> 0.08635 | G64: =F64 -> 0.08635 | H64: =G64 -> 0.08635 | J64: * Reset Sep 2027 - redemption is 2028
B65: Senior notes - 2030 redemption | C65: % | D65: 0.08875 | E65: 0.08875 | F65: 0.08875 | G65: =G9+0.05252 -> 0.08402 | H65: =G65 -> 0.08402 | J65: * Reset for 2029
B66: Average senior debt coupon | D66: 0.091 | E66: 0.091 | F66: 0.087 | G66: 0.085 | H66: 0.085
B68: Subordinated debt liabilties | C68: % | D68: 0.0993 | E68: 0.0993 | F68: 0.0993 | G68: 0.0993 | H68: 0.0993 | J68: * Redeems in 2028 - then goes to a reference rate
B69: Subordinated debt - issuance | C69: £m | D69: 0 | E69: 0 | F69: 0 | G69: 0 | H69: 0
B70: Subordinated debt - redemption | C70: £m | D70: 0 | E70: 0 | F70: 0 | G70: 0 | H70: 0
B72: Repo spread | C72: % | D72: 0.02 | E72: 0.02 | F72: 0.02 | G72: 0.02 | H72: 0.02
B73: Repo cost | C73: % | D73: =D72+D9 -> 0.059 | E73: =E72+E9 -> 0.0665 | F73: =F72+F9 -> 0.0565 | G73: =G72+G9 -> 0.0515 | H73: =H72+H9 -> 0.0465
B75: Cash yield | C75: % | D75: =D8 -> 0.0375 | E75: =E8 -> 0.045 | F75: =F8 -> 0.035 | G75: =G8 -> 0.03 | H75: =H8 -> 0.025
B76: Investment security spread | C76: % | D76: 0.01 | E76: 0.01 | F76: 0.01 | G76: 0.01 | H76: 0.01
B77: Investment security yield | D77: =D76+D9 -> 0.049 | E77: =E76+E9 -> 0.0565 | F77: =F76+F9 -> 0.0465 | G77: =G76+G9 -> 0.0415 | H77: =H76+H9 -> 0.0365
B79: Credit, Capital and RWA assumptions
B81: One savings bank
B83: BTL cost of risk | C83: bps | D83: 10 | E83: 10 | F83: 10 | G83: 10 | H83: 10
B84: Residential cost of risk | C84: bps | D84: 5 | E84: 5 | F84: 5 | G84: 5 | H84: 5
B85: Residential development cost of risk | C85: bps | D85: 30 | E85: 30 | F85: 30 | G85: 30 | H85: 30
B86: Commercial cost of risk | C86: bps | D86: 20 | E86: 20 | F86: 20 | G86: 20 | H86: 20
B87: Asset Finance cost of risk | C87: bps | D87: 30 | E87: 30 | F87: 30 | G87: 30 | H87: 30
B89: CCFS
B91: BTL cost of risk | C91: bps | D91: 10 | E91: 10 | F91: 10 | G91: 10 | H91: 10
B92: Residential cost of risk | C92: bps | D92: 10 | E92: 10 | F92: 10 | G92: 10 | H92: 10
B94: Risk-weighted assets
B96: Mortgage RWA density | C96: % | D96: 0.35 | E96: 0.35 | F96: 0.35 | G96: 0.35 | H96: 0.35
B97: BTL RWA density | C97: % | D97: 0.35 | E97: 0.35 | F97: 0.35 | G97: 0.35 | H97: 0.35
B98: Residential development RWA density | C98: % | D98: 1.5 | E98: 1.5 | F98: 1.5 | G98: 1.5 | H98: 1.5
B99: Commercial RWA density | C99: % | D99: 0.9 | E99: 0.9 | F99: 0.9 | G99: 0.9 | H99: 0.9
B100: Asset Finance RWA density | C100: % | D100: 0.9 | E100: 0.9 | F100: 0.9 | G100: 0.9 | H100: 0.9
B102: Operational RWA | C102: £m | D102: 900 | E102: 900 | F102: 900 | G102: 900 | H102: 900
B104: Other expense/income assumption
B106: Tax Rate | C106: % | D106: 0.25 | E106: 0.25 | F106: 0.25 | G106: 0.25 | H106: 0.25
B107: Headcount growth | C107: % | D107: 0.01 | E107: 0.01 | F107: 0.01 | G107: 0.01 | H107: 0.01
B108: Wage inflation | C108: % | D108: 0.02 | E108: 0.02 | F108: 0.02 | G108: 0.02 | H108: 0.02
B109: Capital expenditure growth rate | C109: % | D109: 0.03 | E109: 0.03 | F109: 0.03 | G109: 0.03 | H109: 0.03
B110: Useful life of PP&E and intangibles | C110: years | D110: 7 | E110: 7 | F110: 7 | G110: 7 | H110: 7
B111: Normalized PP&E capital expenditure | C111: £m | D111: 12
B113: Equity assumptions
B115: Dividend payout ratio | C115: % | D115: 0.4 | E115: 0.4 | F115: 0.4 | G115: 0.4 | H115: 0.4

Sheet Model
B2: =Cover!$B$2 -> OSB
B3: Financial Statements - Income Statement
C7: Units / £m | E7: 2024 | F7: 2025 | G7: =F7+1 -> 2026 | H7: =G7+1 -> 2027 | I7: =H7+1 -> 2028 | J7: =I7+1 -> 2029 | K7: =J7+1 -> 2030
B9: Interest Receivable | E9: 2099.3 | F9: 1914.8 | G9: =G299 -> 1891.2295 | H9: =H299 -> 2178.4571 | I9: =I299 -> 1910.3192 | J9: =J299 -> 1791.181 | K9: =K299 -> 1668.2097
B10: Interest Payable | E10: -1432.9 | F10: -1235.4 | G10: =-G337 -> -1188.3567 | H10: =-H337 -> -1411.0323 | I10: =-I337 -> -1141.4169 | J10: =-J337 -> -1011.3138 | K10: =-K337 -> -879.94391
B11: Net Interest Income | E11: =SUM(E9:E10) -> 666.4 | F11: =SUM(F9:F10) -> 679.4 | G11: =SUM(G9:G10) -> 702.87283 | H11: =SUM(H9:H10) -> 767.42471 | I11: =SUM(I9:I10) -> 768.90234 | J11: =SUM(J9:J10) -> 779.86723 | K11: =SUM(K9:K10) -> 788.26577
B13: Fair value losses on financial instruments | E13: -1.5 | F13: -22.1 | G13: =G476 -> 0 | H13: =H476 -> 0 | I13: =I476 -> 0 | J13: =J476 -> 0 | K13: =K476 -> 0
B14: Gain/(loss) on sale of financial assets | E14: -2.4 | F14: 3.4 | G14: =G477 -> 0 | H14: =H477 -> 0 | I14: =I477 -> 0 | J14: =J477 -> 0 | K14: =K477 -> 0
B15: Other operating income | E15: 4.7 | F15: 7.3 | G15: =G478 -> 7.3 | H15: =H478 -> 7.3 | I15: =I478 -> 7.3 | J15: =J478 -> 7.3 | K15: =K478 -> 7.3
B16: Total Income | E16: =SUM(E13:E15)+E11 -> 667.2 | F16: =SUM(F13:F15)+F11 -> 668 | G16: =SUM(G13:G15)+G11 -> 710.17283 | H16: =SUM(H13:H15)+H11 -> 774.72471 | I16: =SUM(I13:I15)+I11 -> 776.20234 | J16: =SUM(J13:J15)+J11 -> 787.16723 | K16: =SUM(K13:K15)+K11 -> 795.56577
B17: Administrative expenses | E17: -258.1 | F17: -270.1 | G17: =-G491 -> -281.70585 | H17: =-H491 -> -296.02401 | I17: =-I491 -> -309.94536 | J17: =-J491 -> -323.98766 | K17: =-K491 -> -338.43773
B18: Provisions for credit losses | E18: -2.7 | F18: -2.4 | G18: =0 -> 0 | H18: =0 -> 0 | I18: =0 -> 0 | J18: =0 -> 0 | K18: =0 -> 0
B19: Impairment of financial assets | E19: 11.7 | F19: -13 | G19: =-G419 -> -29.383707 | H19: =-H419 -> -31.525842 | I19: =-I419 -> -33.479301 | J19: =-J419 -> -35.168603 | K19: =-K419 -> -36.635799
B20: Profit before taxation | E20: =SUM(E16:E19) -> 418.1 | F20: =SUM(F16:F19) -> 382.5 | G20: =SUM(G16:G19) -> 399.08327 | H20: =SUM(H16:H19) -> 447.17486 | I20: =SUM(I16:I19) -> 432.77768 | J20: =SUM(J16:J19) -> 428.01096 | K20: =SUM(K16:K19) -> 420.49224
B21: Taxation | E21: -110 | F21: -96.8 | G21: =-G20*Assumptions!D106 -> -99.770817 | H21: =-H20*Assumptions!E106 -> -111.79372 | I21: =-I20*Assumptions!F106 -> -108.19442 | J21: =-J20*Assumptions!G106 -> -107.00274 | K21: =-K20*Assumptions!H106 -> -105.12306
B22: Profit for the year | E22: =SUM(E20:E21) -> 308.1 | F22: =SUM(F20:F21) -> 285.7 | G22: =SUM(G20:G21) -> 299.31245 | H22: =SUM(H20:H21) -> 335.38115 | I22: =SUM(I20:I21) -> 324.58326 | J22: =SUM(J20:J21) -> 321.00822 | K22: =SUM(K20:K21) -> 315.36918
B23: Other comprehensive expense | E23: -0.1 | F23: -0.7 | G23: 0 | H23: 0 | I23: 0 | J23: 0 | K23: 0
B24: Total comprehensive income | E24: =SUM(E22:E23) -> 308 | F24: =SUM(F22:F23) -> 285 | G24: =SUM(G22:G23) -> 299.31245 | H24: =SUM(H22:H23) -> 335.38115 | I24: =SUM(I22:I23) -> 324.58326 | J24: =SUM(J22:J23) -> 321.00822 | K24: =SUM(K22:K23) -> 315.36918
B26: Earning per share | C26: Units
B27: - Basic | C27: pence per share
B28: - Diluted | C28: pence per share
B31: =Cover!$B$2 -> OSB
B32: Financial Statements - Balance Sheet
C36: Units / £m | E36: 2024 | F36: 2025 | G36: =F36+1 -> 2026 | H36: =G36+1 -> 2027 | I36: =H36+1 -> 2028 | J36: =I36+1 -> 2029 | K36: =J36+1 -> 2030
B37: Assets
B38: Cash and cash equivalents | E38: 3406.2 | F38: 3053.4 | G38: =G75-SUM(G39:G48) -> 2336.9875 | H38: =H75-SUM(H39:H48) -> 1755.2055 | I38: =I75-SUM(I39:I48) -> 1310.8738 | J38: =J75-SUM(J39:J48) -> 1099.7678 | K38: =K75-SUM(K39:K48) -> 1006.626
B39: Investment securities | E39: 1434.4 | F39: 1814.5 | G39: =F39 -> 1814.5 | H39: =G39 -> 1814.5 | I39: =H39 -> 1814.5 | J39: =I39 -> 1814.5 | K39: =J39 -> 1814.5
B40: Loans and advances to customers | E40: 25126.3 | F40: 25920.6 | G40: =G193 -> 26875.02 | H40: =H193 -> 27824.606 | I40: =I193 -> 28627.273 | J40: =J193 -> 29290.54 | K40: =K193 -> 29893.119
B41: Fair value adjustments on hedged assets | E41: -179.3 | F41: 85.1 | G41: =F41 -> 85.1 | H41: =G41 -> 85.1 | I41: =H41 -> 85.1 | J41: =I41 -> 85.1 | K41: =J41 -> 85.1
B42: Derivative assets | E42: 313.8 | F42: 101.4 | G42: =F42 -> 101.4 | H42: =G42 -> 101.4 | I42: =H42 -> 101.4 | J42: =I42 -> 101.4 | K42: =J42 -> 101.4
B43: Other assets | E43: 17.8 | F43: 21 | G43: =F43 -> 21 | H43: =G43 -> 21 | I43: =H43 -> 21 | J43: =I43 -> 21 | K43: =J43 -> 21
B44: Current taxation asset | E44: 14.8 | F44: 1.7 | G44: =F44 -> 1.7 | H44: =G44 -> 1.7 | I44: =H44 -> 1.7 | J44: =I44 -> 1.7 | K44: =J44 -> 1.7
B45: Deferred taxation assets | E45: 6.2 | F45: 8.8 | G45: =F45 -> 8.8 | H45: =G45 -> 8.8 | I45: =H45 -> 8.8 | J45: =I45 -> 8.8 | K45: =J45 -> 8.8
B46: Non-current assets held for sale | E46: 0 | F46: 1.5 | G46: =F46 -> 1.5 | H46: =G46 -> 1.5 | I46: =H46 -> 1.5 | J46: =I46 -> 1.5 | K46: =J46 -> 1.5
B47: Property, plant and equipment | E47: 54.6 | F47: 47.8 | G47: =G457 -> 52.448571 | H47: =H457 -> 55.675743 | I47: =I457 -> 57.438872 | J47: =J457 -> 57.694038 | K47: =K457 -> 56.396002
B48: Intangible assets | E48: 48.8 | F48: 66.9 | G48: =G464 -> 83.453357 | H48: =H464 -> 96.773029 | I48: =I464 -> 106.76201 | J48: =J464 -> 113.32037 | K48: =K464 -> 116.34519
B49: Total assets | E49: =SUM(E38:E48) -> 30243.6 | F49: =SUM(F38:F48) -> 31122.7 | G49: =SUM(G38:G48) -> 31381.909 | H49: =SUM(H38:H48) -> 31766.261 | I49: =SUM(I38:I48) -> 32136.347 | J49: =SUM(J38:J48) -> 32595.322 | K49: =SUM(K38:K48) -> 33106.487
B52: Liabilities
B53: Amounts owed to credit institutions | E53: 1935.2 | F53: 1838.1 | G53: =G247 -> 1838.1 | H53: =H247 -> 1838.1 | I53: =I247 -> 1838.1 | J53: =J247 -> 1838.1 | K53: =K247 -> 1838.1
B54: Amounts owed to retail depositors | E54: 23820.3 | F54: 24251.1 | G54: =G210 -> 24736.122 | H54: =H210 -> 25230.844 | I54: =I210 -> 25735.461 | J54: =J210 -> 26250.171 | K54: =K210 -> 26775.174
B55: Fair value adjustments on hedged liabilities | E55: -6.1 | F55: 11.9 | G55: =F55 -> 11.9 | H55: =G55 -> 11.9 | I55: =H55 -> 11.9 | J55: =I55 -> 11.9 | K55: =J55 -> 11.9
B56: Amounts owed to other customers | E56: 104.9 | F56: 478.4 | G56: =G215 -> 478.4 | H56: =H215 -> 478.4 | I56: =I215 -> 478.4 | J56: =J215 -> 478.4 | K56: =K215 -> 478.4
B57: Debt securities in issue | E57: 1018.3 | F57: 1010 | G57: =G222 -> 808 | H57: =H222 -> 646.4 | I57: =I222 -> 517.12 | J57: =J222 -> 413.696 | K57: =K222 -> 330.9568
B58: Derivative liabilities | E58: 81.9 | F58: 152 | G58: =F58 -> 152 | H58: =G58 -> 152 | I58: =H58 -> 152 | J58: =I58 -> 152 | K58: =J58 -> 152
B59: Lease liabilities | E59: 9.1 | F59: 6.3 | G59: =F59 -> 6.3 | H59: =G59 -> 6.3 | I59: =H59 -> 6.3 | J59: =I59 -> 6.3 | K59: =J59 -> 6.3
B60: Other liabilities | E60: 56.4 | F60: 70.8 | G60: =F60 -> 70.8 | H60: =G60 -> 70.8 | I60: =H60 -> 70.8 | J60: =I60 -> 70.8 | K60: =J60 -> 70.8
B61: Provisions | E61: 4.6 | F61: 3.4 | G61: =0 -> 0 | H61: =0 -> 0 | I61: =0 -> 0 | J61: =0 -> 0 | K61: =0 -> 0
B62: Deferred tax liabilities | E62: 13.1 | F62: 20.5 | G62: =F62 -> 20.5 | H62: =G62 -> 20.5 | I62: =H62 -> 20.5 | J62: =I62 -> 20.5 | K62: =J62 -> 20.5
B63: Senior notes | E63: 722.7 | F63: 723.4 | G63: =G228 -> 723.4 | H63: =H228 -> 773.4 | I63: =I228 -> 773.4 | J63: =J228 -> 823.4 | K63: =K228 -> 823.4
B64: Subordinated debt liabilities | E64: 259.8 | F64: 260.1 | G64: =G234 -> 260.1 | H64: =H234 -> 260.1 | I64: =I234 -> 260.1 | J64: =J234 -> 260.1 | K64: =K234 -> 260.1
B65: Total Liabilities | E65: =SUM(E53:E64) -> 28020.2 | F65: =SUM(F53:F64) -> 28826 | G65: =SUM(G53:G64) -> 29105.622 | H65: =SUM(H53:H64) -> 29488.744 | I65: =SUM(I53:I64) -> 29864.081 | J65: =SUM(J53:J64) -> 30325.367 | K65: =SUM(K53:K64) -> 30767.631
B67: Equity
B68: Share capital | E68: 3.7 | F68: 3.6
B69: Share premium | E69: 4.5 | F69: 6
B70: Other equity instruments | E70: 150 | F70: 167.1
B71: Retained earnings | E71: 3406.4 | F71: 3457
B72: Other reserves | E72: -1341.2 | F72: -1337
B73: Total equity | E73: =SUM(E68:E72) -> 2223.4 | F73: =SUM(F68:F72) -> 2296.7 | G73: =G564 -> 2276.2875 | H73: =H564 -> 2277.5162 | I73: =I564 -> 2272.2661 | J73: =J564 -> 2269.9558 | K73: =K564 -> 2338.8558
B75: Total Liabilities and equity | E75: =E65+E73 -> 30243.6 | F75: =F65+F73 -> 31122.7 | G75: =G65+G73 -> 31381.909 | H75: =H65+H73 -> 31766.261 | I75: =I65+I73 -> 32136.347 | J75: =J65+J73 -> 32595.322 | K75: =K65+K73 -> 33106.487
B78: =Cover!$B$2 -> OSB
B79: Executive Summary / Key Metrics
C83: Units / £m | E83: 2024 | F83: 2025 | G83: =F83+1 -> 2026 | H83: =G83+1 -> 2027 | I83: =H83+1 -> 2028 | J83: =I83+1 -> 2029 | K83: =J83+1 -> 2030
B85: Key Metrics
B87: Loan Book | C87: £m | F87: =F193 -> 25831.7 | G87: =G193 -> 26875.02 | H87: =H193 -> 27824.606 | I87: =I193 -> 28627.273 | J87: =J193 -> 29290.54 | K87: =K193 -> 29893.119
B88: Loan Growth Rate | C88: % | G88: =G196 -> 0.040389134 | H88: =H196 -> 0.035333417 | I88: =I196 -> 0.02884736 | J88: =J196 -> 0.023169077 | K88: =K196 -> 0.020572485
B89: NII | C89: £m | F89: =F11 -> 679.4 | G89: =G11 -> 702.87283 | H89: =H11 -> 767.42471 | I89: =I11 -> 768.90234 | J89: =J11 -> 779.86723 | K89: =K11 -> 788.26577
B90: NIM | C90: % | G90: =G341 -> 0.022773924 | H90: =H341 -> 0.024588742 | I90: =I341 -> 0.024352791 | J90: =J341 -> 0.024387063 | K90: =K341 -> 0.024284574
B91: Cost-to-income | C91: % | F91: =-F17/F16 -> 0.40434132 | G91: =-G17/G16 -> 0.39667225 | H91: =-H17/H16 -> 0.38210219 | I91: =-I17/I16 -> 0.39931 | J91: =-J17/J16 -> 0.41158683 | K91: =-K17/K16 -> 0.42540509
B92: Cost of risk | C92: bps | G92: =G422 -> 11.14989 | H92: =H422 -> 11.526895 | I92: =I422 -> 11.861182 | J92: =J422 -> 12.144313 | K92: =K422 -> 12.380376
B93: PBT | C93: £m | G93: =G20 -> 399.08327 | H93: =H20 -> 447.17486 | I93: =I20 -> 432.77768 | J93: =J20 -> 428.01096 | K93: =K20 -> 420.49224
B94: RoTE | C94: % | G94: =G574 -> 0.13535483 | H94: =H574 -> 0.15336697 | I94: =I574 -> 0.14936254 | J94: =J574 -> 0.14854135 | K94: =K574 -> 0.14403227
B95: CET1 ratio | C95: % | G95: =G543 -> 0.15761521 | H95: =H543 -> 0.148376 | I95: =I543 -> 0.14069665 | J95: =J543 -> 0.135 | K95: =K543 -> 0.135
B96: Dividend | C96: £m | G96: =-G562 -> 119.72498 | H96: =-H562 -> 134.15246 | I96: =-I562 -> 129.83331 | J96: =-J562 -> 128.40329 | K96: =-K562 -> 126.14767
B97: Share buybacks | C97: £m | G97: =-G563 -> 200 | H97: =-H563 -> 200 | I97: =-I563 -> 200 | J97: =-J563 -> 194.91523 | K97: =-K563 -> 120.32153
B100: =Cover!$B$2 -> OSB
B101: Asset Schedule - OSB
C105: Units / £m | E105: 2024 | F105: 2025 | G105: =F105+1 -> 2026 | H105: =G105+1 -> 2027 | I105: =H105+1 -> 2028 | J105: =I105+1 -> 2029 | K105: =J105+1 -> 2030
B107: Buy-to-Let
B109: Opening Balance | F109: =E112 -> 11201.2 | G109: =F112 -> 12061.9 | H109: =G112 -> 12809.713 | I109: =H112 -> 13453.555 | J109: =I112 -> 14003.517 | K109: =J112 -> 14468.767
B110: Originations | E110: 2049.2 | F110: 1870.8 | G110: =F110*(1+Assumptions!D14) -> 1833.384 | H110: =G110*(1+Assumptions!E14) -> 1796.7163 | I110: =H110*(1+Assumptions!F14) -> 1760.782 | J110: =I110*(1+Assumptions!G14) -> 1725.5664 | K110: =J110*(1+Assumptions!H14) -> 1725.5664
B111: Repayments | F111: -1010.1 | G111: =-G109*Assumptions!D15 -> -1085.571 | H111: =-H109*Assumptions!E15 -> -1152.8742 | I111: =-I109*Assumptions!F15 -> -1210.82 | J111: =-J109*Assumptions!G15 -> -1260.3165 | K111: =-K109*Assumptions!H15 -> -1302.189
B112: Closing Balances | E112: 11201.2 | F112: =SUM(F109:F111) -> 12061.9 | G112: =SUM(G109:G111) -> 12809.713 | H112: =SUM(H109:H111) -> 13453.555 | I112: =SUM(I109:I111) -> 14003.517 | J112: =SUM(J109:J111) -> 14468.767 | K112: =SUM(K109:K111) -> 14892.144
B114: YoY Growth | F114: =(F112-E112)/E112 -> 0.076839981 | G114: =(G112-F112)/F112 -> 0.061997944 | H114: =(H112-G112)/G112 -> 0.050262028 | I114: =(I112-H112)/H112 -> 0.040878565 | J114: =(J112-I112)/I112 -> 0.033223782 | K114: =(K112-J112)/J112 -> 0.029261465
B115: Average Balance | F115: =AVERAGE(F109,F112) -> 11631.55 | G115: =AVERAGE(G109,G112) -> 12435.806 | H115: =AVERAGE(H109,H112) -> 13131.634 | I115: =AVERAGE(I109,I112) -> 13728.536 | J115: =AVERAGE(J109,J112) -> 14236.142 | K115: =AVERAGE(K109,K112) -> 14680.456
B117: Residential
B119: Opening Balance | F119: =E122 -> 2181.2 | G119: =F122 -> 1967.1 | H119: =G122 -> 1682.0575 | I119: =H122 -> 1417.2974 | J119: =I122 -> 1169.2704 | K119: =J122 -> 964.64807
B120: Originations | E120: 255.9 | F120: 118.4 | G120: =F120*(1+Assumptions!D16) -> 59.2 | H120: =G120*(1+Assumptions!E16) -> 29.6 | I120: 0 | J120: 0 | K120: 0
B121: Repayments | F121: -332.5 | G121: =-G119*Assumptions!D17 -> -344.2425 | H121: =-H119*Assumptions!E17 -> -294.36006 | I121: =-I119*Assumptions!F17 -> -248.02705 | J121: =-J119*Assumptions!G17 -> -204.62232 | K121: =-K119*Assumptions!H17 -> -168.81341
B122: Closing Balances | E122: 2181.2 | F122: =SUM(F119:F121) -> 1967.1 | G122: =SUM(G119:G121) -> 1682.0575 | H122: =SUM(H119:H121) -> 1417.2974 | I122: =SUM(I119:I121) -> 1169.2704 | J122: =SUM(J119:J121) -> 964.64807 | K122: =SUM(K119:K121) -> 795.83466
B124: YoY Growth | F124: =(F122-E122)/E122 -> -0.098156978 | G124: =(G122-F122)/F122 -> -0.14490494 | H124: =(H122-G122)/G122 -> -0.1574025 | I124: =(I122-H122)/H122 -> -0.175 | J124: =(J122-I122)/I122 -> -0.175 | K124: =(K122-J122)/J122 -> -0.175
B125: Average Balance | F125: =AVERAGE(F119,F122) -> 2074.15 | G125: =AVERAGE(G119,G122) -> 1824.5787 | H125: =AVERAGE(H119,H122) -> 1549.6775 | I125: =AVERAGE(I119,I122) -> 1293.2839 | J125: =AVERAGE(J119,J122) -> 1066.9592 | K125: =AVERAGE(K119,K122) -> 880.24136
B127: Residential development
B129: Opening Balance | F129: =E132 -> 262 | G129: =F132 -> 343.1 | H129: =G132 -> 448.055 | I129: =H132 -> 528.63575 | J129: =I132 -> 598.77558 | K129: =J132 -> 653.63987
B130: Originations | E130: 189.1 | F130: 301.9 | G130: =F130*(1+Assumptions!D18) -> 362.28 | H130: =G130*(1+Assumptions!E18) -> 416.622 | I130: =H130*(1+Assumptions!F18) -> 466.61664 | J130: =I130*(1+Assumptions!G18) -> 503.94597 | K130: =J130*(1+Assumptions!H18) -> 534.18273
B131: Repayments | F131: -220.8 | G131: =-G129*Assumptions!D19 -> -257.325 | H131: =-H129*Assumptions!E19 -> -336.04125 | I131: =-I129*Assumptions!F19 -> -396.47681 | J131: =-J129*Assumptions!G19 -> -449.08168 | K131: =-K129*Assumptions!H19 -> -490.2299
B132: Closing Balance | E132: 262 | F132: =SUM(F129:F131) -> 343.1 | G132: =SUM(G129:G131) -> 448.055 | H132: =SUM(H129:H131) -> 528.63575 | I132: =SUM(I129:I131) -> 598.77558 | J132: =SUM(J129:J131) -> 653.63987 | K132: =SUM(K129:K131) -> 697.5927
B134: YoY Growth | F134: =(F132-E132)/E132 -> 0.30954198 | G134: =(G132-F132)/F132 -> 0.30590207 | H134: =(H132-G132)/G132 -> 0.17984567 | I134: =(I132-H132)/H132 -> 0.13268083 | J134: =(J132-I132)/I132 -> 0.091627465 | K134: =(K132-J132)/J132 -> 0.067243191
B135: Average Balance | F135: =AVERAGE(F129,F132) -> 302.55 | G135: =AVERAGE(G129,G132) -> 395.5775 | H135: =AVERAGE(H129,H132) -> 488.34537 | I135: =AVERAGE(I129,I132) -> 563.70566 | J135: =AVERAGE(J129,J132) -> 626.20772 | K135: =AVERAGE(K129,K132) -> 675.61628
B137: Commercial lending
B139: Opening Balance | F139: =E142 -> 1356 | G139: =F142 -> 1866.1 | H139: =G142 -> 2357.285 | I139: =H142 -> 2851.9023 | J139: =I142 -> 3283.1457 | K139: =J142 -> 3630.3788
...
