Workbook

Sheet Cover
B2: Paragon Bank
B4: Modelled by Peter Hopkinson
B5: =DATE(2026, 9, 25) -> 46290

Sheet Assumptions
B2: =Cover!$B$2 -> Paragon Bank
B3: Model Assumptions
C5: Units | D5: 2026 | E5: =D5+1 -> 2027 | F5: =E5+1 -> 2028 | H5: Notes
B6: Macro Assumptions
B8: Bank Rate | C8: % | D8: 0.0375 | E8: 0.045 | F8: 0.04
B9: SONIA | C9: % | D9: 0.0413 | E9: 0.0477 | F9: 0.0425
B10: Inflation | C10: % | D10: 0.0375 | E10: 0.035 | F10: 0.025
B12: Loan Book
B14: Mortgage Lending - Origination Rate | C14: % | D14: 0.05 | E14: 0.05 | F14: 0.05
B15: Commercial Lending - Origination Rates | C15: % | D15: 0.075 | E15: 0.075 | F15: 0.075
B16: Mortgage Lending - Redemption Rate | C16: % | D16: 0.08 | E16: 0.08 | F16: 0.08
B17: Commercial Lending - Redemption Rate | C17: % | D17: 0.45 | E17: 0.45 | F17: 0.45
B19: Funding Assumptions
B21: Deposit Growth Rates | C21: % | D21: 0.01 | E21: 0.01 | F21: 0.03
B22: Covered Bond Issuance | C22: £m | D22: 500 | E22: 0 | F22: 500
B23: Covered Bond Repayment | C23: £m | D23: 0 | E23: 0 | F23: 499.2
B24: Corporate Bond Issuance | C24: £m | D24: 200 | E24: 0 | F24: 0
B25: Corporate Bond Repayment | C25: £m | D25: 150.1 | E25: 0 | F25: 0
B26: TFSME Issuance / (Repayment) | C26: £m | D26: -250 | E26: 0 | F26: 0 | H26: * Remaining balance paid down as scheme ends
B27: ILTR Issuance / (Repayment) | C27: £m | D27: 1000 | E27: -250 | F27: 0
B28: Sale and Repurchase Agreement Growth Rate | C28: % | D28: 0 | E28: 0 | F28: 0
B30: Retail Deposit Spread | C30: % | D30: 0 | E30: 0 | F30: 0
B31: Short-term borrowing spread | C31: % | D31: 0.006 | E31: 0.006 | F31: 0.006
B32: Covered bond spread | C32: % | D32: 0.006 | E32: 0.006 | F32: 0.006
B33: Corporate bond rate | C33: % | D33: 0.0525 | E33: 0.065 | F33: 0.065
B34: Repo Spread | C34: % | D34: 0.0047 | E34: 0.0047 | F34: 0.0047
B35: ILTR Spread | C35: % | D35: 0.0015 | E35: 0.0015 | F35: 0.0015
B37: Asset yield / NII assumptions
B39: Mortgage asset spread | C39: % | D39: 0.025 | E39: 0.025 | F39: 0.025
B40: Mortgage asset yield | C40: % | D40: =D9+0.025 -> 0.0663 | E40: =E9+0.025 -> 0.0727 | F40: =F9+0.025 -> 0.0675
B41: Commercial asset spread | C41: % | D41: 0.06 | E41: 0.06 | F41: 0.06
B42: Commercial asset yield | C42: % | D42: =D41+D9 -> 0.1013 | E42: =E41+E9 -> 0.1077 | F42: =F41+F9 -> 0.1025
B43: Cash/reserves spread | C43: % | D43: -0.001 | E43: -0.001 | F43: -0.001
B44: Investment securities spread | C44: % | D44: 0.01 | E44: 0.01 | F44: 0.01
B46: Credit Performance Assumptions
B48: Mortgage cost of risk | C48: bps | D48: 10 | E48: 10 | F48: 10
B49: Commercial cost of risk | C49: bps | D49: 90 | E49: 90 | F49: 90
B51: Depreciation, PP&E and Amortization
B53: Useful life of PP&E | C53: years | D53: 5 | E53: 5 | F53: 5
B54: Capital Expenditure Growth Rate | C54: % | D54: 0.03 | E54: 0.03 | F54: 0.03
B55: Impairment of Goodwill | C55: £m | D55: 0 | E55: 0 | F55: 0
B57: Operating Schedule Assumptions
B59: Lease income and cost growth rate | C59: % | D59: 0.03 | E59: 0.03 | F59: 0.03
B60: Other income growth rate | C60: % | D60: 0 | E60: 0 | F60: 0
B62: Headcount growth | C62: % | D62: 0.015 | E62: 0.015 | F62: 0.015
B63: Wage Inflation | C63: % | D63: 0.02 | E63: 0.02 | F63: 0.02
B65: Other P&L/Tax Assumptions
B67: Liability provisions | C67: £m | D67: 0 | E67: 0 | F67: 0
B68: Fair value movements | C68: £m | D68: 0 | E68: 0 | F68: 0
B69: Effective Tax Rate | C69: % | D69: 0.275 | E69: 0.275 | F69: 0.275
B71: RWA/Capital Assumptions
B73: Mortgage RWA | C73: % | D73: 0.35
B74: Commercial RWA | C74: % | D74: 0.9
B75: Operational RWA growth | C75: % | D75: 0.05
B76: CET1 requirement | C76: % | D76: 0.091
B78: Equity
B80: Dividend payout ratio | C80: % | D80: 0.4
B81: Share buybacks | C81: £m | D81: 60 | E81: 75 | F81: 75

Sheet Model
B2: =Cover!$B$2 -> Paragon Bank
B3: Financial Statements - Income Statement
C7: Units / £m | E7: 2024 | F7: 2025 | G7: =F7+1 -> 2026 | H7: =G7+1 -> 2027 | I7: =H7+1 -> 2028
B9: Interest Receivable | E9: 1314.7 | F9: 1249 | G9: =G215 -> 1311.3767 | H9: =H215 -> 1535.5872 | I9: =I215 -> 1457.6103
B10: Interest Payable | E10: -831.5 | F10: -746.7 | G10: =-G245 -> -771.3949 | H10: =-H245 -> -932.95911 | I10: =-I245 -> -842.38931
B11: Net Interest Income | E11: =SUM(E9:E10) -> 483.2 | F11: =SUM(F9:F10) -> 502.3 | G11: =SUM(G9:G10) -> 539.9818 | H11: =SUM(H9:H10) -> 602.62808 | I11: =SUM(I9:I10) -> 615.22098
B13: Other leasing income | E13: 30.4 | F13: 31.7 | G13: =G401 -> 32.651 | H13: =H401 -> 33.63053 | I13: =I401 -> 34.639446
B14: Related costs | E14: -24.2 | F14: -25.6 | G14: =G402 -> -26.368 | H14: =H402 -> -27.15904 | I14: =I402 -> -27.973811
B15: Net operating lease income | E15: =SUM(E13:E14) -> 6.2 | F15: =SUM(F13:F14) -> 6.1 | G15: =SUM(G13:G14) -> 6.283 | H15: =SUM(H13:H14) -> 6.47149 | I15: =SUM(I13:I14) -> 6.6656347
B16: Other income | E16: 7 | F16: 6.7 | G16: =G404 -> 6.7 | H16: =H404 -> 6.7 | I16: =I404 -> 6.7
B17: Other operating income | E17: =SUM(E15:E16) -> 13.2 | F17: =SUM(F15:F16) -> 12.8 | G17: =SUM(G15:G16) -> 12.983 | H17: =SUM(H15:H16) -> 13.17149 | I17: =SUM(I15:I16) -> 13.365635
B19: Total Operating Income | E19: =E11+E17 -> 496.4 | F19: =F11+F17 -> 515.1 | G19: =G11+G17 -> 552.9648 | H19: =H11+H17 -> 615.79957 | I19: =I11+I17 -> 628.58661
B21: Operating expenses | E21: -179.2 | F21: -179.3 | G21: =-G415 -> -200.86851 | H21: =-H415 -> -213.8555 | I21: =-I415 -> -227.24246
B22: Provisions for credit losses | E22: -24.5 | F22: -41.9 | G22: =-G318 -> -37.051584 | H22: =-H318 -> -39.173575 | I22: =-I318 -> -41.555655
B23: Provisions for liabilties | E23: 0 | F23: -25.5 | G23: =Assumptions!D67 -> 0 | H23: =Assumptions!E67 -> 0 | I23: =Assumptions!F67 -> 0
B24: Operating profit before fair value items | E24: =E19+SUM(E21:E23) -> 292.7 | F24: =F19+SUM(F21:F23) -> 268.4 | G24: =G19+SUM(G21:G23) -> 315.04471 | H24: =H19+SUM(H21:H23) -> 362.7705 | I24: =I19+SUM(I21:I23) -> 359.7885
B25: Fair value net (losses) | E25: -38.9 | F25: -11.9 | G25: =Assumptions!D68 -> 0 | H25: =Assumptions!E68 -> 0 | I25: =Assumptions!F68 -> 0
B26: Operating Profit on ordinary activities before taxation | E26: =SUM(E24:E25) -> 253.8 | F26: =SUM(F24:F25) -> 256.5 | G26: =SUM(G24:G25) -> 315.04471 | H26: =SUM(H24:H25) -> 362.7705 | I26: =SUM(I24:I25) -> 359.7885
B27: Tax charge on profit on ordinary activities | E27: -67.8 | F27: -76.2 | G27: =G26*-Assumptions!D69 -> -86.637295 | H27: =H26*-Assumptions!E69 -> -99.761887 | I27: =I26*-Assumptions!F69 -> -98.941836
B28: Profit on ordinary activities after taxation | E28: =SUM(E26:E27) -> 186 | F28: =SUM(F26:F27) -> 180.3 | G28: =SUM(G26:G27) -> 228.40741 | H28: =SUM(H26:H27) -> 263.00861 | I28: =SUM(I26:I27) -> 260.84666
B31: Earning per share | C31: Units / pence
B32: - Basic | E32: 88.5 | F32: 91.2
B33: - Diluted | E33: 85.2 | F33: 87.9
B36: Margin/Ratios
B38: Revenue Growth | C38: % | F38: =(F9-E9)/E9 -> -0.049973378 | G38: =(G9-F9)/F9 -> 0.049941311 | H38: =(H9-G9)/G9 -> 0.17097337 | I38: =(I9-H9)/H9 -> -0.050779867
B39: Cost-to-income ratio | C39: % | E39: =ABS(E21)/E19 -> 0.36099919 | F39: =ABS(F21)/F19 -> 0.34808775 | G39: =ABS(G21)/G19 -> 0.36325732 | H39: =ABS(H21)/H19 -> 0.34728101 | I39: =ABS(I21)/I19 -> 0.36151336
B40: Pre-provision operating margin | C40: % | E40: =E24/E19 -> 0.58964545 | F40: =F24/F19 -> 0.52106387 | G40: =G24/G19 -> 0.56973736 | H40: =H24/H19 -> 0.58910482 | I40: =I24/I19 -> 0.57237697
B47: =Cover!$B$2 -> Paragon Bank
B48: Financial Statements - Balance Sheet
C52: Units / £m | E52: 2024 | F52: 2025 | G52: =F52+1 -> 2026 | H52: =G52+1 -> 2027 | I52: =H52+1 -> 2028
B53: Assets
B54: Cash - central bank | E54: 2315.5 | F54: 2175.7 | G54: =G88-SUM(G55:G63) -> 3019.5961 | H54: =H88-SUM(H55:H63) -> 2251.6373 | I54: =I88-SUM(I55:I63) -> 1975.6534
B55: Cash - retail bank | E55: 209.9 | F55: 213.8 | G55: =F55 -> 213.8 | H55: =G55 -> 213.8 | I55: =H55 -> 213.8
B56: Investment securities | E56: 427.4 | F56: 626.2 | G56: =F56 -> 626.2 | H56: =G56 -> 626.2 | I56: =H56 -> 626.2
B57: Loans to customers | E57: 15630.3 | F57: 16335.9 | G57: =G123 -> 16999.808 | H57: =H123 -> 17760.305 | I57: =I123 -> 18622.815
B58: Derivative financial assets | E58: 391.8 | F58: 275.4 | G58: =F58 -> 275.4 | H58: =G58 -> 275.4 | I58: =H58 -> 275.4
B59: Sundry assets | E59: 20.7 | F59: 24.2 | G59: =F59*(1+G38) -> 25.40858 | H59: =G59*(1+H38) -> 29.75277 | I59: =H59*(1+I38) -> 28.241929
B60: Current tax assets | E60: 9.7 | F60: 6.2 | G60: =F60 -> 6.2 | H60: =G60 -> 6.2 | I60: =H60 -> 6.2
B61: Retirement benefit obligations | E61: 22.2 | F61: 23.5 | G61: =F61 -> 23.5 | H61: =G61 -> 23.5 | I61: =H61 -> 23.5
B62: Property, plant and equipment | E62: 71 | F62: 77 | G62: =G362 -> 81.5896 | H62: =H362 -> 81.760088 | I62: =I362 -> 77.378891
B63: Intangible assets | E63: 171.5 | F63: 172.1 | G63: =G371 -> 172.6502 | H63: =H371 -> 172.73711 | I63: =I371 -> 172.34682
B64: Total assets | E64: =SUM(E54:E63) -> 19270 | F64: =SUM(F54:F63) -> 19930 | G64: =SUM(G54:G63) -> 21444.152 | H64: =SUM(H54:H63) -> 21441.293 | I64: =SUM(I54:I63) -> 22021.536
B67: Liabilities
B68: Short-term borrowing | E68: 0.4 | F68: 0.5 | G68: =G170 -> 0.5 | H68: =H170 -> 0.5 | I68: =I170 -> 0.5
B69: Retail deposits | E69: 16314.7 | F69: 16270.8 | G69: =G146 -> 16433.508 | H69: =H146 -> 16597.843 | I69: =I146 -> 17095.778
B70: Derivative financial liabilities | E70: 99.7 | F70: 68.2 | G70: =F70 -> 68.2 | H70: =G70 -> 68.2 | I70: =H70 -> 68.2
B71: Asset backed loan notes | E71: 0 | F71: 0 | G71: =F71 -> 0 | H71: =G71 -> 0 | I71: =H71 -> 0
B72: Covered bonds | E72: 0 | F72: 499.2 | G72: =G155 -> 999.2 | H72: =H155 -> 999.2 | I72: =I155 -> 1000
B73: Retail bond issuance | E73: 0 | F73: 0 | G73: =F73 -> 0 | H73: =G73 -> 0 | I73: =H73 -> 0
B74: Corporate bond issuance | E74: 149.9 | F74: 150.1 | G74: =G161 -> 200 | H74: =H161 -> 200 | I74: =I161 -> 200
B75: Central bank facilities | E75: 755 | F75: 950 | G75: =G168 -> 1700 | H75: =H168 -> 1450 | I75: =I168 -> 1450
B76: Sale and repurchase agreements | E76: 100 | F76: 100 | G76: =G169 -> 100 | H76: =H169 -> 100 | I76: =I169 -> 100
B77: Sundry liabilities | E77: 417.4 | F77: 431.6 | G77: =F77 -> 431.6 | H77: =G77 -> 431.6 | I77: =H77 -> 431.6
B78: Provisions | E78: 0 | F78: 25.5 | G78: =Assumptions!D67 -> 0 | H78: =Assumptions!E67 -> 0 | I78: =Assumptions!F67 -> 0
B79: Deferred tax liabilities | E79: 13.4 | F79: 13.9 | G79: =F79 -> 13.9 | H79: =G79 -> 13.9 | I79: =H79 -> 13.9
B80: Total Liabilities | E80: =SUM(E68:E79) -> 17850.5 | F80: =SUM(F68:F79) -> 18509.8 | G80: =SUM(G68:G79) -> 19946.908 | H80: =SUM(H68:H79) -> 19861.243 | I80: =SUM(I68:I79) -> 20359.978
B82: Equity
B83: Called up share capital | E83: 210.6 | F83: 197.4
B84: Reserves | E84: 1274.3 | F84: 1276.6
B85: Own shares | E85: -65.4 | F85: -53.8
B86: Total equity | E86: =SUM(E83:E85) -> 1419.5 | F86: =SUM(F83:F85) -> 1420.2 | G86: =G487 -> 1497.2444 | H86: =H487 -> 1580.0496 | I86: =I487 -> 1661.5576
B88: Total Liabilities and equity | E88: =E80+E86 -> 19270 | F88: =F80+F86 -> 19930 | G88: =G80+G86 -> 21444.152 | H88: =H80+H86 -> 21441.293 | I88: =I80+I86 -> 22021.536
B89: Balance? | G89: =G88-G64 -> 0 | H89: =H88-H64 -> 0 | I89: =I88-I64 -> 0
B94: =Cover!$B$2 -> Paragon Bank
B95: Asset Schedule
C99: Units / £m | E99: 2024 | F99: 2025 | G99: =F99+1 -> 2026 | H99: =G99+1 -> 2027 | I99: =H99+1 -> 2028
B101: Commercial Lending
B103: Opening Balance | F103: =E106 -> 2289.8 | G103: =F106 -> 2464.6 | H103: =G106 -> 2630.695 | I103: =H106 -> 2817.6846
B104: Originations | F104: 1186.2 | G104: =F104*(1+$C$128) -> 1275.165 | H104: =G104*(1+$C$128) -> 1370.8024 | I104: =H104*(1+$C$128) -> 1473.6126
B105: Repayments | F105: -1011.4 | G105: =-G103*$C$129 -> -1109.07 | H105: =-H103*$C$129 -> -1183.8127 | I105: =-I103*$C$129 -> -1267.9581
B106: Closing Balances | E106: 2289.8 | F106: 2464.6 | G106: =SUM(G103:G105) -> 2630.695 | H106: =SUM(H103:H105) -> 2817.6846 | I106: =SUM(I103:I105) -> 3023.3391
B108: YoY Growth | C108: % | F108: =(F106-E106)/E106 -> 0.076338545 | G108: =(G106-F106)/F106 -> 0.067392275 | H108: =(H106-G106)/G106 -> 0.071079933 | I108: =(I106-H106)/H106 -> 0.072987044
B109: Average Balance | F109: =AVERAGE(F106,F103) -> 2377.2 | G109: =AVERAGE(G106,G103) -> 2547.6475 | H109: =AVERAGE(H106,H103) -> 2724.1898 | I109: =AVERAGE(I106,I103) -> 2920.5119
B111: Mortgage Lending
B113: Opening Balance | F113: 13415.7 | G113: =F116 -> 13876.4 | H113: =G116 -> 14369.113 | I113: =H116 -> 14942.621
B114: Originations | F114: 1491 | G114: =F114*(1+$C$128) -> 1602.825 | H114: =G114*(1+$C$128) -> 1723.0369 | I114: =H114*(1+$C$128) -> 1852.2646
B115: Repayments | F115: -1030.3 | G115: =-G113*$C$127 -> -1110.112 | H115: =-H113*$C$127 -> -1149.529 | I115: =-I113*$C$127 -> -1195.4097
B116: Closing Balance | E116: 13415.7 | F116: 13876.4 | G116: =SUM(G113:G115) -> 14369.113 | H116: =SUM(H113:H115) -> 14942.621 | I116: =SUM(I113:I115) -> 15599.476
B118: YoY Growth | C118: % | F118: =(F116-E116)/E116 -> 0.034340362 | G118: =(G116-F116)/F116 -> 0.035507264 | H118: =(H116-G116)/G116 -> 0.039912543 | I118: =(I116-H116)/H116 -> 0.043958485
B119: Average Balance | F119: =AVERAGE(F113,F116) -> 13646.05 | G119: =AVERAGE(G113,G116) -> 14122.756 | H119: =AVERAGE(H113,H116) -> 14655.867 | I119: =AVERAGE(I113,I116) -> 15271.048
B121: Total
B122: Average Loan Book | E122: =E119+E109 -> 0 | F122: =F119+F109 -> 16023.25 | G122: =G119+G109 -> 16670.404 | H122: =H119+H109 -> 17380.057 | I122: =I119+I109 -> 18191.56
B123: Closing Loan Book | E123: =E106+E116 -> 15705.5 | F123: =F106+F116 -> 16341 | G123: =G106+G116 -> 16999.808 | H123: =H106+H116 -> 17760.305 | I123: =I106+I116 -> 18622.815
B125: Forecast Assumptions
B126: Mortgage Origination Growth | C126: =Assumptions!D14 -> 0.05
B127: Mortgage Lending | C127: =Assumptions!D16 -> 0.08
B128: Commercial Origination Growth | C128: =Assumptions!D15 -> 0.075
B129: Commercial Lending | C129: =Assumptions!D17 -> 0.45
B135: =Cover!$B$2 -> Paragon Bank
B136: Funding Schedule
C140: Units / £m | E140: 2024 | F140: 2025 | G140: =F140+1 -> 2026 | H140: =G140+1 -> 2027 | I140: =H140+1 -> 2028
B142: Retail Deposits
B144: Retail Deposits - Opening Balance | F144: =E146 -> 16314.7 | G144: =F146 -> 16270.8 | H144: =G146 -> 16433.508 | I144: =H146 -> 16597.843
B145: Deposit Growth / (Closing) | F145: =F146-F144 -> -43.9 | G145: =G146-G144 -> 162.708 | H145: =H146-H144 -> 164.33508 | I145: =I146-I144 -> 497.93529
B146: Closing Retail Deposits | E146: =E69 -> 16314.7 | F146: =F69 -> 16270.8 | G146: =F146*(1+G184) -> 16433.508 | H146: =G146*(1+H184) -> 16597.843 | I146: =H146*(1+I184) -> 17095.778
B147: Average Retail Deposits | F147: =AVERAGE(F144,F146) -> 16292.75 | G147: =AVERAGE(G144,G146) -> 16352.154 | H147: =AVERAGE(H144,H146) -> 16515.676 | I147: =AVERAGE(I144,I146) -> 16846.811
B150: Bond Schedules
B152: Covered Bonds - Opening Balance | F152: =E155 -> 0 | G152: =F155 -> 499.2 | H152: =G155 -> 999.2 | I152: =H155 -> 999.2
B153: Issuance | E153: 0 | F153: =499.2 -> 499.2 | G153: =Assumptions!D22 -> 500 | H153: =Assumptions!E22 -> 0 | I153: =Assumptions!F22 -> 500
B154: Repayment / (Maturity) | E154: 0 | F154: 0 | G154: =-Assumptions!D23 -> 0 | H154: =-Assumptions!E23 -> 0 | I154: =-Assumptions!F23 -> -499.2
...
