Workbook

Sheet Cover
B2: Solid State PLC
B4: Modelled by Peter Hopkinson
B5: =DATE(2026, 10, 14) -> 46309

Sheet Assumptions
B2: =Cover!$B$2 -> Solid State PLC
B3: Assumptions | L3: ="Currently Running: "&CHOOSE(Assumptions!$B$10,Assumptions!$F$15,Assumptions!$F$16,Assumptions!$F$17)&"Scenario" -> Currently Running: Upside Scenario
F5: Fiscal Years Ending December 31
F6: 2025 | G6: =F6+1 -> 2026 | H6: =G6+1 -> 2027 | I6: =H6+1 -> 2028 | J6: =I6+1 -> 2029 | K6: =J6+1 -> 2030 | L6: =K6+1 -> 2031
B7: (£m in millions) | F7: H = Historical | L7: F = Forecast
B9: Scenario Selector:
B10: 2
B12: Macro Assumptions
B14: Inflation | F14: Selected | H14: =CHOOSE($B$10,H15,H16,H17) -> 0.03 | I14: =CHOOSE($B$10,I15,I16,I17) -> 0.03 | J14: =CHOOSE($B$10,J15,J16,J17) -> 0.03 | K14: =CHOOSE($B$10,K15,K16,K17) -> 0.03 | L14: =CHOOSE($B$10,L15,L16,L17) -> 0.03
F15: Base | H15: 0.04 | I15: 0.04 | J15: 0.035 | K15: 0.03 | L15: 0.03
F16: Upside | H16: 0.03 | I16: 0.03 | J16: 0.03 | K16: 0.03 | L16: 0.03
F17: Downside | H17: 0.04 | I17: 0.045 | J17: 0.045 | K17: 0.04 | L17: 0.03
B19: Wage Inflation | F19: Selected | H19: =CHOOSE($B$10,H20,H21,H22) -> 0.03 | I19: =CHOOSE($B$10,I20,I21,I22) -> 0.03 | J19: =CHOOSE($B$10,J20,J21,J22) -> 0.03 | K19: =CHOOSE($B$10,K20,K21,K22) -> 0.03 | L19: =CHOOSE($B$10,L20,L21,L22) -> 0.03
F20: Base | H20: 0.04 | I20: 0.04 | J20: 0.035 | K20: 0.03 | L20: 0.03
F21: Upside | H21: 0.03 | I21: 0.03 | J21: 0.03 | K21: 0.03 | L21: 0.03
F22: Downside | H22: 0.04 | I22: 0.045 | J22: 0.045 | K22: 0.04 | L22: 0.03
B24: Overhead Inflation | F24: Selected | H24: =CHOOSE($B$10,H25,H26,H27) -> 0.03 | I24: =CHOOSE($B$10,I25,I26,I27) -> 0.03 | J24: =CHOOSE($B$10,J25,J26,J27) -> 0.03 | K24: =CHOOSE($B$10,K25,K26,K27) -> 0.03 | L24: =CHOOSE($B$10,L25,L26,L27) -> 0.03
F25: Base | H25: 0.04 | I25: 0.04 | J25: 0.035 | K25: 0.03 | L25: 0.03
F26: Upside | H26: 0.03 | I26: 0.03 | J26: 0.03 | K26: 0.03 | L26: 0.03
F27: Downside | H27: 0.04 | I27: 0.045 | J27: 0.045 | K27: 0.04 | L27: 0.03
B30: Revenue Assumptions
B33: Volume Growth - Communications | F33: Selected | H33: =CHOOSE($B$10,H34,H35,H36) -> 0.03 | I33: =CHOOSE($B$10,I34,I35,I36) -> 0.03 | J33: =CHOOSE($B$10,J34,J35,J36) -> 0.03 | K33: =CHOOSE($B$10,K34,K35,K36) -> 0.03 | L33: =CHOOSE($B$10,L34,L35,L36) -> 0.03
F34: Base | H34: 0.02 | I34: 0.02 | J34: 0.02 | K34: 0.02 | L34: 0.02
F35: Upside | H35: 0.03 | I35: 0.03 | J35: 0.03 | K35: 0.03 | L35: 0.03
F36: Downside | H36: -0.01 | I36: -0.005 | J36: 0 | K36: 0.01 | L36: 0.01
B38: Volume Growth - Power | F38: Selected | H38: =CHOOSE($B$10,H39,H40,H41) -> 0.1 | I38: =CHOOSE($B$10,I39,I40,I41) -> 0.1 | J38: =CHOOSE($B$10,J39,J40,J41) -> 0.09 | K38: =CHOOSE($B$10,K39,K40,K41) -> 0.08 | L38: =CHOOSE($B$10,L39,L40,L41) -> 0.08
F39: Base | H39: 0.08 | I39: 0.08 | J39: 0.08 | K39: 0.075 | L39: 0.075
F40: Upside | H40: 0.1 | I40: 0.1 | J40: 0.09 | K40: 0.08 | L40: 0.08
F41: Downside | H41: 0.03 | I41: 0.03 | J41: 0.03 | K41: 0.03 | L41: 0.03
B43: Volume Growth - Computing | F43: Selected | H43: =CHOOSE($B$10,H44,H45,H46) -> 0.04 | I43: =CHOOSE($B$10,I44,I45,I46) -> 0.04 | J43: =CHOOSE($B$10,J44,J45,J46) -> 0.035 | K43: =CHOOSE($B$10,K44,K45,K46) -> 0.035 | L43: =CHOOSE($B$10,L44,L45,L46) -> 0.04
F44: Base | H44: 0.03 | I44: 0.03 | J44: 0.03 | K44: 0.03 | L44: 0.03
F45: Upside | H45: 0.04 | I45: 0.04 | J45: 0.035 | K45: 0.035 | L45: 0.04
F46: Downside | H46: -0.01 | I46: -0.005 | J46: 0 | K46: 0.01 | L46: 0.01
B48: Volume Growth - Electronics | F48: Selected | H48: =CHOOSE($B$10,H49,H50,H51) -> 0.09 | I48: =CHOOSE($B$10,I49,I50,I51) -> 0.08 | J48: =CHOOSE($B$10,J49,J50,J51) -> 0.075 | K48: =CHOOSE($B$10,K49,K50,K51) -> 0.07 | L48: =CHOOSE($B$10,L49,L50,L51) -> 0.065
F49: Base | H49: 0.06 | I49: 0.06 | J49: 0.055 | K49: 0.05 | L49: 0.05
F50: Upside | H50: 0.09 | I50: 0.08 | J50: 0.075 | K50: 0.07 | L50: 0.065
F51: Downside | H51: 0.02 | I51: 0.02 | J51: 0.02 | K51: 0.02 | L51: 0.02

Sheet Model
B3: =Cover!$B$2 -> Solid State PLC
B4: Financial Statements - Income Statement | L4: ="Currently Running: "&CHOOSE(Assumptions!$B$10,Assumptions!$F$15,Assumptions!$F$16,Assumptions!$F$17)&"Scenario" -> Currently Running: Upside Scenario
F6: Fiscal Years Ending December 31
F7: 2025 | G7: 2026 | H7: =G7+1 -> 2027 | I7: =H7+1 -> 2028 | J7: =I7+1 -> 2029 | K7: =J7+1 -> 2030 | L7: =K7+1 -> 2031
B8: (£ in 000s) | F8: H = Historical | L8: F = Forecast
B10: Revenue | F10: 125064 | G10: 154144 | H10: =H231 -> 152272.39 | I10: =I231 -> 158508.23 | J10: =J231 -> 173337.27 | K10: =K231 -> 188771.53 | L10: =L231 -> 205330.42
B11: Cost of Sales | F11: -85737 | G11: -102528 | H11: =-H293 -> -93965.271 | I11: =-I293 -> -103045.85 | J11: =-J293 -> -112542.75 | K11: =-K293 -> -122449.69 | L11: =-L293 -> -133046.03
B12: Gross profit | F12: =SUM(F10:F11) -> 39327 | G12: =SUM(G10:G11) -> 51616 | H12: =SUM(H10:H11) -> 58307.121 | I12: =SUM(I10:I11) -> 55462.386 | J12: =SUM(J10:J11) -> 60794.525 | K12: =SUM(K10:K11) -> 66321.841 | L12: =SUM(L10:L11) -> 72284.384
B13: Gross profit margin | F13: =F12/F10 -> 0.314455 | G13: =G12/G10 -> 0.33485572 | H13: =H12/H10 -> 0.38291328 | I13: =I12/I10 -> 0.34990224 | J13: =J12/J10 -> 0.35072967 | K13: =K12/K10 -> 0.35133391 | L13: =L12/L10 -> 0.35203934
B15: Sales, general and administrative expenses | F15: -37993 | G15: -44669 | H15: =-H303 -> -46009.07 | I15: =-I303 -> -49135.957 | J15: =-J303 -> -54871.318 | K15: =-K303 -> -61046.631 | L15: =-L303 -> -67842.079
B16: EBIT | F16: =SUM(F15:F15)+F12 -> 1334 | G16: =SUM(G15:G15)+G12 -> 6947 | H16: =SUM(H15:H15)+H12 -> 12298.051 | I16: =SUM(I15:I15)+I12 -> 6326.4293 | J16: =SUM(J15:J15)+J12 -> 5923.2071 | K16: =SUM(K15:K15)+K12 -> 5275.21 | L16: =SUM(L15:L15)+L12 -> 4442.3052
B17: EBIT Margin | F17: =F16/F10 -> 0.010666539 | G17: =G16/G10 -> 0.045068248 | H17: =H16/H10 -> 0.0807635 | I17: =I16/I10 -> 0.039912307 | J17: =J16/J10 -> 0.034171572 | K17: =K16/K10 -> 0.027944945 | L17: =L16/L10 -> 0.021634911
B19: Depreciation of PP&E | H19: =-H428 -> -780.05877 | I19: =-I428 -> -1075.3004 | J19: =-J428 -> -1390.5536 | K19: =-K428 -> -1734.557 | L19: =-L428 -> -2108.9538
B20: Depreciation of ROU assets | H20: =-H373 -> -1262.6 | I20: =-I373 -> -1612.6 | J20: =-J373 -> -2012.6 | K20: =-K373 -> -2412.6 | L20: =-L373 -> -2812.6
B21: Amortisation | H21: =-H452 -> -1714.4724 | I21: =-I452 -> -2025.253 | J21: =-J452 -> -2357.0985 | K21: =-K452 -> -2719.2073 | L21: =-L452 -> -3113.3093
B22: Depreciation and Amortization | H22: =SUM(H19:H21) -> -3757.1312 | I22: =SUM(I19:I21) -> -4713.1534 | J22: =SUM(J19:J21) -> -5760.2521 | K22: =SUM(K19:K21) -> -6866.3643 | L22: =SUM(L19:L21) -> -8034.8631
B23: EBITDA | F23: =F16-F22 -> 1334 | G23: =G16-G22 -> 6947 | H23: =H16-H22 -> 16055.183 | I23: =I16-I22 -> 11039.583 | J23: =J16-J22 -> 11683.459 | K23: =K16-K22 -> 12141.574 | L23: =L16-L22 -> 12477.168
B24: EBITDA Margin | F24: =F23/F10 -> 0.010666539 | G24: =G23/G10 -> 0.045068248 | H24: =H23/H10 -> 0.10543725 | I24: =I23/I10 -> 0.069646746 | J24: =J23/J10 -> 0.06740304 | K24: =K23/K10 -> 0.064318884 | L24: =L23/L10 -> 0.060766293
B26: Finance expense | F26: -1014 | G26: -1102 | H26: =H513-H507+H387 -> -1195.938 | I26: =I513-I507+I387 -> -467.06639 | J26: =J513-J507+J387 -> -530.69604 | K26: =K513-K507+K387 -> -599.46854 | L26: =L513-L507+L387 -> -667.64124
B27: Net finance costs | F27: =SUM(F26:F26) -> -1014 | G27: =SUM(G26:G26) -> -1102 | H27: =SUM(H26:H26) -> -1195.938 | I27: =SUM(I26:I26) -> -467.06639 | J27: =SUM(J26:J26) -> -530.69604 | K27: =SUM(K26:K26) -> -599.46854 | L27: =SUM(L26:L26) -> -667.64124
B29: Profit before tax | F29: =F16+F27 -> 320 | G29: =G16+G27 -> 5845 | H29: =H16+H27 -> 11102.113 | I29: =I16+I27 -> 5859.363 | J29: =J16+J27 -> 5392.511 | K29: =K16+K27 -> 4675.7414 | L29: =L16+L27 -> 3774.664
B31: Tax (expense)/credit | F31: 192 | G31: -1757 | H31: =-H537 -> -3330.634 | I31: =-I537 -> -1757.8089 | J31: =-J537 -> -1617.7533 | K31: =-K537 -> -1402.7224 | L31: =-L537 -> -1132.3992
B32: Net Profit | F32: =F29+F31 -> 512 | G32: =G29+G31 -> 4088 | H32: =H29+H31 -> 7771.4793 | I32: =I29+I31 -> 4101.5541 | J32: =J29+J31 -> 3774.7577 | K32: =K29+K31 -> 3273.019 | L32: =L29+L31 -> 2642.2648
B33: Net Profit Margin | F33: =F32/F10 -> 0.0040939039 | G33: =G32/G10 -> 0.026520656 | H33: =H32/H10 -> 0.051036693 | I33: =I32/I10 -> 0.025875968 | J33: =J32/J10 -> 0.021776953 | K33: =K32/K10 -> 0.01733852 | L33: =L32/L10 -> 0.012868355
B35: Earning per share
B36: - Basic | D36: pence per share | F36: 0.9 | G36: 7.2 | H36: =(H32*1000/$D$38)*100 -> 13.615065 | I36: =(I32*1000/$D$38)*100 -> 7.1856238 | J36: =(J32*1000/$D$38)*100 -> 6.6131004 | K36: =(K32*1000/$D$38)*100 -> 5.7340907 | L36: =(L32*1000/$D$38)*100 -> 4.6290554
B38: Shares Trading | D38: 57080000
B42: =Cover!$B$2 -> Solid State PLC
B43: Financial Statements - Balance Sheet | L43: ="Currently Running: "&CHOOSE(Assumptions!$B$10,Assumptions!$F$15,Assumptions!$F$16,Assumptions!$F$17)&"Scenario" -> Currently Running: Upside Scenario
F45: Fiscal Years Ending December 31
F46: 2025 | G46: 2026 | H46: =G46+1 -> 2027 | I46: =H46+1 -> 2028 | J46: =I46+1 -> 2029 | K46: =J46+1 -> 2030 | L46: =K46+1 -> 2031
B47: (£ in 000s) | F47: H = Historical | L47: F = Forecast
B49: Assets
B51: Inventories | F51: 28239 | G51: 30502 | H51: =H324 -> 27954.595 | I51: =I324 -> 30656.06 | J51: =J324 -> 33481.38 | K51: =K324 -> 36428.687 | L51: =L324 -> 39581.091
B52: Trade and other receivables | F52: 21616 | G52: 20157 | H52: =H323 -> 19912.255 | I52: =I323 -> 20727.699 | J52: =J323 -> 22666.853 | K52: =K323 -> 24685.15 | L52: =L323 -> 26850.511
B53: Corporation tax asset | F53: 986 | G53: 2392 | H53: =IF(H547>0, H547, 0) -> 0 | I53: =IF(I547>0, I547, 0) -> 0 | J53: =IF(J547>0, J547, 0) -> 0 | K53: =IF(K547>0, K547, 0) -> 0 | L53: =IF(L547>0, L547, 0) -> 0
B54: Cash and cash equivalents | F54: 3513 | G54: 6568 | H54: =H132 -> 3897.1818 | I54: =I132 -> 3956.7221 | J54: =J132 -> 3654.4073 | K54: =K132 -> 3641.7662 | L54: =L132 -> 3785.1186
B55: Current Assets | F55: =SUM(F51:F54) -> 54354 | G55: =SUM(G51:G54) -> 59619 | H55: =SUM(H51:H54) -> 51764.031 | I55: =SUM(I51:I54) -> 55340.481 | J55: =SUM(J51:J54) -> 59802.64 | K55: =SUM(K51:K54) -> 64755.603 | L55: =SUM(L51:L54) -> 70216.721
B56: PP&E, gross
B57: (-) Accumulated depreciation
B58: PP&E, net | F58: 5487 | G58: 6354 | H58: =H435 -> 8467.1167 | I58: =I435 -> 10403.473 | J58: =J435 -> 12306.327 | K58: =K435 -> 14158.429 | L58: =L435 -> 15950.754
B59: Intangible assets | F59: 36968 | G59: 34643 | H59: =H462 -> 34451.252 | I59: =I462 -> 34011.081 | J59: =J462 -> 33387.355 | K59: =K462 -> 32555.863 | L59: =L462 -> 31495.858
B60: Right-of-use assets | F60: 6075 | G60: 5563 | H60: =H381 -> 5800.4 | I60: =I381 -> 6187.8 | J60: =J381 -> 6175.2 | K60: =K381 -> 5762.6 | L60: =L381 -> 4950
B61: Deferred tax asset | F61: 1458 | G61: 1035 | H61: =IF(H556>0, H556, 0) -> 0 | I61: =IF(I556>0, I556, 0) -> 0 | J61: =IF(J556>0, J556, 0) -> 0 | K61: =IF(K556>0, K556, 0) -> 0 | L61: =IF(L556>0, L556, 0) -> 0
B62: Total Assets | F62: =SUM(F58:F61)+F55 -> 104342 | G62: =SUM(G58:G61)+G55 -> 107214 | H62: =SUM(H55)+SUM(H58:H61) -> 100482.8 | I62: =SUM(I55)+SUM(I58:I61) -> 105942.83 | J62: =SUM(J55)+SUM(J58:J61) -> 111671.52 | K62: =SUM(K55)+SUM(K58:K61) -> 117232.5 | L62: =SUM(L55)+SUM(L58:L61) -> 122613.33
B64: Liabiltiies and Shareholders Equity
B66: Trade and other payables | F66: -17020 | G66: -17007 | H66: =-H326 -> -15586.643 | I66: =-I326 -> -17092.899 | J66: =-J326 -> -18668.213 | K66: =-K326 -> -20311.543 | L66: =-L326 -> -22069.229
B67: Deferred and contingent consideration on acquisitions - current | F67: -181 | G67: -365 | H67: =G67 -> -365 | I67: =H67 -> -365 | J67: =I67 -> -365 | K67: =J67 -> -365 | L67: =K67 -> -365
B68: Contract Liabilities | F68: -5847 | G68: -6278 | H68: =-H327 -> -6201.7729 | I68: =-I327 -> -6455.7472 | J68: =-J327 -> -7059.7065 | K68: =-K327 -> -7688.3153 | L68: =-L327 -> -8362.7281
B69: Corporation tax liabilities | F69: -229 | G69: -145 | H69: =IF(H547<0, H547, 0) -> 0 | I69: =IF(I547<0, I547, 0) -> 0 | J69: =IF(J547<0, J547, 0) -> 0 | K69: =IF(K547<0, K547, 0) -> 0 | L69: =IF(L547<0, L547, 0) -> 0
B70: Lease liabilities | F70: -1402 | G70: -1222 | H70: =H397 -> -966.2052 | I70: =I397 -> -904.17751 | J70: =J397 -> -838.42816 | K70: =K397 -> -768.73385 | L70: =L397 -> -768.73385
B71: Provisions | F71: -190 | G71: -1014 | H71: =G71 -> -1014 | I71: =H71 -> -1014 | J71: =I71 -> -1014 | K71: =J71 -> -1014 | L71: =K71 -> -1014
B72: Total Current Liabilities | F72: =SUM(F66:F71) -> -24869 | G72: =SUM(G66:G71) -> -26031 | H72: =SUM(H66:H71) -> -24133.621 | I72: =SUM(I66:I71) -> -25831.824 | J72: =SUM(J66:J71) -> -27945.348 | K72: =SUM(K66:K71) -> -30147.592 | L72: =SUM(L66:L71) -> -32579.691
B73: Borrowings - Current | F73: -8634 | G73: -17
B74: Borrowings - Non Current | F74: -1935 | G74: -10142 | H74: =-H489 -> -549.34195 | I74: =-I489 -> -549.34195 | J74: =-J489 -> -549.34195 | K74: =-K489 -> -549.34195 | L74: =-L489 -> -549.34195
B75: Total Debt | F75: =SUM(F73,F74) -> -10569 | G75: =SUM(G73,G74) -> -10159 | H75: =SUM(H73,H74) -> -549.34195 | I75: =SUM(I73,I74) -> -549.34195 | J75: =SUM(J73,J74) -> -549.34195 | K75: =SUM(K73,K74) -> -549.34195 | L75: =SUM(L73,L74) -> -549.34195
B76: Deferred and contingent consideration on acquisitions - non current | F76: -161 | G76: -270 | H76: =G76 -> -270 | I76: =H76 -> -270 | J76: =I76 -> -270 | K76: =J76 -> -270 | L76: =K76 -> -270
B77: Provisions | F77: -1098 | G77: -985 | H77: =G77 -> -985 | I77: =H77 -> -985 | J77: =I77 -> -985 | K77: =J77 -> -985 | L77: =K77 -> -985
B78: Deferrred tax liabilities | F78: -1548 | G78: -1784 | H78: =IF(H556<0, H556, 0) -> -749 | I78: =IF(I556<0, I556, 0) -> -749 | J78: =IF(J556<0, J556, 0) -> -749 | K78: =IF(K556<0, K556, 0) -> -749 | L78: =IF(L556<0, L556, 0) -> -749
B79: Lease liabilities | F79: -4601 | G79: -4671 | H79: =H398 -> -5430.3748 | I79: =I398 -> -6526.1973 | J79: =J398 -> -7687.7691 | K79: =K398 -> -8919.0353 | L79: =L398 -> -10150.301
B80: Total liabilities | F80: =SUM(F76:F79)+F72+F75 -> -42846 | G80: =SUM(G76:G79)+G72+G75 -> -43900 | H80: =SUM(H76:H79)+H72+H75 -> -32117.338 | I80: =SUM(I76:I79)+I72+I75 -> -34911.363 | J80: =SUM(J76:J79)+J72+J75 -> -38186.459 | K80: =SUM(K76:K79)+K72+K75 -> -41619.969 | L80: =SUM(L76:L79)+L72+L75 -> -45283.334
B81: Share capital | F81: 2854 | G81: 2854 | H81: =G81 -> 2854 | I81: =H81 -> 2854 | J81: =I81 -> 2854 | K81: =J81 -> 2854 | L81: =K81 -> 2854
B82: Share premium reserves | F82: 28300 | G82: 28300 | H82: =G82 -> 28300 | I82: =H82 -> 28300 | J82: =I82 -> 28300 | K82: =J82 -> 28300 | L82: =K82 -> 28300
B83: Exchange reserves | F83: -64 | G83: -64 | H83: =G83 -> -64 | I83: =H83 -> -64 | J83: =I83 -> -64 | K83: =J83 -> -64 | L83: =K83 -> -64
B84: Foreign exchange reserves | F84: -2203 | G84: -2876 | H84: =G84 -> -2876 | I84: =H84 -> -2876 | J84: =I84 -> -2876 | K84: =J84 -> -2876 | L84: =K84 -> -2876
B85: Shares held in treasury | F85: -538 | G85: -500 | H85: =G85 -> -500 | I85: =H85 -> -500 | J85: =I85 -> -500 | K85: =J85 -> -500 | L85: =K85 -> -500
B86: Retained earnings | F86: 33147 | G86: 35600 | H86: =H581 -> 40651.462 | I86: =I581 -> 43317.472 | J86: =J581 -> 45771.064 | K86: =K581 -> 47898.527 | L86: =L581 -> 49615.999
B87: Total Liabilities and Equity | F87: =SUM(F81:F86)-F80 -> 104342 | G87: =SUM(G81:G86)-G80 -> 107214 | H87: =SUM(H81:H86)-H80 -> 100482.8 | I87: =SUM(I81:I86)-I80 -> 105942.83 | J87: =SUM(J81:J86)-J80 -> 111671.52 | K87: =SUM(K81:K86)-K80 -> 117232.5 | L87: =SUM(L81:L86)-L80 -> 122613.33
B88: Balance? | F88: =F62-F87 -> 0 | G88: =G62-G87 -> 0 | H88: =H62-H87 -> 0 | I88: =I62-I87 -> 0 | J88: =J62-J87 -> 0 | K88: =K62-K87 -> 0 | L88: =L62-L87 -> 0
B90: * Provisions and deferred consideration on acquisitions assumed to remain constant, based on materiality basis
B95: =Cover!$B$2 -> Solid State PLC
B96: Financial Statements - Cash Flow Statement | L96: ="Currently Running: "&CHOOSE(Assumptions!$B$10,Assumptions!$F$15,Assumptions!$F$16,Assumptions!$F$17)&"Scenario" -> Currently Running: Upside Scenario
F98: Fiscal Years Ending December 31
F99: 2025 | G99: =F99+1 -> 2026 | H99: =G99+1 -> 2027 | I99: =H99+1 -> 2028 | J99: =I99+1 -> 2029 | K99: =J99+1 -> 2030 | L99: =K99+1 -> 2031
B100: (£m in millions) | F100: H = Historical | L100: F = Forecast
B102: Operating Activities
B104: Net Profit | H104: =H32 -> 7771.4793 | I104: =I32 -> 4101.5541 | J104: =J32 -> 3774.7577 | K104: =K32 -> 3273.019 | L104: =L32 -> 2642.2648
B105: PP&E depreciation | H105: =-H19 -> 780.05877 | I105: =-I19 -> 1075.3004 | J105: =-J19 -> 1390.5536 | K105: =-K19 -> 1734.557 | L105: =-L19 -> 2108.9538
B106: ROU depreciation | H106: =-H20 -> 1262.6 | I106: =-I20 -> 1612.6 | J106: =-J20 -> 2012.6 | K106: =-K20 -> 2412.6 | L106: =-L20 -> 2812.6
B107: Amortization of Intangible Assets | H107: =-H21 -> 1714.4724 | I107: =-I21 -> 2025.253 | J107: =-J21 -> 2357.0985 | K107: =-K21 -> 2719.2073 | L107: =-L21 -> 3113.3093
B108: Income Statement Adjustments | H108: =SUM(H105:H107) -> 3757.1312 | I108: =SUM(I105:I107) -> 4713.1534 | J108: =SUM(J105:J107) -> 5760.2521 | K108: =SUM(K105:K107) -> 6866.3643 | L108: =SUM(L105:L107) -> 8034.8631
B109: (Increase) / decrease in working capital | H109: =H330 -> 1295.5665 | I109: =I330 -> -1756.6792 | J109: =J330 -> -2585.2011 | K109: =K330 -> -2693.6652 | L109: =L330 -> -2885.6669
B110: Add back total tax expense | H110: =-H31 -> 3330.634 | I110: =-I31 -> 1757.8089 | J110: =-J31 -> 1617.7533 | K110: =-K31 -> 1402.7224 | L110: =-L31 -> 1132.3992
B111: Minus cash paid | H111: =-H540 -> -1083.634 | I111: =-I540 -> -1757.8089 | J111: =-J540 -> -1617.7533 | K111: =-K540 -> -1402.7224 | L111: =-L540 -> -1132.3992
B112: Balance Sheet Adjustments
B113: Cash Flow from Operations | H113: =SUM(H104:H107)+SUM(H109:H111) -> 15071.177 | I113: =SUM(I104:I107)+SUM(I109:I111) -> 7058.0282 | J113: =SUM(J104:J107)+SUM(J109:J111) -> 6949.8088 | K113: =SUM(K104:K107)+SUM(K109:K111) -> 7445.7181 | L113: =SUM(L104:L107)+SUM(L109:L111) -> 7791.461
B115: Investing Activities
B117: Capital expenditure on PP&E | H117: =-H410 -> -2893.1755 | I117: =-I410 -> -3011.6565 | J117: =-J410 -> -3293.4082 | K117: =-K410 -> -3586.6591 | L117: =-L410 -> -3901.2779
B118: Additions to intangibles | H118: =-H413 -> -1522.7239 | I118: =-I413 -> -1585.0823 | J118: =-J413 -> -1733.3727 | K118: =-K413 -> -1887.7153 | L118: =-L413 -> -2053.3042
B119: Cash flow from investing | H119: =SUM(H117:H118) -> -4415.8994 | I119: =SUM(I117:I118) -> -4596.7388 | J119: =SUM(J117:J118) -> -5026.7809 | K119: =SUM(K117:K118) -> -5474.3744 | L119: =SUM(L117:L118) -> -5954.5821
B121: Financing Activities
B123: Borrowing Issuance | H123: =H487 -> 0 | I123: =I487 -> 0 | J123: =J487 -> 0 | K123: =K487 -> 0 | L123: =L487 -> 0
B124: Borrowing Repayments | H124: =H488 -> -9609.658 | I124: =I488 -> 0 | J124: =J488 -> 0 | K124: =K488 -> 0 | L124: =L488 -> 0
B125: Lease principal payments | H125: =-H395 -> -996.42 | I125: =-I395 -> -966.2052 | J125: =-J395 -> -904.17751 | K125: =-K395 -> -838.42816 | L125: =-L395 -> -768.73385
B126: Dividends | H126: =-H572 -> -2720.0178 | I126: =-I572 -> -1435.5439 | J126: =-J572 -> -1321.1652 | K126: =-K572 -> -1145.5566 | L126: =-L572 -> -924.79268
B127: Share buybacks | H127: =H579 -> 0 | I127: =I579 -> 0 | J127: =J579 -> 0 | K127: =K579 -> 0 | L127: =L579 -> 0
B128: Cash flow from financing | H128: =SUM(H123:H127) -> -13326.096 | I128: =SUM(I123:I127) -> -2401.7491 | J128: =SUM(J123:J127) -> -2225.3427 | K128: =SUM(K123:K127) -> -1983.9848 | L128: =SUM(L123:L127) -> -1693.5265
B130: Cash - Beginning of Period | H130: =G54 -> 6568 | I130: =H132 -> 3897.1818 | J130: =I132 -> 3956.7221 | K130: =J132 -> 3654.4073 | L130: =K132 -> 3641.7662
B131: Cash Movement during the year | H131: =H113+H119+H128 -> -2670.8182 | I131: =I113+I119+I128 -> 59.540302 | J131: =J113+J119+J128 -> -302.31486 | K131: =K113+K119+K128 -> -12.641059 | L131: =L113+L119+L128 -> 143.35238
B132: Cash - End of Period | H132: =SUM(H130:H131) -> 3897.1818 | I132: =SUM(I130:I131) -> 3956.7221 | J132: =SUM(J130:J131) -> 3654.4073 | K132: =SUM(K130:K131) -> 3641.7662 | L132: =SUM(L130:L131) -> 3785.1186
...
